Workbook
Name AHV_1: #REF!
Name AHV_2: #REF!
Name AHV_3: #REF!
Name AHV_4: #REF!
Name AHV_5: #REF!
Name AHV_6: #REF!
Name AlterMann: #REF!
Name asdf: #REF!
Name D: #REF!
Name Dossier_End2End_1: #REF!
Name DossierName: #REF!
Name DossierName1: #REF!
Name First_Feamale_1: #REF!
Name First_Feamale_3: #REF!
Name First_Female_2: #REF!
Name First_Female_3: #REF!
Name First_Female_4: #REF!
Name First_Female_5: #REF!
Name FrauAlter: #REF!
Name Kind1Alter: #REF!
Name Kind2Alter: #REF!
Name KlientName: #REF!
Name NameMutter: #REF!
Name NameSohn: #REF!
Name NameTochter: #REF!
Name NameVater: #REF!
Name RandomStart: #REF!
Name s: #REF!
Name SpeedFaktor: '000'!$B$27
Name URL: #REF!
Name URLAVENTIS: #REF!
Name URLDemoAventis: #REF!
Name URLDevAventis: #REF!
Name URLTestAventis: #REF!
Name URLTestrun: #REF!

Sheet 000
A1: StepNumber | B1: Action | C1: TestData | D1: Screenshot | F1: video | G1: =30*1000*SpeedFaktor -> 30000 | H1: 10 | S1: Testresult | T1: 09.12.2024 10:35:06 | U1: 09.12.2024 11:14:33 | V1: Hoch | X1: 22.07.2025 05:11:20 | Y1: Message | Z1: 22.07.2025 09:53:01 | AA1: Message | AB1: 22.07.2025 15:36:51 | AC1: Message | AD1: 22.07.2025 18:44:05 | AE1: Message | AF1: 22.07.2025 19:54:04 | AG1: Message | AH1: 04.02.2025 13:50:39 | AI1: Hoch | AJ1: 28.03.2025 10:25:49 | AK1: Hoch | AL1: 31.03.2025 18:57:12 | AM1: Hoch | AN1: 01.04.2025 00:27:19 | AO1: Hoch | AP1: 01.04.2025 23:50:20 | AQ1: Hoch | AR1: 09.04.2025 | AS1: Hoch | AT1: 09.04.2025 20:54:34 | AU1: Hoch | AV1: 25.06.2025 16:52:40 | AW1: Hoch | AX1: 25.06.2025 19:45:42 | AY1: Hoch | AZ1: 26.06.2025 08:23:51 | BA1: Message 26.06.2025 08:23:51 | BB1: 05.07.2025 02:04:53 | BC1: Message 05.07.2025 02:04:53 | BD1: 22.07.2025 22:30:01 | BE1: Message | BF1: 23.07.2025 08:43:42 | BG1: Message | BH1: 23.07.2025 09:48:50 | BI1: Message | BJ1: 24.07.2025 02:30:17 | BK1: Message | BL1: 24.07.2025 07:10:05 | BM1: Message | BN1: 24.07.2025 15:47:38 | BO1: Message | BP1: 24.07.2025 15:57:20 | BQ1: Message | BR1: 24.07.2025 17:55:15 | BS1: Message | BT1: 24.07.2025 19:37:23 | BU1: Message | BV1: 24.07.2025 23:36:24 | BW1: Message | BX1: 05.08.2025 16:09:15 | BY1: Message | BZ1: 05.08.2025 16:15:04 | CA1: Message | CB1: 05.08.2025 16:22:04 | CC1: Message | CD1: 05.08.2025 16:43:41 | CE1: Message | CF1: 05.08.2025 17:02:04 | CG1: Message | CH1: 05.08.2025 17:20:58 | CI1: Message | CJ1: 09.08.2025 04:54:00 | CK1: Message | CL1: 09.08.2025 14:38:53 | CM1: Message | CN1: 09.08.2025 21:56:15 | CO1: Message | CP1: 18.08.2025 15:31:20 | CQ1: Message | CR1: 20.08.2025 10:02:58 | CS1: Message | CT1: 24.08.2025 15:36:50 | CU1: Message | CV1: 26.08.2025 11:41:22 | CW1: Message | CX1: 26.08.2025 13:36:43 | CY1: Message | CZ1: 26.08.2025 16:55:49 | DA1: Message | DB1: 30.10.2025 03:23:00 | DC1: Message | DD1: 03.11.2025 13:58:05 | DE1: Message
A2: 1 | B2: L00_URLAventis | C2: ='001a'!B59 -> {"url":p.aventisURL} | T2: 3063 | U2: 1257 | V2: =U2/$T2 -> 0.41038198 | X2: 1232 | Z2: 808 | AB2: 812 | AD2: 1260 | AF2: 1167 | AH2: 1292 | AI2: =AH2/$T2 -> 0.42180868 | AJ2: 1857 | AK2: =AJ2/$T2 -> 0.60626836 | AL2: 1313 | AM2: =AL2/$T2 -> 0.42866471 | AN2: 2008 | AO2: =AN2/$T2 -> 0.65556644 | AP2: 1711 | AQ2: =AP2/$T2 -> 0.55860268 | AR2: 1108 | AS2: =AR2/$T2 -> 0.36173686 | AT2: 1035 | AU2: =AT2/$T2 -> 0.33790402 | AV2: 925 | AW2: =AV2/$T2 -> 0.30199151 | AX2: 775 | AY2: =AX2/$T2 -> 0.25301992 | AZ2: 1532 | BB2: 606 | BD2: 1190 | BF2: 826 | BH2: 943 | BJ2: 913 | BL2: 966 | BN2: 680 | BP2: 1429 | BR2: 786 | BT2: 861 | BV2: 826 | BX2: 1630 | BZ2: 1666 | CB2: 1701 | CD2: 1482 | CF2: 1623 | CH2: 1615 | CJ2: 1643 | CL2: 1574 | CN2: 1630 | CP2: 887 | CR2: 876 | CT2: 1644 | CV2: 879 | CX2: 907 | CZ2: 877 | DB2: 857 | DD2: 559
A3: 3 | B3: M01_LoginMSOnline | C3: {"username":"aventis-test-aml@diartis.ch","password":"E7Qr=3cTiz$8Q!","fullname":"Test AmtsleiterIn Aventis","team":"Superuser"} | T3: 7444 | U3: 8520 | V3: =U3/$T3 -> 1.1445459 | X3: 4903 | Z3: 5580 | AB3: 5670 | AD3: 7847 | AF3: 7797 | AH3: 8584 | AI3: =AH3/$T3 -> 1.1531435 | AJ3: 10657 | AK3: =AJ3/$T3 -> 1.4316228 | AL3: 6184 | AM3: =AL3/$T3 -> 0.83073616 | AN3: 9052 | AO3: =AN3/$T3 -> 1.2160129 | AP3: 9966 | AQ3: =AP3/$T3 -> 1.3387963 | AR3: 9882 | AS3: =AR3/$T3 -> 1.3275121 | AT3: 11480 | AU3: =AT3/$T3 -> 1.5421816 | AV3: 4115 | AW3: =AV3/$T3 -> 0.5527942 | AX3: 4455 | AY3: =AX3/$T3 -> 0.59846857 | AZ3: 5668 | BB3: 3456 | BD3: 7938 | BF3: 8216 | BH3: 7025 | BJ3: 6381 | BL3: 4986 | BN3: 6752 | BP3: 7092 | BR3: 5294 | BT3: 5692 | BV3: 6212 | BX3: 5490 | BZ3: 5038 | CB3: 6857 | CD3: 5431 | CF3: 6550 | CH3: 5365 | CJ3: 5553 | CL3: 6093 | CN3: 5638 | CP3: 5456 | CR3: 8101 | CT3: 8444 | CV3: 7435 | CX3: 6390 | CZ3: 7346 | DB3: 8137 | DD3: 6289
A4: 4 | B4: L05_Check_VersionNumber | C4: =E4 -> {"username":"Bern.Sachbearbeiterin@diartis.ch","password":"XXxa22?pdTA66-S@","url":p.AventisURL,"version":"2025.5.275-stable"} | D4: Yes | E4: =F4&G4&H4&I4&J4&K4&L4&M4&N4&O4&P4 -> {"username":"Bern.Sachbearbeiterin@diartis.ch","password":"XXxa22?pdTA66-S@","url":p.AventisURL,"version":"2025.5.275-stable"} | F4: {"username":" | G4: Bern.Sachbearbeiterin@diartis.ch | H4: ","password":" | I4: XXxa22?pdTA66-S@ | J4: ","url": | K4: p.AventisURL | L4: ,"version":" | M4: 2025.5.275-stable | N4: "} | R4: seriell | T4: 447 | U4: 0 | V4: =U4/$T4 -> 0 | X4: 800 | Z4: 999 | AB4: 951 | AD4: 1044 | AF4: 911 | AH4: 0 | AI4: =AH4/$T4 -> 0 | AJ4: 542 | AK4: =AJ4/$T4 -> 1.212528 | AL4: 312 | AM4: =AL4/$T4 -> 0.69798658 | AN4: 317 | AO4: =AN4/$T4 -> 0.70917226 | AP4: 354 | AQ4: =AP4/$T4 -> 0.79194631 | AR4: 369 | AS4: =AR4/$T4 -> 0.82550336 | AT4: 283 | AU4: =AT4/$T4 -> 0.63310962 | AV4: 808 | AW4: =AV4/$T4 -> 1.8076063 | AX4: 1103 | AY4: =AX4/$T4 -> 2.4675615 | AZ4: 908 | BB4: 691 | BD4: 901 | BF4: 1028 | BH4: 1047 | BJ4: 0 | BK4: Error: [31mTimed out 10000ms waiting for [39m[2mexpect([22m[31mlocator[39m[2m).[22mtoHaveText[2m([22m[32mexpected[39m[2m)[22mLocator: locator('div.versions-container.ng-star-inserted').locator('span.version-row')Expected string: [32m"2025.4.[7m48[27m-dev"[39mReceived string: [31m"2025.4.[7m141[27m-dev"[39mCall log:[2m - Expect "soft toHaveText" with timeout 10000ms[22m[2m - waiting for locator('div.versions-container.ng-star-inserted').locator('span.version-row')[22m[2m 12 × locator resolved to <span class="version-row" _ngcontent-ng-c3803718529="">2025.4.141-dev</span>[22m[2m - unexpected value "2025.4.141-dev"[22m Screenshots: C:\Aventis\Aventis_Playwright-\test-results\videos\006_KeyWords_Smoketest_V2-000-000-Microsoft-Edge\test-failed-1.png Videos: C:\Aventis\Aventis_Playwright-\test-results\videos\006_KeyWords_Smoketest_V2-000-000-Microsoft-Edge\video.webm | BL4: 462 | BN4: 868 | BP4: 817 | BR4: 406 | BT4: 664 | BV4: 468 | BX4: 666 | BZ4: 685 | CB4: 702 | CD4: 1155 | CF4: 729 | CH4: 639 | CJ4: 721 | CL4: 719 | CN4: 704 | CP4: 461 | CR4: 662 | CT4: 344 | CV4: 764 | CX4: 625 | CZ4: 595 | DB4: 0 | DC4: Error: [2mexpect([22m[31mlocator[39m[2m).[22mtoHaveText[2m([22m[32mexpected[39m[2m)[22m failedLocator: locator('div.versions-container.ng-star-inserted').locator('span.version-row')Expected: [32m"2025.5.249-dev"[39mTimeout: 10000msError: element(s) not foundCall log:[2m - Expect "soft toHaveText" with timeout 10000ms[22m[2m - waiting for locator('div.versions-container.ng-star-inserted').locator('span.version-row')[22m[2m 10 × locator resolved to <span class="version-row" _ngcontent-ng-c2680178628="">2025.5.275-stable</span>[22m[2m - unexpected value "2025.5.275-stable"[22m Screenshots: C:\Aventis_Playwright\test-results\videos\006_KeyWords_Smoketest_V2-000-000-Microsoft-Edge\test-failed-1.png | DD4: 318
R5: 5 Parallel
C6: Schritt eins und 2 sind eigentlich redundant - ist aber brauchbar so | M6: 2025.5.249-dev | R6: 10 Parallel
R7: 20 Parallel
C8: Versionsnummer muss angepasst werden | R8: 50 Parallel
C9: 2024.4.77.62-dev
C10: 2024.4.77.102-dev
C11: 2024.4.77.271-dev
C12: 2024.6.82.143-dev
C13: 2024.6.82.143-dev | D13: test
C14: 2024.6.83.16-dev | D14: dev
C15: 2024.6.82.143-dev
C16: 2025.1.84.76-dev
C17: 2025.1.85.55-dev
C18: 2025.1.85.63-dev
C19: 2025.1.85.129-dev
C20: 2025.2.87.104-dev
C21: 2025.2.88.113-dev
C22: 2025.3.112-dev
C23: 2025.4.48-dev
C24: 2025.4.141-dev
C25: 2025.4.244-dev
C26: 2025.4.385-stable
A27: SpeedFaktor | B27: 1

Sheet 001x
A1: Step | B1: Keyword | C1: Testdata | D1: Screenshot | E1: done | F1: video | G1: =4*60*1000*SpeedFaktor -> 240000 | H1: 300 | AH1: Testresult | AI1: 09.12.2024 | AK1: Testresult | AL1: 09.12.2024 | AM1: Hoch | AN1: 04.02.2025 | AO1: Hoch | AP1: 04.02.2025 13:50:39 | AQ1: Hoch | AR1: 28.03.2025 10:25:49 | AS1: Hoch | AT1: 31.03.2025 18:57:12 | AU1: Hoch | AV1: 01.04.2025 00:27:19 | AW1: Hoch | AX1: 01.04.2025 23:50:20 | AY1: Hoch | AZ1: 09.04.2025 14:35:45 | BA1: Message 09.04.2025 14:35:45 | BB1: 09.04.2025 20:54:34 | BC1: Hoch | BD1: 25.06.2025 19:45:42 | BE1: Hoch | BF1: 26.06.2025 08:23:51 | BG1: Hoch | BH1: 05.07.2025 02:04:53 | BI1: Hoch | BK1: 22.07.2025 05:11:20 | BL1: Hoch | BM1: 22.07.2025 09:53:01 | BN1: Hoch | BO1: 22.07.2025 15:36:51 | BP1: Hoch | BQ1: 22.07.2025 18:44:05 | BR1: Hoch | BS1: 22.07.2025 19:54:04 | BT1: Hoch | BU1: 22.07.2025 22:30:01 | BV1: Hoch | BW1: 23.07.2025 08:43:42 | BX1: Hoch | BY1: 23.07.2025 09:48:50 | BZ1: Hoch | CA1: 24.07.2025 02:30:17 | CB1: Hoch | CC1: 24.07.2025 15:47:38 | CD1: Hoch | CE1: 24.07.2025 17:55:15 | CF1: Hoch | CG1: 24.07.2025 19:37:23 | CH1: Hoch | CI1: 24.07.2025 23:36:24 | CJ1: Hoch | CK1: 05.08.2025 16:09:15 | CL1: Hoch | CM1: 05.08.2025 16:15:04 | CN1: Hoch | CO1: 05.08.2025 16:22:04 | CP1: Hoch | CQ1: 05.08.2025 16:43:41 | CR1: Hoch | CS1: 05.08.2025 17:02:04 | CT1: Hoch | CU1: 05.08.2025 17:20:58 | CV1: Hoch | CW1: 18.08.2025 15:31:20 | CX1: Hoch | CY1: 20.08.2025 10:02:58 | CZ1: Message | DA1: 24.08.2025 15:36:50 | DB1: Message | DC1: 26.08.2025 11:41:22 | DD1: Message | DE1: 26.08.2025 13:36:43 | DF1: Message | DG1: 26.08.2025 16:55:49 | DH1: Message
A2: 1 | B2: L00_URLAventis | C2: =B58 -> {"url":p.aventisURL} | E2: =F2&G2&H2&I2&J2&K2&L2&M2&N2&O2&P2&Q2&R2&S2&T2&U2&V2&W2&X2 -> {"url":"https://dev.aventis.swiss"} | F2: {"url":" | G2: https://dev.aventis.swiss | H2: "} | AI2: 2535 | AL2: 933 | AM2: =AL2/($AI2) -> 0.36804734 | AN2: 554 | AO2: =AN2/($AI2) -> 0.21854043 | AP2: 770 | AQ2: =AP2/($AI2) -> 0.30374753 | AR2: 382 | AS2: =AR2/($AI2) -> 0.15069034 | AT2: 555 | AU2: =AT2/($AI2) -> 0.21893491 | AV2: 356 | AW2: =AV2/($AI2) -> 0.14043393 | AX2: 355 | AY2: =AX2/($AI2) -> 0.14003945 | AZ2: 424 | BB2: 354 | BC2: =BB2/($AI2) -> 0.13964497 | BD2: 4014 | BE2: =BD2/($AI2) -> 1.583432 | BF2: 4014 | BG2: =BF2/($AI2) -> 1.583432 | BH2: 4011 | BI2: =BH2/($AI2) -> 1.5822485 | BK2: 338 | BL2: =BK2/($AI2) -> 0.13333333 | BM2: 299 | BN2: =BM2/($AI2) -> 0.11794872 | BO2: 331 | BP2: =BO2/($AI2) -> 0.13057199 | BQ2: 406 | BR2: =BQ2/($AI2) -> 0.16015779 | BS2: 356 | BT2: =BS2/($AI2) -> 0.14043393 | BU2: 295 | BV2: =BU2/($AI2) -> 0.11637081 | BW2: 291 | BX2: =BW2/($AI2) -> 0.1147929 | BY2: 367 | BZ2: =BY2/($AI2) -> 0.14477318 | CA2: 444 | CB2: =CA2/($AI2) -> 0.17514793 | CC2: 354 | CD2: =CC2/($AI2) -> 0.13964497 | CE2: 420 | CF2: =CE2/($AI2) -> 0.16568047 | CG2: 366 | CH2: =CG2/($AI2) -> 0.1443787 | CI2: 173 | CJ2: =CI2/($AI2) -> 0.068244576 | CK2: 1013 | CL2: =CK2/($AI2) -> 0.39960552 | CM2: 707 | CN2: =CM2/($AI2) -> 0.27889546 | CO2: 733 | CP2: =CO2/($AI2) -> 0.28915187 | CQ2: 1009 | CR2: =CQ2/($AI2) -> 0.39802761 | CS2: 953 | CT2: =CS2/($AI2) -> 0.37593688 | CU2: 1182 | CV2: =CU2/($AI2) -> 0.46627219 | CW2: 213 | CX2: =CW2/($AI2) -> 0.084023669 | CY2: 403 | DA2: 904 | DC2: 335 | DE2: 369 | DG2: 363
A3: 4 | B3: M01_LoginMSOnline | C3: =E3 -> {"username":"bern.sozialarbeiterin1a@diartis.ch","password":"SMze97-jkSJ59!F.","fullname":"Sozialarbeiterin 1A Bern","team":"Sozialarbeit Bern 1"} | E3: =F3&G3&H3&I3&J3&K3&L3&M3&N3&O3&P3&Q3&R3&S3&T3&U3&V3&W3&X3 -> {"username":"bern.sozialarbeiterin1a@diartis.ch","password":"SMze97-jkSJ59!F.","fullname":"Sozialarbeiterin 1A Bern","team":"Sozialarbeit Bern 1"} | F3: {"username":" | G3: bern.sozialarbeiterin1a@diartis.ch | H3: ","password":" | I3: SMze97-jkSJ59!F. | J3: ","fullname":" | K3: Sozialarbeiterin 1A Bern | L3: ","team":" | M3: Sozialarbeit Bern 1 | N3: "} | AI3: 407 | AJ3: seriell | AL3: 407 | AM3: =AL3/($AI3) -> 1 | AN3: 417 | AO3: =AN3/($AI3) -> 1.02457 | AP3: 412 | AQ3: =AP3/($AI3) -> 1.012285 | AR3: 421 | AS3: =AR3/($AI3) -> 1.034398 | AT3: 403 | AU3: =AT3/($AI3) -> 0.99017199 | AV3: 411 | AW3: =AV3/($AI3) -> 1.009828 | AX3: 1391 | AY3: =AX3/($AI3) -> 3.4176904 | AZ3: 1355 | BB3: 1177 | BC3: =BB3/($AI3) -> 2.8918919 | BD3: 410 | BE3: =BD3/($AI3) -> 1.007371 | BF3: 416 | BG3: =BF3/($AI3) -> 1.022113 | BH3: 404 | BI3: =BH3/($AI3) -> 0.99262899 | BK3: 413 | BL3: =BK3/($AI3) -> 1.014742 | BM3: 403 | BN3: =BM3/($AI3) -> 0.99017199 | BO3: 1161 | BP3: =BO3/($AI3) -> 2.8525799 | BQ3: 1183 | BR3: =BQ3/($AI3) -> 2.9066339 | BS3: 1170 | BT3: =BS3/($AI3) -> 2.8746929 | BU3: 1089 | BV3: =BU3/($AI3) -> 2.6756757 | BW3: 1108 | BX3: =BW3/($AI3) -> 2.7223587 | BY3: 1162 | BZ3: =BY3/($AI3) -> 2.8550369 | CA3: 1253 | CB3: =CA3/($AI3) -> 3.0786241 | CC3: 1022 | CD3: =CC3/($AI3) -> 2.5110565 | CE3: 1168 | CF3: =CE3/($AI3) -> 2.8697789 | CG3: 1042 | CH3: =CG3/($AI3) -> 2.5601966 | CI3: 774 | CJ3: =CI3/($AI3) -> 1.9017199 | CK3: 1476 | CL3: =CK3/($AI3) -> 3.6265356 | CM3: 1335 | CN3: =CM3/($AI3) -> 3.2800983 | CO3: 1310 | CP3: =CO3/($AI3) -> 3.2186732 | CQ3: 1597 | CR3: =CQ3/($AI3) -> 3.9238329 | CS3: 1493 | CT3: =CS3/($AI3) -> 3.6683047 | CU3: 1812 | CV3: =CU3/($AI3) -> 4.4520885 | CW3: 814 | CX3: =CW3/($AI3) -> 2 | CY3: 1180 | DA3: 1383 | DC3: 1128 | DE3: 1072 | DG3: 1124
B4: P01_Person_Search | C4: =E4 -> {"name":p.FamilyName1,"vorname":p.ManFirstName1,"ahvNumber":"","geburtsdatum":""} | E4: =F4&G4&H4&I4&J4&K4&L4&M4&N4&O4&P4&Q4&R4&S4&T4&U4&V4&W4&X4 -> {"name":p.FamilyName1,"vorname":p.ManFirstName1,"ahvNumber":"","geburtsdatum":""} | F4: {"name": | G4: =G$63 -> p.FamilyName1 | H4: ,"vorname": | I4: =H$62 -> p.ManFirstName1 | J4: ,"ahvNumber":"" | L4: ,"geburtsdatum":" | N4: "} | AI4: 6791 | AJ4: 5 Parallel | AL4: 9630 | AM4: =AL4/($AI4) -> 1.4180533 | AN4: 8889 | AO4: =AN4/($AI4) -> 1.3089383 | AP4: 10209 | AQ4: =AP4/($AI4) -> 1.5033132 | AR4: 9507 | AS4: =AR4/($AI4) -> 1.3999411 | AT4: 6454 | AU4: =AT4/($AI4) -> 0.9503755 | AV4: 8318 | AW4: =AV4/($AI4) -> 1.2248564 | AX4: 10072 | AY4: =AX4/($AI4) -> 1.4831394 | AZ4: 10056 | BB4: 9423 | BC4: =BB4/($AI4) -> 1.3875718 | BD4: 6604 | BE4: =BD4/($AI4) -> 0.97246355 | BF4: 10404 | BG4: =BF4/($AI4) -> 1.5320277 | BH4: 4702 | BI4: =BH4/($AI4) -> 0.69238698 | BK4: 7245 | BL4: =BK4/($AI4) -> 1.0668532 | BM4: 6500 | BN4: =BM4/($AI4) -> 0.95714917 | BO4: 7445 | BP4: =BO4/($AI4) -> 1.0963039 | BQ4: 7658 | BR4: =BQ4/($AI4) -> 1.127669 | BS4: 6851 | BT4: =BS4/($AI4) -> 1.0088352 | BU4: 7556 | BV4: =BU4/($AI4) -> 1.1126491 | BW4: 7074 | BX4: =BW4/($AI4) -> 1.0416728 | BY4: 7362 | BZ4: =BY4/($AI4) -> 1.0840819 | CA4: 6882 | CB4: =CA4/($AI4) -> 1.0134001 | CC4: 7465 | CD4: =CC4/($AI4) -> 1.099249 | CE4: 7303 | CF4: =CE4/($AI4) -> 1.0753939 | CG4: 6858 | CH4: =CG4/($AI4) -> 1.009866 | CI4: 5092 | CJ4: =CI4/($AI4) -> 0.74981593 | CK4: 6341 | CL4: =CK4/($AI4) -> 0.93373583 | CM4: 6443 | CN4: =CM4/($AI4) -> 0.94875571 | CO4: 6003 | CP4: =CO4/($AI4) -> 0.88396407 | CQ4: 6485 | CR4: =CQ4/($AI4) -> 0.95494036 | CS4: 10819 | CT4: =CS4/($AI4) -> 1.593138 | CU4: 6713 | CV4: =CU4/($AI4) -> 0.98851421 | CW4: 5703 | CX4: =CW4/($AI4) -> 0.83978795 | CY4: 8793 | DA4: 6465 | DC4: 8399 | DE4: 7518 | DG4: 8015
A5: 6 | B5: P05_Person_Create_Manual_Complete | C5: =E5 -> {"name":p.FamilyName1,"vorname":p.ManFirstName1,"ahvNumber":p.AHVNumber1,"language":"Deutsch","zivilstand":"ledig","geburtsdatum":p.BirthdayAdult1,"national":"Schweiz","gender":"männlich","aufenthalt":""} | E5: =F5&G5&H5&I5&J5&K5&L5&M5&N5&O5&P5&Q5&R5&S5&T5&U5&V5&W5&X5 -> {"name":p.FamilyName1,"vorname":p.ManFirstName1,"ahvNumber":p.AHVNumber1,"language":"Deutsch","zivilstand":"ledig","geburtsdatum":p.BirthdayAdult1,"national":"Schweiz","gender":"männlich","aufenthalt":""} | F5: {"name": | G5: =G4 -> p.FamilyName1 | H5: ,"vorname": | I5: =I4 -> p.ManFirstName1 | J5: ,"ahvNumber": | K5: =I$62 -> p.AHVNumber1 | L5: ,"language":" | M5: Deutsch | N5: ","zivilstand":" | O5: ledig | P5: ","geburtsdatum": | Q5: =J62 -> p.BirthdayAdult1 | R5: ,"national":" | S5: Schweiz | T5: ","gender":" | U5: männlich | V5: ","aufenthalt":" | X5: "} | AI5: 4248 | AJ5: 10 Parallel | AL5: 2994 | AM5: =AL5/($AI5) -> 0.70480226 | AN5: 3290 | AO5: =AN5/($AI5) -> 0.77448211 | AP5: 3368 | AQ5: =AP5/($AI5) -> 0.79284369 | AR5: 3306 | AS5: =AR5/($AI5) -> 0.77824859 | AT5: 1785 | AU5: =AT5/($AI5) -> 0.42019774 | AV5: 3248 | AW5: =AV5/($AI5) -> 0.7645951 | AX5: 3124 | AY5: =AX5/($AI5) -> 0.7354049 | AZ5: 2770 | BB5: 2828 | BC5: =BB5/($AI5) -> 0.66572505 | BD5: 1839 | BE5: =BD5/($AI5) -> 0.4329096 | BF5: 3591 | BG5: =BF5/($AI5) -> 0.84533898 | BH5: 1286 | BI5: =BH5/($AI5) -> 0.3027307 | BK5: 1866 | BL5: =BK5/($AI5) -> 0.43926554 | BM5: 1734 | BN5: =BM5/($AI5) -> 0.40819209 | BO5: 1743 | BP5: =BO5/($AI5) -> 0.41031073 | BQ5: 1989 | BR5: =BQ5/($AI5) -> 0.46822034 | BS5: 1938 | BT5: =BS5/($AI5) -> 0.45621469 | BU5: 1806 | BV5: =BU5/($AI5) -> 0.42514124 | BW5: 1746 | BX5: =BW5/($AI5) -> 0.41101695 | BY5: 1735 | BZ5: =BY5/($AI5) -> 0.4084275 | CA5: 1625 | CB5: =CA5/($AI5) -> 0.38253296 | CC5: 1839 | CD5: =CC5/($AI5) -> 0.4329096 | CE5: 1633 | CF5: =CE5/($AI5) -> 0.3844162 | CG5: 1427 | CH5: =CG5/($AI5) -> 0.33592279 | CI5: 569 | CJ5: =CI5/($AI5) -> 0.13394539 | CK5: 459 | CL5: =CK5/($AI5) -> 0.10805085 | CM5: 1317 | CN5: =CM5/($AI5) -> 0.31002825 | CO5: 1435 | CP5: =CO5/($AI5) -> 0.33780603 | CQ5: 1356 | CR5: =CQ5/($AI5) -> 0.31920904 | CS5: 1454 | CT5: =CS5/($AI5) -> 0.34227872 | CU5: 1334 | CV5: =CU5/($AI5) -> 0.31403013 | CW5: 1162 | CX5: =CW5/($AI5) -> 0.27354049 | CY5: 1488 | DA5: 484 | DC5: 1126 | DE5: 1206 | DG5: 1425
A6: 7 | B6: P10_Person_Communikation_Complete | C6: =E6 -> {"mobile":"079 5413355","privateNumber":"079 5309370","email":"5624abc@gmail.com"} | E6: =F6&G6&H6&I6&J6&K6&L6&M6&N6&O6&P6&Q6&R6&S6&T6&U6&V6&W6&X6 -> {"mobile":"079 5413355","privateNumber":"079 5309370","email":"5624abc@gmail.com"} | F6: {"mobile":" | G6: ="079 "&RANDBETWEEN(5234500,5699999) -> 079 5413355 | H6: ","privateNumber":" | I6: ="079 "&RANDBETWEEN(5234500,5699999) -> 079 5309370 | J6: ","email":" | K6: 5624abc@gmail.com | L6: "} | AI6: 3639 | AJ6: 20 Parallel | AL6: 3657 | AM6: =AL6/($AI6) -> 1.0049464 | AN6: 4534 | AO6: =AN6/($AI6) -> 1.2459467 | AP6: 4999 | AQ6: =AP6/($AI6) -> 1.373729 | AR6: 4750 | AS6: =AR6/($AI6) -> 1.3053037 | AT6: 2507 | AU6: =AT6/($AI6) -> 0.68892553 | AV6: 4176 | AW6: =AV6/($AI6) -> 1.147568 | AX6: 3909 | AY6: =AX6/($AI6) -> 1.0741962 | AZ6: 3585 | BB6: 3326 | BC6: =BB6/($AI6) -> 0.91398736 | BD6: 3008 | BE6: =BD6/($AI6) -> 0.82660071 | BF6: 4148 | BG6: =BF6/($AI6) -> 1.1398736 | BH6: 2528 | BI6: =BH6/($AI6) -> 0.69469635 | BK6: 3014 | BL6: =BK6/($AI6) -> 0.82824952 | BM6: 2617 | BN6: =BM6/($AI6) -> 0.71915361 | BO6: 2785 | BP6: =BO6/($AI6) -> 0.76532014 | BQ6: 3146 | BR6: =BQ6/($AI6) -> 0.86452322 | BS6: 3792 | BT6: =BS6/($AI6) -> 1.0420445 | BU6: 3891 | BV6: =BU6/($AI6) -> 1.0692498 | BW6: 3784 | BX6: =BW6/($AI6) -> 1.0398461 | BY6: 3631 | BZ6: =BY6/($AI6) -> 0.99780159 | CA6: 2395 | CB6: =CA6/($AI6) -> 0.65814784 | CC6: 3816 | CD6: =CC6/($AI6) -> 1.0486397 | CE6: 2687 | CF6: =CE6/($AI6) -> 0.73838967 | CG6: 2464 | CH6: =CG6/($AI6) -> 0.6771091 | CI6: 2247 | CJ6: =CI6/($AI6) -> 0.61747733 | CK6: 2207 | CL6: =CK6/($AI6) -> 0.6064853 | CM6: 2514 | CN6: =CM6/($AI6) -> 0.69084913 | CO6: 2449 | CP6: =CO6/($AI6) -> 0.67298708 | CQ6: 2560 | CR6: =CQ6/($AI6) -> 0.70348997 | CS6: 2643 | CT6: =CS6/($AI6) -> 0.72629843 | CU6: 2534 | CV6: =CU6/($AI6) -> 0.69634515 | CW6: 2486 | CX6: =CW6/($AI6) -> 0.68315471 | CY6: 2948 | DA6: 2208 | DC6: 2753 | DE6: 2659 | DG6: 2809
A7: 8 | B7: P15_Person_Adress | C7: =E7 -> {"zusatz":"","strasse":"Strasse_566","houseNumber":"5","ort":"3053 Münchenbuchsee","validDate":"01.01.2025"} | E7: =F7&G7&H7&I7&J7&K7&L7&M7&N7&O7&P7&Q7&R7&S7&T7&U7&V7&W7&X7 -> {"zusatz":"","strasse":"Strasse_566","houseNumber":"5","ort":"3053 Münchenbuchsee","validDate":"01.01.2025"} | F7: {"zusatz":" | H7: ","strasse":" | I7: ="Strasse_"&RANDBETWEEN(1,1000) -> Strasse_566 | J7: ","houseNumber":" | K7: =RANDBETWEEN(1,100) -> 5 | L7: ","ort":" | M7: 3053 Münchenbuchsee | N7: ","validDate":" | O7: ="01.01."&TEXT(TODAY(),"YYYY") -> 01.01.2025 | P7: "} | AI7: 434 | AJ7: 50 Parallel | AL7: 443 | AM7: =AL7/($AI7) -> 1.0207373 | AN7: 807 | AO7: =AN7/($AI7) -> 1.859447 | AP7: 785 | AQ7: =AP7/($AI7) -> 1.8087558 | AR7: 742 | AS7: =AR7/($AI7) -> 1.7096774 | AT7: 407 | AU7: =AT7/($AI7) -> 0.93778802 | AV7: 629 | AW7: =AV7/($AI7) -> 1.4493088 | AX7: 624 | AY7: =AX7/($AI7) -> 1.437788 | AZ7: 547 | BB7: 428 | BC7: =BB7/($AI7) -> 0.98617512 | BD7: 246 | BE7: =BD7/($AI7) -> 0.56682028 | BF7: 641 | BG7: =BF7/($AI7) -> 1.4769585 | BH7: 247 | BI7: =BH7/($AI7) -> 0.56912442 | BK7: 358 | BL7: =BK7/($AI7) -> 0.82488479 | BM7: 344 | BN7: =BM7/($AI7) -> 0.79262673 | BO7: 321 | BP7: =BO7/($AI7) -> 0.73963134 | BQ7: 400 | BR7: =BQ7/($AI7) -> 0.92165899 | BS7: 509 | BT7: =BS7/($AI7) -> 1.1728111 | BU7: 513 | BV7: =BU7/($AI7) -> 1.1820276 | BW7: 456 | BX7: =BW7/($AI7) -> 1.0506912 | BY7: 457 | BZ7: =BY7/($AI7) -> 1.0529954 | CA7: 366 | CB7: =CA7/($AI7) -> 0.84331797 | CC7: 422 | CD7: =CC7/($AI7) -> 0.97235023 | CE7: 346 | CF7: =CE7/($AI7) -> 0.79723502 | CG7: 294 | CH7: =CG7/($AI7) -> 0.67741935 | CI7: 174 | CJ7: =CI7/($AI7) -> 0.40092166 | CK7: 148 | CL7: =CK7/($AI7) -> 0.34101382 | CM7: 240 | CN7: =CM7/($AI7) -> 0.55299539 | CO7: 234 | CP7: =CO7/($AI7) -> 0.53917051 | CQ7: 248 | CR7: =CQ7/($AI7) -> 0.57142857 | CS7: 224 | CT7: =CS7/($AI7) -> 0.51612903 | CU7: 252 | CV7: =CU7/($AI7) -> 0.58064516 | CW7: 175 | CX7: =CW7/($AI7) -> 0.40322581 | CY7: 403 | DA7: 151 | DC7: 237 | DE7: 293 | DG7: 325
A8: 9 | B8: P20_Person_ZahlungsVerbindung | C8: =E8 -> {"iban":p.IBAN1} | E8: =F8&G8&H8&I8&J8&K8&L8&M8&N8&O8&P8&Q8&R8&S8&T8&U8&V8&W8&X8 -> {"iban":p.IBAN1} | F8: {"iban": | G8: p.IBAN1 | H8: } | AI8: 5206 | AL8: 5243 | AM8: =AL8/($AI8) -> 1.0071072 | AN8: 5874 | AO8: =AN8/($AI8) -> 1.1283135 | AP8: 5927 | AQ8: =AP8/($AI8) -> 1.138494 | AR8: 5864 | AS8: =AR8/($AI8) -> 1.1263926 | AT8: 5028 | AU8: =AT8/($AI8) -> 0.96580868 | AV8: 5359 | AW8: =AV8/($AI8) -> 1.0293892 | AX8: 5610 | AY8: =AX8/($AI8) -> 1.0776028 | AZ8: 5301 | BB8: 5109 | BC8: =BB8/($AI8) -> 0.98136765 | BD8: 4704 | BE8: =BD8/($AI8) -> 0.9035728 | BF8: 5426 | BG8: =BF8/($AI8) -> 1.0422589 | BH8: 4624 | BI8: =BH8/($AI8) -> 0.88820592 | BK8: 4951 | BL8: =BK8/($AI8) -> 0.95101806 | BM8: 4775 | BN8: =BM8/($AI8) -> 0.91721091 | BO8: 4813 | BP8: =BO8/($AI8) -> 0.92451018 | BQ8: 5016 | BR8: =BQ8/($AI8) -> 0.96350365 | BS8: 5090 | BT8: =BS8/($AI8) -> 0.97771802 | BU8: 4875 | BV8: =BU8/($AI8) -> 0.93641952 | BW8: 5143 | BX8: =BW8/($AI8) -> 0.98789858 | BY8: 5098 | BZ8: =BY8/($AI8) -> 0.97925471 | CA8: 4840 | CB8: =CA8/($AI8) -> 0.9296965 | CC8: 5137 | CD8: =CC8/($AI8) -> 0.98674606 | CE8: 4898 | CF8: =CE8/($AI8) -> 0.9408375 | CG8: 4725 | CH8: =CG8/($AI8) -> 0.90760661 | CI8: 4511 | CJ8: =CI8/($AI8) -> 0.86650019 | CK8: 4489 | CL8: =CK8/($AI8) -> 0.8622743 | CM8: 4613 | CN8: =CM8/($AI8) -> 0.88609297 | CO8: 4618 | CP8: =CO8/($AI8) -> 0.8870534 | CQ8: 4611 | CR8: =CQ8/($AI8) -> 0.8857088 | CS8: 4609 | CT8: =CS8/($AI8) -> 0.88532463 | CU8: 4684 | CV8: =CU8/($AI8) -> 0.89973108 | CW8: 1637 | CX8: =CW8/($AI8) -> 0.31444487 | CY8: 2374 | DA8: 984 | DC8: 1361 | DE8: 1502 | DG8: 1728
A9: 10 | B9: P30_Person_Uebernehmen | AI9: 2108 | AL9: 2128 | AM9: =AL9/($AI9) -> 1.0094877 | AN9: 2253 | AO9: =AN9/($AI9) -> 1.0687856 | AP9: 2264 | AQ9: =AP9/($AI9) -> 1.0740038 | AR9: 2224 | AS9: =AR9/($AI9) -> 1.0550285 | AT9: 2165 | AU9: =AT9/($AI9) -> 1.0270398 | AV9: 2154 | AW9: =AV9/($AI9) -> 1.0218216 | AX9: 2204 | AY9: =AX9/($AI9) -> 1.0455408 | AZ9: 2132 | BB9: 2158 | BC9: =BB9/($AI9) -> 1.0237192 | BD9: 104 | BE9: =BD9/($AI9) -> 0.049335863 | BF9: 93 | BG9: =BF9/($AI9) -> 0.044117647 | BH9: 93 | BI9: =BH9/($AI9) -> 0.044117647 | BK9: 80 | BL9: =BK9/($AI9) -> 0.037950664 | BM9: 67 | BN9: =BM9/($AI9) -> 0.031783681 | BO9: 75 | BP9: =BO9/($AI9) -> 0.035578748 | BQ9: 87 | BR9: =BQ9/($AI9) -> 0.041271347 | BS9: 80 | BT9: =BS9/($AI9) -> 0.037950664 | BU9: 107 | BV9: =BU9/($AI9) -> 0.050759013 | BW9: 134 | BX9: =BW9/($AI9) -> 0.063567362 | BY9: 78 | BZ9: =BY9/($AI9) -> 0.037001898 | CA9: 55 | CB9: =CA9/($AI9) -> 0.026091082 | CC9: 62 | CD9: =CC9/($AI9) -> 0.029411765 | CE9: 83 | CF9: =CE9/($AI9) -> 0.039373814 | CG9: 69 | CH9: =CG9/($AI9) -> 0.032732448 | CI9: 74 | CJ9: =CI9/($AI9) -> 0.035104364 | CK9: 58 | CL9: =CK9/($AI9) -> 0.027514231 | CM9: 57 | CN9: =CM9/($AI9) -> 0.027039848 | CO9: 57 | CP9: =CO9/($AI9) -> 0.027039848 | CQ9: 54 | CR9: =CQ9/($AI9) -> 0.025616698 | CS9: 58 | CT9: =CS9/($AI9) -> 0.027514231 | CU9: 55 | CV9: =CU9/($AI9) -> 0.026091082 | CW9: 61 | CX9: =CW9/($AI9) -> 0.028937381 | CY9: 147 | DA9: 79 | DC9: 104 | DE9: 121 | DG9: 150
A10: 11 | B10: H01_Haushalt_Uebernehmen_Zustaendigkeit | C10: =E10 -> {"zust_Gemeinde":"Münchenbuchsee","zust_SozTeam":"Sozialarbeit Bern 1","zust_SozMitarbeiter":"Bern Sozialarbeiterin 1A","zust_SachbTeam":"Sachbearbeitung Bern","zust_SachbMitarbeiter":"Bern Sachbearbeiterin"} | E10: =F10&G10&H10&I10&J10&K10&L10&M10&N10&O10&P10&Q10&R10&S10&T10&U10&V10&W10&X10 -> {"zust_Gemeinde":"Münchenbuchsee","zust_SozTeam":"Sozialarbeit Bern 1","zust_SozMitarbeiter":"Bern Sozialarbeiterin 1A","zust_SachbTeam":"Sachbearbeitung Bern","zust_SachbMitarbeiter":"Bern Sachbearbeiterin"} | F10: {"zust_Gemeinde":" | G10: Münchenbuchsee | H10: ","zust_SozTeam":" | I10: Sozialarbeit Bern 1 | J10: ","zust_SozMitarbeiter":" | K10: Bern Sozialarbeiterin 1A | L10: ","zust_SachbTeam":" | M10: Sachbearbeitung Bern | N10: ","zust_SachbMitarbeiter":" | O10: Bern Sachbearbeiterin | P10: "} | AI10: 565 | AJ10: QA | AL10: 227 | AM10: =AL10/($AI10) -> 0.40176991 | AN10: 510 | AO10: =AN10/($AI10) -> 0.90265487 | AP10: 511 | AQ10: =AP10/($AI10) -> 0.90442478 | AR10: 382 | AS10: =AR10/($AI10) -> 0.67610619 | AT10: 310 | AU10: =AT10/($AI10) -> 0.54867257 | AV10: 312 | AW10: =AV10/($AI10) -> 0.55221239 | AX10: 331 | AY10: =AX10/($AI10) -> 0.58584071 | AZ10: 160 | BB10: 192 | BC10: =BB10/($AI10) -> 0.33982301 | BD10: 1157 | BE10: =BD10/($AI10) -> 2.0477876 | BF10: 1275 | BG10: =BF10/($AI10) -> 2.2566372 | BH10: 1240 | BI10: =BH10/($AI10) -> 2.1946903 | BK10: 1219 | BL10: =BK10/($AI10) -> 2.1575221 | BM10: 2010 | BN10: =BM10/($AI10) -> 3.5575221 | BO10: 1166 | BP10: =BO10/($AI10) -> 2.0637168 | BQ10: 1218 | BR10: =BQ10/($AI10) -> 2.1557522 | BS10: 1187 | BT10: =BS10/($AI10) -> 2.100885 | BU10: 1174 | BV10: =BU10/($AI10) -> 2.0778761 | BW10: 1217 | BX10: =BW10/($AI10) -> 2.1539823 | BY10: 1162 | BZ10: =BY10/($AI10) -> 2.0566372 | CA10: 1386 | CB10: =CA10/($AI10) -> 2.4530973 | CC10: 1224 | CD10: =CC10/($AI10) -> 2.1663717 | CE10: 1191 | CF10: =CE10/($AI10) -> 2.1079646 | CG10: 1186 | CH10: =CG10/($AI10) -> 2.099115 | CI10: 1151 | CJ10: =CI10/($AI10) -> 2.0371681 | CK10: 1152 | CL10: =CK10/($AI10) -> 2.0389381 | CM10: 1164 | CN10: =CM10/($AI10) -> 2.060177 | CO10: 1181 | CP10: =CO10/($AI10) -> 2.0902655 | CQ10: 1144 | CR10: =CQ10/($AI10) -> 2.0247788 | CS10: 1161 | CT10: =CS10/($AI10) -> 2.0548673 | CU10: 1162 | CV10: =CU10/($AI10) -> 2.0566372 | CW10: 1194 | CX10: =CW10/($AI10) -> 2.1132743 | CY10: 1313 | DA10: 1142 | DC10: 1185 | DE10: 1210 | DG10: 1267
A11: 12 | B11: D01_Dossier_Eroeffnen | C11: =E11 -> {"dossierBezeichnung":p.DossierName1,"eroeffnetAm":"04.11.2025","dossierSprache":"Deutsch"} | E11: =F11&G11&H11&I11&J11&K11&L11&M11&N11&O11&P11&Q11&R11&S11&T11&U11&V11&W11&X11 -> {"dossierBezeichnung":p.DossierName1,"eroeffnetAm":"04.11.2025","dossierSprache":"Deutsch"} | F11: {"dossierBezeichnung": | G11: =G$62 -> p.DossierName1 | H11: ,"eroeffnetAm":" | I11: =TEXT(TEXT(TODAY(),"DD")&"."&TEXT(TODAY(),"MM")&"."&TEXT(TODAY(),"YYYY"),"DD.MM.YYYY") -> 04.11.2025 | J11: ","dossierSprache":" | K11: Deutsch | L11: "} | AI11: 3489 | AL11: 3700 | AM11: =AL11/($AI11) -> 1.0604758 | AN11: 4194 | AO11: =AN11/($AI11) -> 1.2020636 | AP11: 4214 | AQ11: =AP11/($AI11) -> 1.2077959 | AR11: 3773 | AS11: =AR11/($AI11) -> 1.0813987 | AT11: 3081 | AU11: =AT11/($AI11) -> 0.88306105 | AV11: 3350 | AW11: =AV11/($AI11) -> 0.9601605 | AX11: 3683 | AY11: =AX11/($AI11) -> 1.0556033 | AZ11: 4165 | BB11: 4143 | BC11: =BB11/($AI11) -> 1.1874463 | BD11: 3974 | BE11: =BD11/($AI11) -> 1.1390083 | BF11: 4600 | BG11: =BF11/($AI11) -> 1.3184293 | BH11: 3617 | BI11: =BH11/($AI11) -> 1.0366867 | BK11: 3983 | BL11: =BK11/($AI11) -> 1.1415878 | BM11: 3964 | BN11: =BM11/($AI11) -> 1.1361422 | BO11: 3973 | BP11: =BO11/($AI11) -> 1.1387217 | BQ11: 4033 | BR11: =BQ11/($AI11) -> 1.1559186 | BS11: 4113 | BT11: =BS11/($AI11) -> 1.1788478 | BU11: 3934 | BV11: =BU11/($AI11) -> 1.1275437 | BW11: 3743 | BX11: =BW11/($AI11) -> 1.0728002 | BY11: 3999 | BZ11: =BY11/($AI11) -> 1.1461737 | CA11: 3854 | CB11: =CA11/($AI11) -> 1.1046145 | CC11: 4219 | CD11: =CC11/($AI11) -> 1.209229 | CE11: 3977 | CF11: =CE11/($AI11) -> 1.1398682 | CG11: 4155 | CH11: =CG11/($AI11) -> 1.1908856 | CI11: 4192 | CJ11: =CI11/($AI11) -> 1.2014904 | CK11: 4325 | CL11: =CK11/($AI11) -> 1.2396102 | CM11: 4199 | CN11: =CM11/($AI11) -> 1.2034967 | CO11: 4214 | CP11: =CO11/($AI11) -> 1.2077959 | CQ11: 3978 | CR11: =CQ11/($AI11) -> 1.1401548 | CS11: 4207 | CT11: =CS11/($AI11) -> 1.2057896 | CU11: 4243 | CV11: =CU11/($AI11) -> 1.2161078 | CW11: 4067 | CX11: =CW11/($AI11) -> 1.1656635 | CY11: 4229 | DA11: 4044 | DC11: 4085 | DE11: 4121 | DG11: 4106
A12: 14 | B12: BW04_ZahlungsVerbindung_Freigeben | C12: =E12 -> {"dossierInstitution":p.DossierName1,"klientschaft":`${p.FamilyName1}, ${p.ManFirstName1}`,"buttonBewilligung":"Anfragen","checkStatus":"In Bearbeitung"} | E12: =F12&G12&H12&I12&J12&K12&L12&M12&N12&O12&P12&Q12&R12&S12&T12&U12&V12&W12&X12 -> {"dossierInstitution":p.DossierName1,"klientschaft":`${p.FamilyName1}, ${p.ManFirstName1}`,"buttonBewilligung":"Anfragen","checkStatus":"In Bearbeitung"} | F12: {"dossierInstitution": | G12: =G11 -> p.DossierName1 | H12: ,"klientschaft":` | I12: =I23 -> ${p.FamilyName1}, ${p.ManFirstName1} | J12: `,"buttonBewilligung":" | K12: Anfragen | L12: ","checkStatus":" | M12: In Bearbeitung | N12: "} | AI12: 1017 | AL12: 1012 | AM12: =AL12/($AI12) -> 0.99508358 | AN12: 1010 | AO12: =AN12/($AI12) -> 0.99311701 | AP12: 1013 | AQ12: =AP12/($AI12) -> 0.99606686 | AR12: 1021 | AS12: =AR12/($AI12) -> 1.0039331 | AT12: 1017 | AU12: =AT12/($AI12) -> 1 | AV12: 1012 | AW12: =AV12/($AI12) -> 0.99508358 | AX12: 1006 | AY12: =AX12/($AI12) -> 0.98918387 | AZ12: 1010 | BB12: 1011 | BC12: =BB12/($AI12) -> 0.99410029 | BD12: 1544 | BE12: =BD12/($AI12) -> 1.5181908 | BF12: 1115 | BG12: =BF12/($AI12) -> 1.0963618 | BH12: 1067 | BI12: =BH12/($AI12) -> 1.0491642 | BK12: 917 | BL12: =BK12/($AI12) -> 0.90167158 | BM12: 1533 | BN12: =BM12/($AI12) -> 1.5073746 | BO12: 1538 | BP12: =BO12/($AI12) -> 1.5122911 | BQ12: 1396 | BR12: =BQ12/($AI12) -> 1.3726647 | BS12: 900 | BT12: =BS12/($AI12) -> 0.88495575 | BU12: 914 | BV12: =BU12/($AI12) -> 0.89872173 | BW12: 1098 | BX12: =BW12/($AI12) -> 1.079646 | BY12: 941 | BZ12: =BY12/($AI12) -> 0.9252704 | CA12: 1066 | CB12: =CA12/($AI12) -> 1.0481809 | CC12: 1093 | CD12: =CC12/($AI12) -> 1.0747296 | CE12: 1629 | CF12: =CE12/($AI12) -> 1.6017699 | CG12: 952 | CH12: =CG12/($AI12) -> 0.93608653 | CI12: 1544 | CJ12: =CI12/($AI12) -> 1.5181908 | CK12: 1495 | CL12: =CK12/($AI12) -> 1.4700098 | CM12: 1464 | CN12: =CM12/($AI12) -> 1.439528 | CO12: 1522 | CP12: =CO12/($AI12) -> 1.4965585 | CQ12: 1520 | CR12: =CQ12/($AI12) -> 1.4945919 | CS12: 1481 | CT12: =CS12/($AI12) -> 1.4562439 | CU12: 1517 | CV12: =CU12/($AI12) -> 1.4916421 | CW12: 8953 | CX12: =CW12/($AI12) -> 8.8033432 | CY12: 5523 | DA12: 4299 | DC12: 5380 | DE12: 7390 | DG12: 9091
A13: 15 | B13: L03_LogoutAndLoginDiffAccount | C13: =E13 -> {"username":"Bern.Sachbearbeiterin@diartis.ch","password":"XXxa22?pdTA66-S@"} | E13: =F13&G13&H13&I13&J13&K13&L13&M13&N13&O13&P13&Q13&R13&S13&T13&U13&V13&W13&X13 -> {"username":"Bern.Sachbearbeiterin@diartis.ch","password":"XXxa22?pdTA66-S@"} | F13: {"username":" | G13: Bern.Sachbearbeiterin@diartis.ch | H13: ","password":" | I13: XXxa22?pdTA66-S@ | J13: "} | AI13: 12078 | AL13: 12419 | AM13: =AL13/($AI13) -> 1.0282332 | AN13: 12798 | AO13: =AN13/($AI13) -> 1.0596125 | AP13: 12935 | AQ13: =AP13/($AI13) -> 1.0709555 | AR13: 14401 | AS13: =AR13/($AI13) -> 1.1923332 | AT13: 13760 | AU13: =AT13/($AI13) -> 1.1392615 | AV13: 14182 | AW13: =AV13/($AI13) -> 1.174201 | AX13: 14251 | AY13: =AX13/($AI13) -> 1.1799139 | AZ13: 9685 | BB13: 9964 | BC13: =BB13/($AI13) -> 0.82497102 | BD13: 4009 | BE13: =BD13/($AI13) -> 0.33192582 | BF13: 4022 | BG13: =BF13/($AI13) -> 0.33300215 | BH13: 4012 | BI13: =BH13/($AI13) -> 0.3321742 | BK13: 4017 | BL13: =BK13/($AI13) -> 0.33258818 | BM13: 4020 | BN13: =BM13/($AI13) -> 0.33283656 | BO13: 11484 | BP13: =BO13/($AI13) -> 0.95081967 | BQ13: 10053 | BR13: =BQ13/($AI13) -> 0.83233979 | BS13: 11588 | BT13: =BS13/($AI13) -> 0.95943037 | BU13: 11166 | BV13: =BU13/($AI13) -> 0.92449081 | BW13: 11642 | BX13: =BW13/($AI13) -> 0.96390131 | BY13: 9693 | BZ13: =BY13/($AI13) -> 0.80253353 | CA13: 16101 | CB13: =CA13/($AI13) -> 1.3330849 | CC13: 9509 | CD13: =CC13/($AI13) -> 0.78729922 | CE13: 6931 | CF13: =CE13/($AI13) -> 0.57385329 | CG13: 6610 | CH13: =CG13/($AI13) -> 0.54727604 | CI13: 6177 | CJ13: =CI13/($AI13) -> 0.51142573 | CK13: 43627 | CL13: =CK13/($AI13) -> 3.6121047 | CM13: 32197 | CN13: =CM13/($AI13) -> 2.6657559 | CO13: 32138 | CP13: =CO13/($AI13) -> 2.660871 | CQ13: 17430 | CR13: =CQ13/($AI13) -> 1.4431197 | CS13: 27317 | CT13: =CS13/($AI13) -> 2.2617155 | CU13: 29239 | CV13: =CU13/($AI13) -> 2.4208478 | CW13: 20759 | CX13: =CW13/($AI13) -> 1.7187448 | CY13: 8304 | DA13: 8337 | DC13: 9721 | DE13: 11773 | DG13: 19902
A14: 17 | B14: BW04_ZahlungsVerbindung_Freigeben | C14: =E14 -> {"dossierInstitution":p.DossierName1,"klientschaft":`${p.FamilyName1}, ${p.ManFirstName1}`,"buttonBewilligung":"Bewilligen","checkStatus":"Bewilligt"} | E14: =F14&G14&H14&I14&J14&K14&L14&M14&N14&O14&P14&Q14&R14&S14&T14&U14&V14&W14&X14 -> {"dossierInstitution":p.DossierName1,"klientschaft":`${p.FamilyName1}, ${p.ManFirstName1}`,"buttonBewilligung":"Bewilligen","checkStatus":"Bewilligt"} | F14: {"dossierInstitution": | G14: ='001x'!$G$11 -> p.DossierName1 | H14: ,"klientschaft":` | I14: =I23 -> ${p.FamilyName1}, ${p.ManFirstName1} | J14: `,"buttonBewilligung":" | K14: Bewilligen | L14: ","checkStatus":" | M14: Bewilligt | N14: "} | AI14: 4790 | AL14: 5007 | AM14: =AL14/($AI14) -> 1.0453027 | AN14: 5015 | AO14: =AN14/($AI14) -> 1.0469729 | AP14: 5014 | AQ14: =AP14/($AI14) -> 1.0467641 | AR14: 5021 | AS14: =AR14/($AI14) -> 1.0482255 | AT14: 5014 | AU14: =AT14/($AI14) -> 1.0467641 | AV14: 5009 | AW14: =AV14/($AI14) -> 1.0457203 | AX14: 5004 | AY14: =AX14/($AI14) -> 1.0446764 | AZ14: 5018 | BB14: 5021 | BC14: =BB14/($AI14) -> 1.0482255 | BD14: 8626 | BE14: =BD14/($AI14) -> 1.8008351 | BF14: 8975 | BG14: =BF14/($AI14) -> 1.8736952 | BH14: 9664 | BI14: =BH14/($AI14) -> 2.0175365 | BK14: 8654 | BL14: =BK14/($AI14) -> 1.8066806 | BM14: 8903 | BN14: =BM14/($AI14) -> 1.8586639 | BO14: 10580 | BP14: =BO14/($AI14) -> 2.2087683 | BQ14: 9302 | BR14: =BQ14/($AI14) -> 1.9419624 | BS14: 9758 | BT14: =BS14/($AI14) -> 2.0371608 | BU14: 9814 | BV14: =BU14/($AI14) -> 2.0488518 | BW14: 10548 | BX14: =BW14/($AI14) -> 2.2020877 | BY14: 8948 | BZ14: =BY14/($AI14) -> 1.8680585 | CA14: 9461 | CB14: =CA14/($AI14) -> 1.9751566 | CC14: 9691 | CD14: =CC14/($AI14) -> 2.0231733 | CE14: 10751 | CF14: =CE14/($AI14) -> 2.2444676 | CG14: 9774 | CH14: =CG14/($AI14) -> 2.040501 | CI14: 10115 | CJ14: =CI14/($AI14) -> 2.111691 | CK14: 10077 | CL14: =CK14/($AI14) -> 2.1037578 | CM14: 9625 | CN14: =CM14/($AI14) -> 2.0093946 | CO14: 9869 | CP14: =CO14/($AI14) -> 2.060334 | CQ14: 8732 | CR14: =CQ14/($AI14) -> 1.8229645 | CS14: 10681 | CT14: =CS14/($AI14) -> 2.2298539 | CU14: 9851 | CV14: =CU14/($AI14) -> 2.0565762 | CW14: 9773 | CX14: =CW14/($AI14) -> 2.0402923 | CY14: 11811 | DA14: 12426 | DC14: 12341 | DE14: 12021 | DG14: 10831
A15: 18 | B15: L03_LogoutAndLoginDiffAccount | C15: {"username":"bern.sozialarbeiterin1a@diartis.ch","password":"SMze97-jkSJ59!F."} | E15: =F15&G15&H15&I15&J15&K15&L15&M15&N15&O15&P15&Q15&R15&S15&T15&U15&V15&W15&X15 -> {"username":"Bern.Sachbearbeiterin@diartis.ch","password":"XXxa22?pdTA66-S@"} | F15: {"username":" | G15: Bern.Sachbearbeiterin@diartis.ch | H15: ","password":" | I15: XXxa22?pdTA66-S@ | J15: "} | AI15: 12332 | AL15: 12730 | AM15: =AL15/($AI15) -> 1.0322738 | AN15: 12589 | AO15: =AN15/($AI15) -> 1.0208401 | AP15: 13286 | AQ15: =AP15/($AI15) -> 1.0773597 | AR15: 13640 | AS15: =AR15/($AI15) -> 1.1060655 | AT15: 13635 | AU15: =AT15/($AI15) -> 1.1056601 | AV15: 13688 | AW15: =AV15/($AI15) -> 1.1099578 | AX15: 26297 | AY15: =AX15/($AI15) -> 2.1324197 | AZ15: 10616 | BB15: 10362 | BC15: =BB15/($AI15) -> 0.840253 | BD15: 410 | BE15: =BD15/($AI15) -> 0.033246837 | BF15: 416 | BG15: =BF15/($AI15) -> 0.033733377 | BH15: 401 | BI15: =BH15/($AI15) -> 0.032517029 | BK15: 418 | BL15: =BK15/($AI15) -> 0.033895556 | BM15: 404 | BN15: =BM15/($AI15) -> 0.032760298 | BO15: 10163 | BP15: =BO15/($AI15) -> 0.82411612 | BQ15: 10128 | BR15: =BQ15/($AI15) -> 0.82127798 | BS15: 10432 | BT15: =BS15/($AI15) -> 0.84592929 | BU15: 10609 | BV15: =BU15/($AI15) -> 0.86028219 | BW15: 11196 | BX15: =BW15/($AI15) -> 0.90788193 | BY15: 10494 | BZ15: =BY15/($AI15) -> 0.85095686 | CA15: 8885 | CB15: =CA15/($AI15) -> 0.7204833 | CC15: 9805 | CD15: =CC15/($AI15) -> 0.79508596 | CE15: 8275 | CF15: =CE15/($AI15) -> 0.67101849 | CG15: 7229 | CH15: =CG15/($AI15) -> 0.58619851 | CI15: 5168 | CJ15: =CI15/($AI15) -> 0.41907233 | CK15: 14471 | CL15: =CK15/($AI15) -> 1.1734512 | CM15: 9363 | CN15: =CM15/($AI15) -> 0.75924424 | CO15: 9758 | CP15: =CO15/($AI15) -> 0.79127473 | CQ15: 8724 | CR15: =CQ15/($AI15) -> 0.70742783 | CS15: 9595 | CT15: =CS15/($AI15) -> 0.77805709 | CU15: 8421 | CV15: =CU15/($AI15) -> 0.68285761 | CW15: 13550 | CX15: =CW15/($AI15) -> 1.0987674 | CY15: 10640 | DA15: 7882 | DC15: 9028 | DE15: 9203 | DG15: 8945
A16: 20 | B16: DO11_Dossier_Search_Lupe | C16: =E16 -> {"searchDossierOrKlient":p.DossierName1,"resultType":"Dossiers"} | E16: =F16&G16&H16&I16&J16&K16&L16&M16&N16&O16&P16&Q16&R16&S16&T16&U16&V16&W16&X16 -> {"searchDossierOrKlient":p.DossierName1,"resultType":"Dossiers"} | F16: {"searchDossierOrKlient": | G16: ='001x'!$G$11 -> p.DossierName1 | H16: ,"resultType":" | I16: Dossiers | J16: "} | AI16: 5018 | AL16: 5017 | AM16: =AL16/($AI16) -> 0.99980072 | AN16: 5008 | AO16: =AN16/($AI16) -> 0.99800717 | AP16: 5007 | AQ16: =AP16/($AI16) -> 0.99780789 | AR16: 5010 | AS16: =AR16/($AI16) -> 0.99840574 | AT16: 5024 | AU16: =AT16/($AI16) -> 1.0011957 | AV16: 5005 | AW16: =AV16/($AI16) -> 0.99740933 | AX16: 5011 | AY16: =AX16/($AI16) -> 0.99860502 | AZ16: 5005 | BB16: 5022 | BC16: =BB16/($AI16) -> 1.0007971 | BD16: 8677 | BE16: =BD16/($AI16) -> 1.729175 | BF16: 10125 | BG16: =BF16/($AI16) -> 2.0177361 | BH16: 9485 | BI16: =BH16/($AI16) -> 1.8901953 | BK16: 9709 | BL16: =BK16/($AI16) -> 1.9348346 | BM16: 9970 | BN16: =BM16/($AI16) -> 1.9868473 | BO16: 9975 | BP16: =BO16/($AI16) -> 1.9878438 | BQ16: 10619 | BR16: =BQ16/($AI16) -> 2.1161817 | BS16: 9783 | BT16: =BS16/($AI16) -> 1.9495815 | BU16: 10225 | BV16: =BU16/($AI16) -> 2.0376644 | BW16: 10001 | BX16: =BW16/($AI16) -> 1.9930251 | BY16: 9332 | BZ16: =BY16/($AI16) -> 1.8597051 | CA16: 8820 | CB16: =CA16/($AI16) -> 1.7576724 | CC16: 10004 | CD16: =CC16/($AI16) -> 1.993623 | CE16: 9135 | CF16: =CE16/($AI16) -> 1.8204464 | CG16: 8970 | CH16: =CG16/($AI16) -> 1.7875648 | CI16: 9488 | CJ16: =CI16/($AI16) -> 1.8907931 | CK16: 8800 | CL16: =CK16/($AI16) -> 1.7536867 | CM16: 10321 | CN16: =CM16/($AI16) -> 2.0567955 | CO16: 9974 | CP16: =CO16/($AI16) -> 1.9876445 | CQ16: 9194 | CR16: =CQ16/($AI16) -> 1.8322041 | CS16: 9458 | CT16: =CS16/($AI16) -> 1.8848147 | CU16: 9693 | CV16: =CU16/($AI16) -> 1.9316461 | CW16: 10242 | CX16: =CW16/($AI16) -> 2.0410522 | CY16: 21509 | DA16: 11750 | DC16: 11493 | DE16: 13832 | DG16: 11881
A17: 21 | B17: WO32_01b_Wohnsituation_Haushalt_Wohnung_anpassen | C17: =E17 -> {"vermieter":"Graber Immobilien","wohnungsgrosse":"4 Zimmer","mietkosten":1200,"nebenkosten":100} | E17: =F17&G17&H17&I17&J17&K17&L17&M17&N17&O17&P17&Q17&R17&S17&T17&U17&V17&W17&X17 -> {"vermieter":"Graber Immobilien","wohnungsgrosse":"4 Zimmer","mietkosten":1200,"nebenkosten":100} | F17: {"vermieter":" | G17: Graber Immobilien | H17: ","wohnungsgrosse":" | I17: 4 Zimmer | J17: ","mietkosten": | K17: 1200 | L17: ,"nebenkosten": | M17: 100 | N17: } | AI17: 10549 | AL17: 10895 | AM17: =AL17/($AI17) -> 1.0327993 | AN17: 11011 | AO17: =AN17/($AI17) -> 1.0437956 | AP17: 11381 | AQ17: =AP17/($AI17) -> 1.07887 | AR17: 10897 | AS17: =AR17/($AI17) -> 1.0329889 | AT17: 11079 | AU17: =AT17/($AI17) -> 1.0502417 | AV17: 11119 | AW17: =AV17/($AI17) -> 1.0540336 | AX17: 10646 | AY17: =AX17/($AI17) -> 1.0091952 | AZ17: 2477 | BB17: 2456 | BC17: =BB17/($AI17) -> 0.23281828 | BD17: 5594 | BE17: =BD17/($AI17) -> 0.53028723 | BF17: 6235 | BG17: =BF17/($AI17) -> 0.59105128 | BH17: 5583 | BI17: =BH17/($AI17) -> 0.52924448 | BK17: 5890 | BL17: =BK17/($AI17) -> 0.55834676 | BM17: 6024 | BN17: =BM17/($AI17) -> 0.57104939 | BO17: 5965 | BP17: =BO17/($AI17) -> 0.56545644 | BQ17: 5840 | BR17: =BQ17/($AI17) -> 0.55360698 | BS17: 6394 | BT17: =BS17/($AI17) -> 0.6061238 | BU17: 6114 | BV17: =BU17/($AI17) -> 0.579581 | BW17: 6376 | BX17: =BW17/($AI17) -> 0.60441748 | BY17: 5946 | BZ17: =BY17/($AI17) -> 0.56365532 | CA17: 5882 | CB17: =CA17/($AI17) -> 0.5575884 | CC17: 5357 | CD17: =CC17/($AI17) -> 0.50782065 | CE17: 3013 | CF17: =CE17/($AI17) -> 0.28561949 | CG17: 3110 | CH17: =CG17/($AI17) -> 0.29481467 | CI17: 3362 | CJ17: =CI17/($AI17) -> 0.31870319 | CK17: 115554 | CL17: =CK17/($AI17) -> 10.954024 | CM17: 5494 | CN17: =CM17/($AI17) -> 0.52080766 | CO17: 5566 | CP17: =CO17/($AI17) -> 0.52763295 | CQ17: 5405 | CR17: =CQ17/($AI17) -> 0.51237084 | CS17: 4980 | CT17: =CS17/($AI17) -> 0.47208266 | CU17: 5271 | CV17: =CU17/($AI17) -> 0.49966821 | CW17: 6470 | CX17: =CW17/($AI17) -> 0.61332828 | CY17: 7151 | DA17: 5668 | DC17: 5046 | DE17: 5190 | DG17: 4642
B18: WO30_Wohnsituation_Haushalt_Person_Hinzufuegen | C18: =E18 -> {"name":p.FamilyName1,"vorname":p.WomanFirstName1,"geburtsdatum":p.BirthdayAdult2,"ahvNumber":p.AHVNumber2,"personInhausltVon":"01.11.2025","inHauslt":"Übernehmen","ereignis":"Eheschliessung"} | E18: =F18&G18&H18&I18&J18&K18&L18&M18&N18&O18&P18&Q18&R18&S18&T18&U18&V18&W18&X18 -> {"name":p.FamilyName1,"vorname":p.WomanFirstName1,"geburtsdatum":p.BirthdayAdult2,"ahvNumber":p.AHVNumber2,"personInhausltVon":"01.11.2025","inHauslt":"Übernehmen","ereignis":"Eheschliessung"} | F18: {"name": | G18: =G5 -> p.FamilyName1 | H18: ,"vorname": | I18: =H63 -> p.WomanFirstName1 | J18: ,"geburtsdatum": | K18: =J63 -> p.BirthdayAdult2 | L18: ,"ahvNumber": | M18: =I63 -> p.AHVNumber2 | N18: ,"personInhausltVon":" | O18: ="01."&MONTH(TODAY())&"."&YEAR(TODAY()) -> 01.11.2025 | P18: ","inHauslt":" | Q18: Übernehmen | R18: ","ereignis":" | S18: Eheschliessung | T18: "} | AI18: 2974 | AL18: 3318 | AM18: =AL18/($AI18) -> 1.1156691 | AN18: 5657 | AO18: =AN18/($AI18) -> 1.902152 | AP18: 4597 | AQ18: =AP18/($AI18) -> 1.5457297 | AR18: 5547 | AS18: =AR18/($AI18) -> 1.8651648 | AT18: 5738 | AU18: =AT18/($AI18) -> 1.929388 | AV18: 5121 | AW18: =AV18/($AI18) -> 1.7219233 | AX18: 5462 | AY18: =AX18/($AI18) -> 1.8365837 | AZ18: 5249 | BB18: 5670 | BC18: =BB18/($AI18) -> 1.9065232 | BD18: 3690 | BE18: =BD18/($AI18) -> 1.2407532 | BF18: 3513 | BG18: =BF18/($AI18) -> 1.1812374 | BH18: 3054 | BI18: =BH18/($AI18) -> 1.0268998 | BK18: 4065 | BL18: =BK18/($AI18) -> 1.366846 | BM18: 4042 | BN18: =BM18/($AI18) -> 1.3591123 | BO18: 4106 | BP18: =BO18/($AI18) -> 1.3806321 | BQ18: 4024 | BR18: =BQ18/($AI18) -> 1.3530599 | BS18: 3730 | BT18: =BS18/($AI18) -> 1.2542031 | BU18: 4153 | BV18: =BU18/($AI18) -> 1.3964358 | BW18: 4360 | BX18: =BW18/($AI18) -> 1.466039 | BY18: 3948 | BZ18: =BY18/($AI18) -> 1.327505 | CA18: 3595 | CB18: =CA18/($AI18) -> 1.2088097 | CC18: 3955 | CD18: =CC18/($AI18) -> 1.3298588 | CE18: 3966 | CF18: =CE18/($AI18) -> 1.3335575 | CG18: 3555 | CH18: =CG18/($AI18) -> 1.1953598 | CI18: 2862 | CJ18: =CI18/($AI18) -> 0.96234028 | CK18: 4854 | CL18: =CK18/($AI18) -> 1.6321453 | CM18: 3422 | CN18: =CM18/($AI18) -> 1.1506389 | CO18: 3054 | CP18: =CO18/($AI18) -> 1.0268998 | CQ18: 3169 | CR18: =CQ18/($AI18) -> 1.0655683 | CS18: 3240 | CT18: =CS18/($AI18) -> 1.0894418 | CU18: 7870 | CV18: =CU18/($AI18) -> 2.6462677 | CW18: 4264 | CX18: =CW18/($AI18) -> 1.4337592 | CY18: 4418 | DA18: 3437 | DC18: 3821 | DE18: 4217 | DG18: 3452
B19: WO30_Wohnsituation_Haushalt_Person_Hinzufuegen | C19: =E19 -> {"name":p.FamilyName1,"vorname":p.GirlFirstName1,"geburtsdatum":p.BirthdayKid1,"ahvNumber":p.AHVNumber3,"personInhausltVon":"01.11.2025","inHauslt":"Übernehmen","ereignis":"Geburt"} | E19: =F19&G19&H19&I19&J19&K19&L19&M19&N19&O19&P19&Q19&R19&S19&T19&U19&V19&W19&X19 -> {"name":p.FamilyName1,"vorname":p.GirlFirstName1,"geburtsdatum":p.BirthdayKid1,"ahvNumber":p.AHVNumber3,"personInhausltVon":"01.11.2025","inHauslt":"Übernehmen","ereignis":"Geburt"} | F19: {"name": | G19: =G18 -> p.FamilyName1 | H19: ,"vorname": | I19: =H64 -> p.GirlFirstName1 | J19: ,"geburtsdatum": | K19: =J64 -> p.BirthdayKid1 | L19: ,"ahvNumber": | M19: =I64 -> p.AHVNumber3 | N19: ,"personInhausltVon":" | O19: ="01."&MONTH(TODAY())&"."&YEAR(TODAY()) -> 01.11.2025 | P19: ","inHauslt":" | Q19: Übernehmen | R19: ","ereignis":" | S19: Geburt | T19: "} | AI19: 2228 | AL19: 2472 | AM19: =AL19/($AI19) -> 1.1095153 | AN19: 3858 | AO19: =AN19/($AI19) -> 1.7315978 | AP19: 4051 | AQ19: =AP19/($AI19) -> 1.8182226 | AR19: 5422 | AS19: =AR19/($AI19) -> 2.4335727 | AT19: 5458 | AU19: =AT19/($AI19) -> 2.4497307 | AV19: 5188 | AW19: =AV19/($AI19) -> 2.3285458 | AX19: 5482 | AY19: =AX19/($AI19) -> 2.4605027 | AZ19: 4093 | BB19: 4059 | BC19: =BB19/($AI19) -> 1.8218133 | BD19: 2309 | BE19: =BD19/($AI19) -> 1.0363555 | BF19: 2476 | BG19: =BF19/($AI19) -> 1.1113106 | BH19: 2375 | BI19: =BH19/($AI19) -> 1.0659785 | BK19: 2955 | BL19: =BK19/($AI19) -> 1.3263016 | BM19: 2440 | BN19: =BM19/($AI19) -> 1.0951526 | BO19: 2465 | BP19: =BO19/($AI19) -> 1.1063734 | BQ19: 2924 | BR19: =BQ19/($AI19) -> 1.3123878 | BS19: 2760 | BT19: =BS19/($AI19) -> 1.2387792 | BU19: 2703 | BV19: =BU19/($AI19) -> 1.2131957 | BW19: 2427 | BX19: =BW19/($AI19) -> 1.0893178 | BY19: 2623 | BZ19: =BY19/($AI19) -> 1.177289 | CA19: 2444 | CB19: =CA19/($AI19) -> 1.0969479 | CC19: 2660 | CD19: =CC19/($AI19) -> 1.1938959 | CE19: 2471 | CF19: =CE19/($AI19) -> 1.1090664 | CG19: 2297 | CH19: =CG19/($AI19) -> 1.0309695 | CI19: 2186 | CJ19: =CI19/($AI19) -> 0.98114901 | CK19: 2336 | CL19: =CK19/($AI19) -> 1.048474 | CM19: 2354 | CN19: =CM19/($AI19) -> 1.056553 | CO19: 2351 | CP19: =CO19/($AI19) -> 1.0552065 | CQ19: 2188 | CR19: =CQ19/($AI19) -> 0.98204668 | CS19: 3215 | CT19: =CS19/($AI19) -> 1.4429982 | CU19: 2269 | CV19: =CU19/($AI19) -> 1.0184022 | CW19: 1834 | CX19: =CW19/($AI19) -> 0.82315978 | CY19: 2491 | DA19: 3260 | DC19: 3227 | DE19: 3846 | DG19: 2698
B20: WO30_Wohnsituation_Haushalt_Person_Hinzufuegen | C20: =E20 -> {"name":p.FamilyName1,"vorname":p.ManFirstName2,"geburtsdatum":p.BirthdayKid2,"ahvNumber":p.AHVNumber4,"personInhausltVon":"01.11.2025","inHauslt":"Übernehmen","ereignis":"Geburt"} | E20: =F20&G20&H20&I20&J20&K20&L20&M20&N20&O20&P20&Q20&R20&S20&T20&U20&V20&W20&X20 -> {"name":p.FamilyName1,"vorname":p.ManFirstName2,"geburtsdatum":p.BirthdayKid2,"ahvNumber":p.AHVNumber4,"personInhausltVon":"01.11.2025","inHauslt":"Übernehmen","ereignis":"Geburt"} | F20: {"name": | G20: =G19 -> p.FamilyName1 | H20: ,"vorname": | I20: =H65 -> p.ManFirstName2 | J20: ,"geburtsdatum": | K20: =J65 -> p.BirthdayKid2 | L20: ,"ahvNumber": | M20: =I65 -> p.AHVNumber4 | N20: ,"personInhausltVon":" | O20: ="01."&MONTH(TODAY())&"."&YEAR(TODAY()) -> 01.11.2025 | P20: ","inHauslt":" | Q20: Übernehmen | R20: ","ereignis":" | S20: Geburt | T20: "} | AI20: 3768 | AL20: 3446 | AM20: =AL20/($AI20) -> 0.91454352 | AN20: 4686 | AO20: =AN20/($AI20) -> 1.2436306 | AP20: 4805 | AQ20: =AP20/($AI20) -> 1.2752123 | AR20: 5276 | AS20: =AR20/($AI20) -> 1.4002123 | AT20: 5353 | AU20: =AT20/($AI20) -> 1.4206476 | AV20: 5078 | AW20: =AV20/($AI20) -> 1.3476645 | AX20: 5490 | AY20: =AX20/($AI20) -> 1.4570064 | AZ20: 4861 | BB20: 4786 | BC20: =BB20/($AI20) -> 1.2701699 | BD20: 3176 | BE20: =BD20/($AI20) -> 0.84288747 | BF20: 2698 | BG20: =BF20/($AI20) -> 0.71602972 | BH20: 3130 | BI20: =BH20/($AI20) -> 0.83067941 | BK20: 3416 | BL20: =BK20/($AI20) -> 0.90658174 | BM20: 3782 | BN20: =BM20/($AI20) -> 1.0037155 | BO20: 3406 | BP20: =BO20/($AI20) -> 0.90392781 | BQ20: 3395 | BR20: =BQ20/($AI20) -> 0.90100849 | BS20: 3792 | BT20: =BS20/($AI20) -> 1.0063694 | BU20: 3454 | BV20: =BU20/($AI20) -> 0.91666667 | BW20: 2956 | BX20: =BW20/($AI20) -> 0.78450106 | BY20: 3073 | BZ20: =BY20/($AI20) -> 0.81555202 | CA20: 3289 | CB20: =CA20/($AI20) -> 0.87287686 | CC20: 2978 | CD20: =CC20/($AI20) -> 0.7903397 | CE20: 3031 | CF20: =CE20/($AI20) -> 0.80440552 | CG20: 3312 | CH20: =CG20/($AI20) -> 0.87898089 | CI20: 3241 | CJ20: =CI20/($AI20) -> 0.860138 | CK20: 6528 | CL20: =CK20/($AI20) -> 1.7324841 | CM20: 3389 | CN20: =CM20/($AI20) -> 0.89941614 | CO20: 3310 | CP20: =CO20/($AI20) -> 0.87845011 | CQ20: 3745 | CR20: =CQ20/($AI20) -> 0.99389597 | CS20: 8095 | CT20: =CS20/($AI20) -> 2.1483546 | CU20: 3351 | CV20: =CU20/($AI20) -> 0.88933121 | CW20: 3878 | CX20: =CW20/($AI20) -> 1.0291932 | CY20: 3723 | DA20: 3462 | DC20: 3841 | DE20: 3482 | DG20: 2962
A21: 20 | B21: DO11_Dossier_Search_Lupe | C21: =E21 -> {"searchDossierOrKlient":p.DossierName1,"resultType":"Dossiers"} | E21: =F21&G21&H21&I21&J21&K21&L21&M21&N21&O21&P21&Q21&R21&S21&T21&U21&V21&W21&X21 -> {"searchDossierOrKlient":p.DossierName1,"resultType":"Dossiers"} | F21: {"searchDossierOrKlient": | G21: ='001x'!$G$11 -> p.DossierName1 | H21: ,"resultType":" | I21: Dossiers | J21: "} | AI21: 5018 | AL21: 5017 | AM21: =AL21/($AI21) -> 0.99980072 | AN21: 5008 | AO21: =AN21/($AI21) -> 0.99800717 | AP21: 5007 | AQ21: =AP21/($AI21) -> 0.99780789 | AR21: 5223 | AS21: =AR21/($AI21) -> 1.0408529 | AT21: 5240 | AU21: =AT21/($AI21) -> 1.0442407 | AV21: 5055 | AW21: =AV21/($AI21) -> 1.0073735 | AX21: 5244 | AY21: =AX21/($AI21) -> 1.0450379 | AZ21: 4446 | BB21: 4534 | BC21: =BB21/($AI21) -> 0.90354723 | BD21: 2459 | BE21: =BD21/($AI21) -> 0.49003587 | BF21: 2627 | BG21: =BF21/($AI21) -> 0.52351534 | BH21: 2748 | BI21: =BH21/($AI21) -> 0.54762854 | BK21: 2980 | BL21: =BK21/($AI21) -> 0.5938621 | BM21: 8189 | BN21: =BM21/($AI21) -> 1.6319251 | BO21: 2925 | BP21: =BO21/($AI21) -> 0.58290155 | BQ21: 2789 | BR21: =BQ21/($AI21) -> 0.55579912 | BS21: 2861 | BT21: =BS21/($AI21) -> 0.57014747 | BU21: 2881 | BV21: =BU21/($AI21) -> 0.57413312 | BW21: 2922 | BX21: =BW21/($AI21) -> 0.58230371 | BY21: 2740 | BZ21: =BY21/($AI21) -> 0.54603428 | CA21: 3240 | CB21: =CA21/($AI21) -> 0.64567557 | CC21: 2640 | CD21: =CC21/($AI21) -> 0.52610602 | CE21: 3066 | CF21: =CE21/($AI21) -> 0.6110004 | CG21: 2531 | CH21: =CG21/($AI21) -> 0.50438422 | CI21: 2500 | CJ21: =CI21/($AI21) -> 0.49820646 | CK21: 3370 | CL21: =CK21/($AI21) -> 0.6715823 | CM21: 3339 | CN21: =CM21/($AI21) -> 0.66540454 | CO21: 3747 | CP21: =CO21/($AI21) -> 0.74671184 | CQ21: 4278 | CR21: =CQ21/($AI21) -> 0.85253089 | CS21: 3727 | CT21: =CS21/($AI21) -> 0.74272619 | CU21: 3740 | CV21: =CU21/($AI21) -> 0.74531686 | CW21: 3853 | CX21: =CW21/($AI21) -> 0.76783579 | CY21: 3583 | DA21: 2761 | DC21: 2974 | DE21: 2892 | DG21: 2781
B22: WO32_01b_Wohnsituation_Haushalt_Wohnung_anpassen | C22: =E22 -> {"vermieter":"Graber Immobilien","wohnungsgrosse":"4 Zimmer","mietkosten":3000,"nebenkosten":300} | E22: =F22&G22&H22&I22&J22&K22&L22&M22&N22&O22&P22&Q22&R22&S22&T22&U22&V22&W22&X22 -> {"vermieter":"Graber Immobilien","wohnungsgrosse":"4 Zimmer","mietkosten":3000,"nebenkosten":300} | F22: {"vermieter":" | G22: Graber Immobilien | H22: ","wohnungsgrosse":" | I22: 4 Zimmer | J22: ","mietkosten": | K22: 3000 | L22: ,"nebenkosten": | M22: 300 | N22: } | AI22: 2656 | AL22: 2912 | AM22: =AL22/($AI22) -> 1.0963855 | AN22: 4161 | AO22: =AN22/($AI22) -> 1.5666416 | AP22: 4394 | AQ22: =AP22/($AI22) -> 1.6543675 | AR22: 11040 | AS22: =AR22/($AI22) -> 4.1566265 | AT22: 11254 | AU22: =AT22/($AI22) -> 4.2371988 | AV22: 11193 | AW22: =AV22/($AI22) -> 4.2142319 | AX22: 10765 | AY22: =AX22/($AI22) -> 4.0530873 | AZ22: 3743 | BB22: 3727 | BC22: =BB22/($AI22) -> 1.403238 | BD22: 5066 | BE22: =BD22/($AI22) -> 1.9073795 | BF22: 5061 | BG22: =BF22/($AI22) -> 1.905497 | BH22: 4955 | BI22: =BH22/($AI22) -> 1.8655873 | BK22: 5193 | BL22: =BK22/($AI22) -> 1.9551958 | BM22: 6491 | BN22: =BM22/($AI22) -> 2.4439006 | BO22: 5502 | BP22: =BO22/($AI22) -> 2.0715361 | BQ22: 5250 | BR22: =BQ22/($AI22) -> 1.9766566 | BS22: 5454 | BT22: =BS22/($AI22) -> 2.0534639 | BU22: 5295 | BV22: =BU22/($AI22) -> 1.9935994 | BW22: 5422 | BX22: =BW22/($AI22) -> 2.0414157 | BY22: 5319 | BZ22: =BY22/($AI22) -> 2.0026355 | CA22: 5434 | CB22: =CA22/($AI22) -> 2.0459337 | CC22: 4937 | CD22: =CC22/($AI22) -> 1.8588102 | CE22: 2683 | CF22: =CE22/($AI22) -> 1.0101657 | CG22: 2278 | CH22: =CG22/($AI22) -> 0.85768072 | CI22: 2737 | CJ22: =CI22/($AI22) -> 1.030497 | CK22: 5151 | CL22: =CK22/($AI22) -> 1.9393825 | CM22: 5060 | CN22: =CM22/($AI22) -> 1.9051205 | CO22: 5018 | CP22: =CO22/($AI22) -> 1.8893072 | CQ22: 5676 | CR22: =CQ22/($AI22) -> 2.1370482 | CS22: 5499 | CT22: =CS22/($AI22) -> 2.0704066 | CU22: 5544 | CV22: =CU22/($AI22) -> 2.0873494 | CW22: 5403 | CX22: =CW22/($AI22) -> 2.034262 | CY22: 5391
B23: KL01_Klientschaft_select | C23: =E23 -> {"dossier":p.DossierName1,"klientschaft":`${p.FamilyName1}, ${p.ManFirstName1}`} | E23: =F23&G23&H23&I23&J23&K23&L23&M23&N23&O23&P23&Q23&R23&S23&T23&U23&V23&W23&X23 -> {"dossier":p.DossierName1,"klientschaft":`${p.FamilyName1}, ${p.ManFirstName1}`} | F23: {"dossier": | G23: =G11 -> p.DossierName1 | H23: ,"klientschaft":` | I23: ="${"&$G$4&"}, ${"&$I$4&"}" -> ${p.FamilyName1}, ${p.ManFirstName1} | J23: `} | AI23: 9006 | AL23: 9017 | AM23: =AL23/($AI23) -> 1.0012214 | AN23: 9018 | AO23: =AN23/($AI23) -> 1.0013324 | AP23: 9010 | AQ23: =AP23/($AI23) -> 1.0004441 | AR23: 5023 | AS23: =AR23/($AI23) -> 0.55773928 | AT23: 5019 | AU23: =AT23/($AI23) -> 0.55729514 | AV23: 5007 | AW23: =AV23/($AI23) -> 0.55596269 | AX23: 5020 | AY23: =AX23/($AI23) -> 0.55740617 | AZ23: 5005 | BB23: 5019 | BC23: =BB23/($AI23) -> 0.55729514 | BD23: 2737 | BE23: =BD23/($AI23) -> 0.30390851 | BF23: 2842 | BG23: =BF23/($AI23) -> 0.3155674 | BH23: 2719 | BI23: =BH23/($AI23) -> 0.30190984 | BK23: 2814 | BL23: =BK23/($AI23) -> 0.31245836 | BM23: 3135 | BN23: =BM23/($AI23) -> 0.34810127 | BO23: 2783 | BP23: =BO23/($AI23) -> 0.30901621 | BQ23: 2661 | BR23: =BQ23/($AI23) -> 0.29546969 | BS23: 2900 | BT23: =BS23/($AI23) -> 0.32200755 | BU23: 2926 | BV23: =BU23/($AI23) -> 0.32489451 | BW23: 2996 | BX23: =BW23/($AI23) -> 0.33266711 | BY23: 2749 | BZ23: =BY23/($AI23) -> 0.30524095 | CA23: 2685 | CB23: =CA23/($AI23) -> 0.29813458 | CC23: 2806 | CD23: =CC23/($AI23) -> 0.31157006 | CE23: 2927 | CF23: =CE23/($AI23) -> 0.32500555 | CG23: 2561 | CH23: =CG23/($AI23) -> 0.28436598 | CI23: 2736 | CJ23: =CI23/($AI23) -> 0.30379747 | CK23: 2636 | CL23: =CK23/($AI23) -> 0.29269376 | CM23: 3184 | CN23: =CM23/($AI23) -> 0.35354208 | CO23: 2566 | CP23: =CO23/($AI23) -> 0.28492116 | CQ23: 2392 | CR23: =CQ23/($AI23) -> 0.26560071 | CS23: 3157 | CT23: =CS23/($AI23) -> 0.35054408 | CU23: 3228 | CV23: =CU23/($AI23) -> 0.35842771 | CW23: 2712 | CX23: =CW23/($AI23) -> 0.30113258 | CY23: 2847 | DA23: 5812 | DC23: 5510 | DE23: 4776 | DG23: 4469
B24: E01_Delay | C24: {"Pause":"6000"} | AI24: 2011 | AL24: 2008 | AM24: =AL24/($AI24) -> 0.9985082 | AN24: 2011 | AO24: =AN24/($AI24) -> 1 | AQ24: =AP24/($AI24) -> 0 | AR24: 2013 | AS24: =AR24/($AI24) -> 1.0009945 | AT24: 2020 | AU24: =AT24/($AI24) -> 1.0044754 | AV24: 2017 | AW24: =AV24/($AI24) -> 1.0029836 | AX24: 2019 | AY24: =AX24/($AI24) -> 1.0039781 | AZ24: 2013 | BB24: 341 | BC24: =BB24/($AI24) -> 0.16956738 | BD24: 2007 | BE24: =BD24/($AI24) -> 0.99801094 | BF24: 2003 | BG24: =BF24/($AI24) -> 0.99602188 | BH24: 2009 | BI24: =BH24/($AI24) -> 0.99900547 | BK24: 2019 | BL24: =BK24/($AI24) -> 1.0039781 | BM24: 2008 | BN24: =BM24/($AI24) -> 0.9985082 | BO24: 2005 | BP24: =BO24/($AI24) -> 0.99701641 | BQ24: 2012 | BR24: =BQ24/($AI24) -> 1.0004973 | BS24: 2004 | BT24: =BS24/($AI24) -> 0.99651914 | BU24: 2005 | BV24: =BU24/($AI24) -> 0.99701641 | BW24: 2013 | BX24: =BW24/($AI24) -> 1.0009945 | BY24: 2013 | BZ24: =BY24/($AI24) -> 1.0009945 | CA24: 2006 | CB24: =CA24/($AI24) -> 0.99751367 | CC24: 2006 | CD24: =CC24/($AI24) -> 0.99751367 | CE24: 2015 | CF24: =CE24/($AI24) -> 1.0019891 | CG24: 2010 | CH24: =CG24/($AI24) -> 0.99950273 | CI24: 2012 | CJ24: =CI24/($AI24) -> 1.0004973 | CK24: 2005 | CL24: =CK24/($AI24) -> 0.99701641 | CN24: =CM24/($AI24) -> 0 | CO24: 4190 | CP24: =CO24/($AI24) -> 2.0835405 | CQ24: 4228 | CR24: =CQ24/($AI24) -> 2.1024366 | CS24: 4085 | CT24: =CS24/($AI24) -> 2.0313277 | CU24: 4191 | CV24: =CU24/($AI24) -> 2.0840378 | CW24: 4489 | CX24: =CW24/($AI24) -> 2.2322228 | CY24: 5077
B25: KL03_ErwerbsituationEinnahmen_Lohn_erfassen | C25: =E25 -> {"zahlbarDurch":"BKW Energie AG","pensumm":"100","betrag":"1000","gueltigVon":"01.01.2025","gueltigBis":"31.12.2025","checkbox":"x"} | E25: =F25&G25&H25&I25&J25&K25&L25&M25&N25&O25&P25&Q25&R25&S25&T25&U25&V25&W25&X25 -> {"zahlbarDurch":"BKW Energie AG","pensumm":"100","betrag":"1000","gueltigVon":"01.01.2025","gueltigBis":"31.12.2025","checkbox":"x"} | F25: { | H25: "zahlbarDurch":" | I25: BKW Energie AG | J25: ","pensumm":" | K25: 100 | L25: ","betrag":" | M25: 1000 | N25: ","gueltigVon":" | O25: ="01.01."&YEAR(TODAY()) -> 01.01.2025 | P25: ","gueltigBis":" | Q25: ="31.12."&YEAR(TODAY()) -> 31.12.2025 | R25: ","checkbox":" | S25: x | T25: "} | AI25: 10643 | AL25: 11047 | AM25: =AL25/($AI25) -> 1.0379592 | AN25: 11734 | AO25: =AN25/($AI25) -> 1.1025087 | AP25: 12167 | AQ25: =AP25/($AI25) -> 1.1431927 | AR25: 11254 | AS25: =AR25/($AI25) -> 1.0574086 | AT25: 11496 | AU25: =AT25/($AI25) -> 1.0801466 | AV25: 11443 | AW25: =AV25/($AI25) -> 1.0751668 | AX25: 11104 | AY25: =AX25/($AI25) -> 1.0433149 | AZ25: 4691 | BB25: 4695 | BC25: =BB25/($AI25) -> 0.44113502 | BD25: 4689 | BE25: =BD25/($AI25) -> 0.44057127 | BF25: 4733 | BG25: =BF25/($AI25) -> 0.44470544 | BH25: 4865 | BI25: =BH25/($AI25) -> 0.45710796 | BK25: 4977 | BL25: =BK25/($AI25) -> 0.46763131 | BM25: 5121 | BN25: =BM25/($AI25) -> 0.48116133 | BO25: 5076 | BP25: =BO25/($AI25) -> 0.4769332 | BQ25: 4962 | BR25: =BQ25/($AI25) -> 0.46622193 | BS25: 5164 | BT25: =BS25/($AI25) -> 0.48520154 | BU25: 5050 | BV25: =BU25/($AI25) -> 0.47449028 | BW25: 5029 | BX25: =BW25/($AI25) -> 0.47251715 | BY25: 5045 | BZ25: =BY25/($AI25) -> 0.47402048 | CA25: 5105 | CB25: =CA25/($AI25) -> 0.47965799 | CC25: 4650 | CD25: =CC25/($AI25) -> 0.43690689 | CE25: 2082 | CF25: =CE25/($AI25) -> 0.19562154 | CG25: 1950 | CH25: =CG25/($AI25) -> 0.18321902 | CI25: 1980 | CJ25: =CI25/($AI25) -> 0.18603777 | CK25: 5065 | CL25: =CK25/($AI25) -> 0.47589965 | CM25: 7022 | CN25: =CM25/($AI25) -> 0.65977638 | CO25: 5085 | CP25: =CO25/($AI25) -> 0.47777882 | CQ25: 5042 | CR25: =CQ25/($AI25) -> 0.47373861 | CS25: 7032 | CT25: =CS25/($AI25) -> 0.66071596 | CU25: 4971 | CV25: =CU25/($AI25) -> 0.46706756 | CW25: 4855 | CX25: =CW25/($AI25) -> 0.45616837 | CY25: 5595
B26: KL0X_ErwerbsituationEinnahmen_erfassen | C26: =E26 -> {"dossier":p.DossierName1,"klientschaft":`${p.FamilyName1}, ${p.ManFirstName1}`,"topMenu":"Erwerbseinkommen","subMenu":"Unselbständiges Erwerbseinkommen","zahlbarDurch":"Berner Schuldenberatung","pensumm":"30","13Ja":"x","betrag":"1500","gueltigVon":"01.01.2025","gueltigBis":"31.12.2025","schweregrad":""} | E26: =F26&G26&H26&I26&J26&K26&L26&M26&N26&O26&P26&Q26&R26&S26&T26&U26&V26&W26&X26&Y26&Z26&AA26&AB26&AC26 -> {"dossier":p.DossierName1,"klientschaft":`${p.FamilyName1}, ${p.ManFirstName1}`,"topMenu":"Erwerbseinkommen","subMenu":"Unselbständiges Erwerbseinkommen","zahlbarDurch":"Berner Schuldenberatung","pensumm":"30","13Ja":"x","betrag":"1500","gueltigVon":"01.01.2025","gueltigBis":"31.12.2025","schweregrad":""} | F26: {"dossier": | G26: =G23 -> p.DossierName1 | H26: ,"klientschaft":` | I26: =I23 -> ${p.FamilyName1}, ${p.ManFirstName1} | J26: `,"topMenu":" | K26: Erwerbseinkommen | L26: ","subMenu":" | M26: Unselbständiges Erwerbseinkommen | N26: ","zahlbarDurch":" | O26: Berner Schuldenberatung | P26: ","pensumm":" | Q26: 30 | R26: ","13Ja":" | S26: x | T26: ","betrag":" | U26: 1500 | V26: ","gueltigVon":" | W26: =O25 -> 01.01.2025 | X26: ","gueltigBis":" | Y26: ="31.12."&YEAR(TODAY()) -> 31.12.2025 | Z26: ","schweregrad":" | AB26: "}
B27: DO11_Dossier_Search_Lupe | C27: =E27 -> {"searchDossierOrKlient":p.DossierName1,"resultType":"Dossiers"} | E27: =F27&G27&H27&I27&J27&K27&L27&M27&N27&O27&P27&Q27&R27&S27&T27&U27&V27&W27&X27 -> {"searchDossierOrKlient":p.DossierName1,"resultType":"Dossiers"} | F27: {"searchDossierOrKlient": | G27: ='001x'!$G$11 -> p.DossierName1 | H27: ,"resultType":" | I27: Dossiers | J27: "} | AI27: 9010 | AL27: 9011 | AM27: =AL27/($AI27) -> 1.000111 | AN27: 9018 | AO27: =AN27/($AI27) -> 1.0008879 | AP27: 9018 | AQ27: =AP27/($AI27) -> 1.0008879 | AR27: 5022 | AS27: =AR27/($AI27) -> 0.55738069 | AT27: 5012 | AU27: =AT27/($AI27) -> 0.55627081 | AV27: 5031 | AW27: =AV27/($AI27) -> 0.55837958 | AX27: 5018 | AY27: =AX27/($AI27) -> 0.55693674 | AZ27: 5020 | BB27: 5041 | BC27: =BB27/($AI27) -> 0.55948946 | BD27: 3302 | BE27: =BD27/($AI27) -> 0.36648169 | BF27: 3479 | BG27: =BF27/($AI27) -> 0.38612653 | BH27: 3266 | BI27: =BH27/($AI27) -> 0.36248613 | BK27: 4147 | BL27: =BK27/($AI27) -> 0.46026637 | BM27: 4209 | BN27: =BM27/($AI27) -> 0.46714761 | BO27: 3541 | BP27: =BO27/($AI27) -> 0.39300777 | BQ27: 3635 | BR27: =BQ27/($AI27) -> 0.40344062 | BS27: 3543 | BT27: =BS27/($AI27) -> 0.39322974 | BU27: 3571 | BV27: =BU27/($AI27) -> 0.3963374 | BW27: 3634 | BX27: =BW27/($AI27) -> 0.40332963 | BY27: 3696 | BZ27: =BY27/($AI27) -> 0.41021088 | CA27: 5331 | CB27: =CA27/($AI27) -> 0.59167592 | CC27: 4098 | CD27: =CC27/($AI27) -> 0.45482797 | CE27: 3367 | CF27: =CE27/($AI27) -> 0.37369589 | CG27: 3179 | CH27: =CG27/($AI27) -> 0.35283019 | CI27: 3291 | CJ27: =CI27/($AI27) -> 0.36526082 | CK27: 4436 | CL27: =CK27/($AI27) -> 0.49234184 | CM27: 5052 | CN27: =CM27/($AI27) -> 0.56071032 | CO27: 7170 | CP27: =CO27/($AI27) -> 0.79578246 | CQ27: 6100 | CR27: =CQ27/($AI27) -> 0.67702553 | CS27: 4629 | CT27: =CS27/($AI27) -> 0.51376249 | CU27: 3720 | CV27: =CU27/($AI27) -> 0.41287458 | CW27: 4812 | CX27: =CW27/($AI27) -> 0.53407325 | CY27: 6623 | DA27: 6895 | DC27: 6145 | DE27: 4781 | DG27: 4976
B28: E01_Delay | C28: {"Pause":"6000"} | AI28: 2011 | AL28: 2008 | AM28: =AL28/($AI28) -> 0.9985082 | AN28: 2011 | AO28: =AN28/($AI28) -> 1 | AQ28: =AP28/($AI28) -> 0 | AR28: 2013 | AS28: =AR28/($AI28) -> 1.0009945 | AT28: 2020 | AU28: =AT28/($AI28) -> 1.0044754 | AV28: 2017 | AW28: =AV28/($AI28) -> 1.0029836 | AX28: 2019 | AY28: =AX28/($AI28) -> 1.0039781 | AZ28: 2013 | BB28: 341 | BC28: =BB28/($AI28) -> 0.16956738 | BD28: 2007 | BE28: =BD28/($AI28) -> 0.99801094 | BF28: 2003 | BG28: =BF28/($AI28) -> 0.99602188 | BH28: 2009 | BI28: =BH28/($AI28) -> 0.99900547 | BK28: 2019 | BL28: =BK28/($AI28) -> 1.0039781 | BM28: 2008 | BN28: =BM28/($AI28) -> 0.9985082 | BO28: 2005 | BP28: =BO28/($AI28) -> 0.99701641 | BQ28: 2012 | BR28: =BQ28/($AI28) -> 1.0004973 | BS28: 2004 | BT28: =BS28/($AI28) -> 0.99651914 | BU28: 2005 | BV28: =BU28/($AI28) -> 0.99701641 | BW28: 2013 | BX28: =BW28/($AI28) -> 1.0009945 | BY28: 2013 | BZ28: =BY28/($AI28) -> 1.0009945 | CA28: 2006 | CB28: =CA28/($AI28) -> 0.99751367 | CC28: 2006 | CD28: =CC28/($AI28) -> 0.99751367 | CE28: 2015 | CF28: =CE28/($AI28) -> 1.0019891 | CG28: 2010 | CH28: =CG28/($AI28) -> 0.99950273 | CI28: 2012 | CJ28: =CI28/($AI28) -> 1.0004973 | CK28: 2005 | CL28: =CK28/($AI28) -> 0.99701641 | CN28: =CM28/($AI28) -> 0 | CO28: 4190 | CP28: =CO28/($AI28) -> 2.0835405 | CQ28: 4228 | CR28: =CQ28/($AI28) -> 2.1024366 | CS28: 4085 | CT28: =CS28/($AI28) -> 2.0313277 | CU28: 4191 | CV28: =CU28/($AI28) -> 2.0840378 | CW28: 4489 | CX28: =CW28/($AI28) -> 2.2322228 | CY28: 5077 | DA28: 5624 | DC28: 5469 | DE28: 4557 | DG28: 4480
A29: 31 | B29: A01_AnspruchPruefung_Bedarfspruefung | C29: =E29 -> {"entscheidVom":"04.11.2025","begrundung":"Gar keine Begründung","unterstutzungab":"01.11.2025"} | E29: =F29&G29&H29&I29&J29&K29&L29&M29&N29&O29&P29&Q29&R29&S29&T29&U29&V29&W29&X29 -> {"entscheidVom":"04.11.2025","begrundung":"Gar keine Begründung","unterstutzungab":"01.11.2025"} | F29: {"entscheidVom":" | G29: =TEXT(TEXT(TODAY(),"DD")&"."&TEXT(TODAY(),"MM")&"."&TEXT(TODAY(),"YYYY"),"DD.MM.YYYY") -> 04.11.2025 | H29: ","begrundung":" | I29: Gar keine Begründung | J29: ","unterstutzungab":" | K29: ="01."&TEXT(TODAY(),"MM")&"."&TEXT(TODAY(),"YYYY") -> 01.11.2025 | L29: "} | AI29: 10495 | AL29: 10709 | AM29: =AL29/($AI29) -> 1.0203907 | AN29: 10873 | AO29: =AN29/($AI29) -> 1.0360172 | AP29: 11340 | AQ29: =AP29/($AI29) -> 1.0805145 | AR29: 10826 | AS29: =AR29/($AI29) -> 1.0315388 | AT29: 11092 | AU29: =AT29/($AI29) -> 1.0568842 | AV29: 11079 | AW29: =AV29/($AI29) -> 1.0556455 | AX29: 10608 | AY29: =AX29/($AI29) -> 1.010767 | AZ29: 2528 | BB29: 2494 | BC29: =BB29/($AI29) -> 0.23763697 | BD29: 4818 | BE29: =BD29/($AI29) -> 0.45907575 | BF29: 4986 | BG29: =BF29/($AI29) -> 0.47508337 | BH29: 4682 | BI29: =BH29/($AI29) -> 0.4461172 | BK29: 5051 | BL29: =BK29/($AI29) -> 0.4812768 | BM29: 5031 | BN29: =BM29/($AI29) -> 0.47937113 | BO29: 5232 | BP29: =BO29/($AI29) -> 0.49852311 | BQ29: 4963 | BR29: =BQ29/($AI29) -> 0.47289185 | BS29: 5160 | BT29: =BS29/($AI29) -> 0.4916627 | BU29: 5138 | BV29: =BU29/($AI29) -> 0.48956646 | BW29: 5040 | BX29: =BW29/($AI29) -> 0.48022868 | BY29: 5220 | BZ29: =BY29/($AI29) -> 0.4973797 | CA29: 5673 | CB29: =CA29/($AI29) -> 0.54054312 | CC29: 4745 | CD29: =CC29/($AI29) -> 0.45212006 | CE29: 2293 | CF29: =CE29/($AI29) -> 0.21848499 | CG29: 2166 | CH29: =CG29/($AI29) -> 0.20638399 | CI29: 2801 | CJ29: =CI29/($AI29) -> 0.26688899 | CK29: 4114 | CL29: =CK29/($AI29) -> 0.39199619 | CM29: 4135 | CN29: =CM29/($AI29) -> 0.39399714 | CO29: 14738 | CP29: =CO29/($AI29) -> 1.4042878 | CQ29: 6010 | CR29: =CQ29/($AI29) -> 0.57265364 | CS29: 6012 | CT29: =CS29/($AI29) -> 0.57284421 | CU29: 6009 | CV29: =CU29/($AI29) -> 0.57255836 | CW29: 6010 | CX29: =CW29/($AI29) -> 0.57265364 | CY29: 6006 | DA29: 6013 | DC29: 6017 | DE29: 6006 | DG29: 6014
B30: E01_Delay | C30: {"Pause":"6000"} | AI30: 2011 | AL30: 2008 | AM30: =AL30/($AI30) -> 0.9985082 | AN30: 2011 | AO30: =AN30/($AI30) -> 1 | AQ30: =AP30/($AI30) -> 0 | AR30: 2013 | AS30: =AR30/($AI30) -> 1.0009945 | AT30: 2020 | AU30: =AT30/($AI30) -> 1.0044754 | AV30: 2017 | AW30: =AV30/($AI30) -> 1.0029836 | AX30: 2019 | AY30: =AX30/($AI30) -> 1.0039781 | AZ30: 2013 | BB30: 341 | BC30: =BB30/($AI30) -> 0.16956738 | BD30: 2007 | BE30: =BD30/($AI30) -> 0.99801094 | BF30: 2003 | BG30: =BF30/($AI30) -> 0.99602188 | BH30: 2009 | BI30: =BH30/($AI30) -> 0.99900547 | BK30: 2019 | BL30: =BK30/($AI30) -> 1.0039781 | BM30: 2008 | BN30: =BM30/($AI30) -> 0.9985082 | BO30: 2005 | BP30: =BO30/($AI30) -> 0.99701641 | BQ30: 2012 | BR30: =BQ30/($AI30) -> 1.0004973 | BS30: 2004 | BT30: =BS30/($AI30) -> 0.99651914 | BU30: 2005 | BV30: =BU30/($AI30) -> 0.99701641 | BW30: 2013 | BX30: =BW30/($AI30) -> 1.0009945 | BY30: 2013 | BZ30: =BY30/($AI30) -> 1.0009945 | CA30: 2006 | CB30: =CA30/($AI30) -> 0.99751367 | CC30: 2006 | CD30: =CC30/($AI30) -> 0.99751367 | CE30: 2015 | CF30: =CE30/($AI30) -> 1.0019891 | CG30: 2010 | CH30: =CG30/($AI30) -> 0.99950273 | CI30: 2012 | CJ30: =CI30/($AI30) -> 1.0004973 | CK30: 2005 | CL30: =CK30/($AI30) -> 0.99701641 | CN30: =CM30/($AI30) -> 0 | CO30: 3307 | CP30: =CO30/($AI30) -> 1.6444555 | CQ30: 12881 | CR30: =CQ30/($AI30) -> 6.405271 | CS30: 16955 | CT30: =CS30/($AI30) -> 8.4311288 | CU30: 17778 | CV30: =CU30/($AI30) -> 8.8403779 | CW30: 21192 | CX30: =CW30/($AI30) -> 10.538041 | CY30: 21674 | DA30: 13839 | DC30: 12390 | DE30: 15752 | DG30: 0 | DH30: Error: locator.click: Error: strict mode violation: getByRole('button', { name: /Bedarfsprüfung sichern|Enregistrer l'évaluation des besoins/i }) resolved to 2 elements: 1) <button tabindex="0" role="button" mat-flat-button="" mat-ripple-loader-uninitialized="" mat-ripple-loader-class-name="mat-mdc-button-ripple" class="primary mdc-button mdc-button--unelevated mat-mdc-unelevated-button mat-unthemed mat-mdc-button-base">…</button> aka locator('#cdk-accordion-child-0').getByRole('button', { name: 'Bedarfsprüfung sichern' }) 2) <button tabindex="0" role="button" mat-flat-button="" mat-ripple-loader-uninitialized="" mat-ripple-loader-class-name="mat-mdc-button-ripple" class="primary mdc-button mdc-button--unelevated mat-mdc-unelevated-button mat-unthemed mat-mdc-button-base">…</button> aka locator('#cdk-accordion-child-1').getByRole('button', { name: 'Bedarfsprüfung sichern' })Call log:[2m - waiting for getByRole('button', { name: /Bedarfsprüfung sichern|Enregistrer l'évaluation des besoins/i })[22m Screenshots: C:\Aventis\Aventis_Playwright-\test-results\videos\006_KeyWords_Smoketest_V2-001a-001a-Microsoft-Edge\test-failed-1.png Videos: C:\Aventis\Aventis_Playwright-\test-results\videos\006_KeyWords_Smoketest_V2-001a-001a-Microsoft-Edge\video.webm
B31: R01_Rahmenbudget_Wohnkosten_Anpassen_V2 | C31: =E31 -> {"ubernahmeWohnkostenCFH":"100","uebernahmeWohnkostenVon":"01.11.2025","uebernahmeWohnkostenBis":"27.01.2026","uebernahemBegruendung":"Die Wohnungen sind teuer hier"} | E31: =F31&G31&H31&I31&J31&K31&L31&M31&N31&O31&P31&Q31&R31&S31&T31&U31&V31&W31&X31 -> {"ubernahmeWohnkostenCFH":"100","uebernahmeWohnkostenVon":"01.11.2025","uebernahmeWohnkostenBis":"27.01.2026","uebernahemBegruendung":"Die Wohnungen sind teuer hier"} | F31: {"ubernahmeWohnkostenCFH":" | G31: 100 | H31: ","uebernahmeWohnkostenVon":" | I31: ="01."&TEXT(TODAY(),"MM")&"."&TEXT(TODAY(),"YYYY") -> 01.11.2025 | J31: ","uebernahmeWohnkostenBis":" | K31: ="27."&TEXT(MONTH(TODAY()+180),"MM")&"."&YEAR(TODAY()+180) -> 27.01.2026 | L31: ","uebernahemBegruendung":" | M31: Die Wohnungen sind teuer hier | N31: "} | AI31: 4020 | AL31: 11003 | AM31: =AL31/($AI31) -> 2.7370647 | AN31: 11012 | AO31: =AN31/($AI31) -> 2.7393035 | AP31: 11006 | AQ31: =AP31/($AI31) -> 2.7378109 | AR31: 5009 | AS31: =AR31/($AI31) -> 1.2460199 | AT31: 5011 | AU31: =AT31/($AI31) -> 1.2465174 | AV31: 5008 | AW31: =AV31/($AI31) -> 1.2457711 | AX31: 5012 | AY31: =AX31/($AI31) -> 1.2467662 | AZ31: 5024 | BB31: 5015 | BC31: =BB31/($AI31) -> 1.2475124 | BD31: 10299 | BE31: =BD31/($AI31) -> 2.5619403 | BF31: 10599 | BG31: =BF31/($AI31) -> 2.6365672 | BH31: 10000 | BI31: =BH31/($AI31) -> 2.4875622 | BK31: 11394 | BL31: =BK31/($AI31) -> 2.8343284 | BM31: 11719 | BN31: =BM31/($AI31) -> 2.9151741 | BO31: 11299 | BP31: =BO31/($AI31) -> 2.8106965 | BQ31: 12154 | BR31: =BQ31/($AI31) -> 3.0233831 | BS31: 11838 | BT31: =BS31/($AI31) -> 2.9447761 | BU31: 12116 | BV31: =BU31/($AI31) -> 3.0139303 | BW31: 11604 | BX31: =BW31/($AI31) -> 2.8865672 | BY31: 11074 | BZ31: =BY31/($AI31) -> 2.7547264 | CA31: 11733 | CB31: =CA31/($AI31) -> 2.9186567 | CC31: 11719 | CD31: =CC31/($AI31) -> 2.9151741 | CE31: 10325 | CF31: =CE31/($AI31) -> 2.568408 | CG31: 9157 | CH31: =CG31/($AI31) -> 2.2778607 | CI31: 9700 | CJ31: =CI31/($AI31) -> 2.4129353 | CK31: 18332 | CL31: =CK31/($AI31) -> 4.560199 | CM31: 11574 | CN31: =CM31/($AI31) -> 2.8791045 | CO31: 0 | CP31: =CO31/($AI31) -> 0 | CQ31: 6015 | CR31: =CQ31/($AI31) -> 1.4962687 | CS31: 6006 | CT31: =CS31/($AI31) -> 1.4940299 | CU31: 6015 | CV31: =CU31/($AI31) -> 1.4962687 | CW31: 6003 | CX31: =CW31/($AI31) -> 1.4932836 | CY31: 6010
A32: 50 | B32: E01_Delay | C32: {"Pause":"6000"} | AI32: 2011 | AL32: 2008 | AM32: =AL32/($AI32) -> 0.9985082 | AN32: 2011 | AO32: =AN32/($AI32) -> 1 | AQ32: =AP32/($AI32) -> 0 | AR32: 2013 | AS32: =AR32/($AI32) -> 1.0009945 | AT32: 2020 | AU32: =AT32/($AI32) -> 1.0044754 | AV32: 2017 | AW32: =AV32/($AI32) -> 1.0029836 | AX32: 2019 | AY32: =AX32/($AI32) -> 1.0039781 | AZ32: 2013 | BB32: 341 | BC32: =BB32/($AI32) -> 0.16956738 | BD32: 2007 | BE32: =BD32/($AI32) -> 0.99801094 | BF32: 2003 | BG32: =BF32/($AI32) -> 0.99602188 | BH32: 2009 | BI32: =BH32/($AI32) -> 0.99900547 | BK32: 2019 | BL32: =BK32/($AI32) -> 1.0039781 | BM32: 2008 | BN32: =BM32/($AI32) -> 0.9985082 | BO32: 2005 | BP32: =BO32/($AI32) -> 0.99701641 | BQ32: 2012 | BR32: =BQ32/($AI32) -> 1.0004973 | BS32: 2004 | BT32: =BS32/($AI32) -> 0.99651914 | BU32: 2005 | BV32: =BU32/($AI32) -> 0.99701641 | BW32: 2013 | BX32: =BW32/($AI32) -> 1.0009945 | BY32: 2013 | BZ32: =BY32/($AI32) -> 1.0009945 | CA32: 2006 | CB32: =CA32/($AI32) -> 0.99751367 | CC32: 2006 | CD32: =CC32/($AI32) -> 0.99751367 | CE32: 2015 | CF32: =CE32/($AI32) -> 1.0019891 | CG32: 2010 | CH32: =CG32/($AI32) -> 0.99950273 | CI32: 2012 | CJ32: =CI32/($AI32) -> 1.0004973 | CK32: 2005 | CL32: =CK32/($AI32) -> 0.99701641 | CN32: =CM32/($AI32) -> 0 | CO32: 3307 | CP32: =CO32/($AI32) -> 1.6444555 | CQ32: 12881 | CR32: =CQ32/($AI32) -> 6.405271 | CS32: 16955 | CT32: =CS32/($AI32) -> 8.4311288 | CU32: 17778 | CV32: =CU32/($AI32) -> 8.8403779 | CW32: 3806 | CX32: =CW32/($AI32) -> 1.8925908 | CY32: 1914 | DA32: 6014 | DC32: 6014 | DE32: 6033 | DG32: 609
A33: 35 | B33: BW01_Bewilligungs_Workflow_LeistungsEntscheid | C33: =E33 -> {"lEvonDate":"01.11.2025","lEbisDate":"03.05.2026","checkStatus":"In Bearbeitung"} | E33: =F33&G33&H33&I33&J33&K33&L33&M33&N33&O33&P33&Q33&R33&S33&T33&U33&V33&W33&X33 -> {"lEvonDate":"01.11.2025","lEbisDate":"03.05.2026","checkStatus":"In Bearbeitung"} | F33: {"lEvonDate":" | G33: =K29 -> 01.11.2025 | H33: ","lEbisDate":" | I33: =TEXT(TEXT(TODAY()+180,"DD")&"."&TEXT(TODAY()+180,"MM")&"."&TEXT(TODAY()+180,"YYYY"),"DD.MM.YYYY") -> 03.05.2026 | J33: ","checkStatus":" | K33: In Bearbeitung | L33: "} | AI33: 1017 | AL33: 1014 | AM33: =AL33/($AI33) -> 0.99705015 | AN33: 1009 | AO33: =AN33/($AI33) -> 0.99213373 | AP33: 1008 | AQ33: =AP33/($AI33) -> 0.99115044 | AR33: 1017 | AS33: =AR33/($AI33) -> 1 | AT33: 1017 | AU33: =AT33/($AI33) -> 1 | AV33: 1026 | AW33: =AV33/($AI33) -> 1.0088496 | AX33: 1017 | AY33: =AX33/($AI33) -> 1 | AZ33: 1008 | BB33: 1010 | BC33: =BB33/($AI33) -> 0.99311701 | BD33: 1944 | BE33: =BD33/($AI33) -> 1.9115044 | BF33: 1688 | BG33: =BF33/($AI33) -> 1.6597837 | BH33: 1920 | BI33: =BH33/($AI33) -> 1.8879056 | BK33: 2307 | BL33: =BK33/($AI33) -> 2.2684366 | BM33: 14554 | BN33: =BM33/($AI33) -> 14.310718 | BO33: 3635 | BP33: =BO33/($AI33) -> 3.574238 | BQ33: 2244 | BR33: =BQ33/($AI33) -> 2.2064897 | BS33: 2073 | BT33: =BS33/($AI33) -> 2.0383481 | BU33: 2891 | BV33: =BU33/($AI33) -> 2.8426745 | BW33: 2123 | BX33: =BW33/($AI33) -> 2.0875123 | BY33: 1907 | BZ33: =BY33/($AI33) -> 1.8751229 | CA33: 2856 | CB33: =CA33/($AI33) -> 2.8082596 | CC33: 1540 | CD33: =CC33/($AI33) -> 1.5142576 | CE33: 2090 | CF33: =CE33/($AI33) -> 2.0550639 | CG33: 1762 | CH33: =CG33/($AI33) -> 1.7325467 | CI33: 3116 | CJ33: =CI33/($AI33) -> 3.0639135 | CK33: 8023 | CL33: =CK33/($AI33) -> 7.8888889 | CM33: 3465 | CN33: =CM33/($AI33) -> 3.4070796 | CO33: 196 | CP33: =CO33/($AI33) -> 0.1927237 | CQ33: 1972 | CR33: =CQ33/($AI33) -> 1.9390364 | CS33: 3836 | CT33: =CS33/($AI33) -> 3.7718781 | CU33: 6759 | CV33: =CU33/($AI33) -> 6.6460177 | CW33: 6021 | CX33: =CW33/($AI33) -> 5.920354 | CY33: 6015 | DA33: 6018 | DC33: 6010 | DE33: 6016
B34: L03_LogoutAndLoginDiffAccount | C34: =E34 -> {"username":"aventis-gemeinde-ma@diartis.ch","password":"#xFymiADPk7wJG/FWMz"} | E34: =F34&G34&H34&I34&J34&K34&L34&M34&N34&O34&P34&Q34&R34&S34&T34&U34&V34&W34&X34 -> {"username":"aventis-gemeinde-ma@diartis.ch","password":"#xFymiADPk7wJG/FWMz"} | F34: {"username":" | G34: aventis-gemeinde-ma@diartis.ch | H34: ","password":" | I34: #xFymiADPk7wJG/FWMz | J34: "} | AI34: 6252 | AL34: 33296 | AM34: =AL34/($AI34) -> 5.3256558 | AN34: 16126 | AO34: =AN34/($AI34) -> 2.5793346 | AP34: 16536 | AQ34: =AP34/($AI34) -> 2.6449136 | AR34: 15591 | AS34: =AR34/($AI34) -> 2.493762 | AT34: 15851 | AU34: =AT34/($AI34) -> 2.5353487 | AV34: 15658 | AW34: =AV34/($AI34) -> 2.5044786 | AX34: 15381 | AY34: =AX34/($AI34) -> 2.4601727 | AZ34: 9955 | BB34: 9081 | BC34: =BB34/($AI34) -> 1.4524952 | BD34: 3011 | BE34: =BD34/($AI34) -> 0.48160589 | BF34: 3016 | BG34: =BF34/($AI34) -> 0.48240563 | BH34: 3014 | BI34: =BH34/($AI34) -> 0.48208573 | BK34: 3016 | BL34: =BK34/($AI34) -> 0.48240563 | BM34: 3001 | BN34: =BM34/($AI34) -> 0.4800064 | BO34: 11735 | BP34: =BO34/($AI34) -> 1.8769994 | BQ34: 11939 | BR34: =BQ34/($AI34) -> 1.9096289 | BS34: 11640 | BT34: =BS34/($AI34) -> 1.8618042 | BU34: 12070 | BV34: =BU34/($AI34) -> 1.9305822 | BW34: 11865 | BX34: =BW34/($AI34) -> 1.8977927 | BY34: 11535 | BZ34: =BY34/($AI34) -> 1.8450096 | CA34: 11390 | CB34: =CA34/($AI34) -> 1.821817 | CC34: 11301 | CD34: =CC34/($AI34) -> 1.8075816 | CE34: 10988 | CF34: =CE34/($AI34) -> 1.7575176 | CG34: 11485 | CH34: =CG34/($AI34) -> 1.8370122 | CI34: 11082 | CJ34: =CI34/($AI34) -> 1.7725528 | CK34: 15056 | CL34: =CK34/($AI34) -> 2.4081894 | CM34: 0 | CN34: =CM34/($AI34) -> 0 | CP34: =CO34/($AI34) -> 0 | CR34: =CQ34/($AI34) -> 0 | CT34: =CS34/($AI34) -> 0 | CV34: =CU34/($AI34) -> 0 | CX34: =CW34/($AI34) -> 0
A35: 37 | B35: L03_LogoutAndLoginDiffAccount | C35: =E35 -> {"username":"Bern.Sachbearbeiterin@diartis.ch","password":"XXxa22?pdTA66-S@"} | E35: =F35&G35&H35&I35&J35&K35&L35&M35&N35&O35&P35&Q35&R35&S35&T35&U35&V35&W35&X35 -> {"username":"Bern.Sachbearbeiterin@diartis.ch","password":"XXxa22?pdTA66-S@"} | F35: {"username":" | G35: Bern.Sachbearbeiterin@diartis.ch | H35: ","password":" | I35: XXxa22?pdTA66-S@ | J35: "} | AI35: 3004 | AL35: 3008 | AM35: =AL35/($AI35) -> 1.0013316 | AN35: 3006 | AO35: =AN35/($AI35) -> 1.0006658 | AP35: 3006 | AQ35: =AP35/($AI35) -> 1.0006658 | AR35: 3010 | AS35: =AR35/($AI35) -> 1.0019973 | AT35: 3018 | AU35: =AT35/($AI35) -> 1.0046605 | AV35: 3006 | AW35: =AV35/($AI35) -> 1.0006658 | AX35: 3008 | AY35: =AX35/($AI35) -> 1.0013316 | AZ35: 3007 | BB35: 3008 | BC35: =BB35/($AI35) -> 1.0013316 | BD35: 9135 | BE35: =BD35/($AI35) -> 3.0409454 | BF35: 8411 | BG35: =BF35/($AI35) -> 2.7999334 | BH35: 9333 | BI35: =BH35/($AI35) -> 3.1068575 | BK35: 9239 | BL35: =BK35/($AI35) -> 3.0755659 | BM35: 9147 | BN35: =BM35/($AI35) -> 3.0449401 | BO35: 9040 | BP35: =BO35/($AI35) -> 3.0093209 | BQ35: 9123 | BR35: =BQ35/($AI35) -> 3.0369507 | BS35: 8586 | BT35: =BS35/($AI35) -> 2.8581891 | BU35: 9534 | BV35: =BU35/($AI35) -> 3.1737683 | BW35: 9301 | BX35: =BW35/($AI35) -> 3.0962051 | BY35: 8449 | BZ35: =BY35/($AI35) -> 2.8125832 | CA35: 9063 | CB35: =CA35/($AI35) -> 3.0169774 | CC35: 9298 | CD35: =CC35/($AI35) -> 3.0952064 | CE35: 8311 | CF35: =CE35/($AI35) -> 2.7666445 | CG35: 9275 | CH35: =CG35/($AI35) -> 3.0875499 | CI35: 8399 | CJ35: =CI35/($AI35) -> 2.7959387 | CK35: 10005 | CL35: =CK35/($AI35) -> 3.3305593 | CM35: 172 | CN35: =CM35/($AI35) -> 0.057256991 | CP35: =CO35/($AI35) -> 0 | CQ35: 294017 | CR35: =CQ35/($AI35) -> 97.875166 | CS35: 118678 | CT35: =CS35/($AI35) -> 39.506658 | CU35: 14585 | CV35: =CU35/($AI35) -> 4.8551931 | CW35: 10114 | CX35: =CW35/($AI35) -> 3.3668442 | CY35: 10975 | DA35: 9055 | DC35: 11049 | DE35: 9630
A36: 39 | B36: BW02b_Bewilligungs_Workflow_Step_V2 | C36: =E36 -> {"dossier":p.DossierName1,"buttonName":"Prüfung OK","checkStatus":"In Bearbeitung"} | E36: =F36&G36&H36&I36&J36&K36&L36&M36&N36&O36&P36&Q36&R36&S36&T36&U36&V36&W36&X36 -> {"dossier":p.DossierName1,"buttonName":"Prüfung OK","checkStatus":"In Bearbeitung"} | F36: {"dossier": | G36: ='001x'!$G$11 -> p.DossierName1 | H36: ,"buttonName":" | I36: Prüfung OK | J36: ","checkStatus":" | K36: In Bearbeitung | L36: "} | AI36: 4023 | AL36: 4008 | AM36: =AL36/($AI36) -> 0.99627144 | AN36: 4008 | AO36: =AN36/($AI36) -> 0.99627144 | AP36: 4007 | AQ36: =AP36/($AI36) -> 0.99602287 | AR36: 4006 | AS36: =AR36/($AI36) -> 0.9957743 | AT36: 4029 | AU36: =AT36/($AI36) -> 1.0014914 | AV36: 4009 | AW36: =AV36/($AI36) -> 0.99652001 | AX36: 4006 | AY36: =AX36/($AI36) -> 0.9957743 | AZ36: 4010 | BB36: 4000 | BC36: =BB36/($AI36) -> 0.99428287 | BD36: 4016 | BE36: =BD36/($AI36) -> 0.99826 | BF36: 4007 | BG36: =BF36/($AI36) -> 0.99602287 | BH36: 4008 | BI36: =BH36/($AI36) -> 0.99627144 | BK36: 4011 | BL36: =BK36/($AI36) -> 0.99701715 | BM36: 4008 | BN36: =BM36/($AI36) -> 0.99627144 | BO36: 10990 | BP36: =BO36/($AI36) -> 2.7317922 | BQ36: 10413 | BR36: =BQ36/($AI36) -> 2.5883669 | BS36: 11494 | BT36: =BS36/($AI36) -> 2.8570718 | BU36: 11609 | BV36: =BU36/($AI36) -> 2.8856575 | BW36: 10326 | BX36: =BW36/($AI36) -> 2.5667412 | BY36: 10779 | BZ36: =BY36/($AI36) -> 2.6793438 | CA36: 10140 | CB36: =CA36/($AI36) -> 2.5205071 | CC36: 10588 | CD36: =CC36/($AI36) -> 2.6318668 | CE36: 11170 | CF36: =CE36/($AI36) -> 2.7765349 | CG36: 9876 | CH36: =CG36/($AI36) -> 2.4548844 | CI36: 10803 | CJ36: =CI36/($AI36) -> 2.6853095 | CK36: 12080 | CL36: =CK36/($AI36) -> 3.0027343 | CN36: =CM36/($AI36) -> 0 | CP36: =CO36/($AI36) -> 0 | CQ36: 10252 | CR36: =CQ36/($AI36) -> 2.548347 | CS36: 8710 | CT36: =CS36/($AI36) -> 2.165051 | CU36: 8455 | CV36: =CU36/($AI36) -> 2.1016654 | CW36: 8964 | CX36: =CW36/($AI36) -> 2.2281879 | CY36: 16278 | DA36: 15438 | DC36: 10657 | DE36: 11446
A37: 40 | B37: L03_LogoutAndLoginDiffAccount | C37: =E37 -> {"username":"aventis-gemeinde-ma@diartis.ch","password":"#xFymiADPk7wJG/FWMz"} | E37: =F37&G37&H37&I37&J37&K37&L37&M37&N37&O37&P37&Q37&R37&S37&T37&U37&V37&W37&X37 -> {"username":"aventis-gemeinde-ma@diartis.ch","password":"#xFymiADPk7wJG/FWMz"} | F37: {"username":" | G37: aventis-gemeinde-ma@diartis.ch | H37: ","password":" | I37: #xFymiADPk7wJG/FWMz | J37: "} | AI37: 6252 | AL37: 33296 | AM37: =AL37/($AI37) -> 5.3256558 | AN37: 16126 | AO37: =AN37/($AI37) -> 2.5793346 | AP37: 16536 | AQ37: =AP37/($AI37) -> 2.6449136 | AR37: 15591 | AS37: =AR37/($AI37) -> 2.493762 | AT37: 15851 | AU37: =AT37/($AI37) -> 2.5353487 | AV37: 15658 | AW37: =AV37/($AI37) -> 2.5044786 | AX37: 15381 | AY37: =AX37/($AI37) -> 2.4601727 | AZ37: 9955 | BB37: 9081 | BC37: =BB37/($AI37) -> 1.4524952 | BD37: 7798 | BE37: =BD37/($AI37) -> 1.2472809 | BF37: 8041 | BG37: =BF37/($AI37) -> 1.2861484 | BH37: 7717 | BI37: =BH37/($AI37) -> 1.234325 | BK37: 7691 | BL37: =BK37/($AI37) -> 1.2301663 | BM37: 8688 | BN37: =BM37/($AI37) -> 1.3896353 | BO37: 8810 | BP37: =BO37/($AI37) -> 1.4091491 | BQ37: 9187 | BR37: =BQ37/($AI37) -> 1.4694498 | BS37: 8930 | BT37: =BS37/($AI37) -> 1.4283429 | BU37: 9653 | BV37: =BU37/($AI37) -> 1.5439859 | BW37: 9271 | BX37: =BW37/($AI37) -> 1.4828855 | BY37: 9605 | BZ37: =BY37/($AI37) -> 1.5363084 | CA37: 8290 | CB37: =CA37/($AI37) -> 1.3259757 | CC37: 8678 | CD37: =CC37/($AI37) -> 1.3880358 | CE37: 6401 | CF37: =CE37/($AI37) -> 1.0238324 | CG37: 5987 | CH37: =CG37/($AI37) -> 0.95761356 | CI37: 6089 | CJ37: =CI37/($AI37) -> 0.97392834 | CK37: 13086 | CL37: =CK37/($AI37) -> 2.0930902 | CN37: =CM37/($AI37) -> 0 | CP37: =CO37/($AI37) -> 0 | CQ37: 12221 | CR37: =CQ37/($AI37) -> 1.9547345 | CS37: 12586 | CT37: =CS37/($AI37) -> 2.0131158 | CU37: 7078 | CV37: =CU37/($AI37) -> 1.1321177 | CW37: 11049 | CX37: =CW37/($AI37) -> 1.7672745 | CY37: 9727 | DA37: 7582 | DC37: 6993 | DE37: 7672
A38: 42 | B38: BW02b_Bewilligungs_Workflow_Step_V2 | C38: =E38 -> {"dossier":p.DossierName1,"buttonName":"Bewilligen","checkStatus":"Bewilligt"} | E38: =F38&G38&H38&I38&J38&K38&L38&M38&N38&O38&P38&Q38&R38&S38&T38&U38&V38&W38&X38 -> {"dossier":p.DossierName1,"buttonName":"Bewilligen","checkStatus":"Bewilligt"} | F38: {"dossier": | G38: ='001x'!$G$11 -> p.DossierName1 | H38: ,"buttonName":" | I38: Bewilligen | J38: ","checkStatus":" | K38: Bewilligt | L38: "} | AI38: 4015 | AL38: 4015 | AM38: =AL38/($AI38) -> 1 | AN38: 4016 | AO38: =AN38/($AI38) -> 1.0002491 | AP38: 4005 | AQ38: =AP38/($AI38) -> 0.99750934 | AR38: 4029 | AS38: =AR38/($AI38) -> 1.0034869 | AT38: 4014 | AU38: =AT38/($AI38) -> 0.99975093 | AV38: 4019 | AW38: =AV38/($AI38) -> 1.0009963 | AX38: 4005 | AY38: =AX38/($AI38) -> 0.99750934 | AZ38: 4020 | BB38: 4018 | BC38: =BB38/($AI38) -> 1.0007472 | BD38: 4009 | BE38: =BD38/($AI38) -> 0.9985056 | BF38: 4010 | BG38: =BF38/($AI38) -> 0.99875467 | BH38: 4010 | BI38: =BH38/($AI38) -> 0.99875467 | BK38: 4014 | BL38: =BK38/($AI38) -> 0.99975093 | BM38: 4012 | BN38: =BM38/($AI38) -> 0.9992528 | BO38: 9980 | BP38: =BO38/($AI38) -> 2.4856787 | BQ38: 10493 | BR38: =BQ38/($AI38) -> 2.6134496 | BS38: 10367 | BT38: =BS38/($AI38) -> 2.5820672 | BU38: 10616 | BV38: =BU38/($AI38) -> 2.6440847 | BW38: 10513 | BX38: =BW38/($AI38) -> 2.6184309 | BY38: 10520 | BZ38: =BY38/($AI38) -> 2.6201743 | CA38: 10214 | CB38: =CA38/($AI38) -> 2.5439601 | CC38: 9895 | CD38: =CC38/($AI38) -> 2.4645081 | CE38: 10367 | CF38: =CE38/($AI38) -> 2.5820672 | CG38: 10142 | CH38: =CG38/($AI38) -> 2.5260274 | CI38: 10162 | CJ38: =CI38/($AI38) -> 2.5310087 | CK38: 10156 | CL38: =CK38/($AI38) -> 2.5295143 | CN38: =CM38/($AI38) -> 0 | CP38: =CO38/($AI38) -> 0 | CQ38: 9521 | CR38: =CQ38/($AI38) -> 2.3713574 | CS38: 9789 | CT38: =CS38/($AI38) -> 2.4381071 | CU38: 10266 | CV38: =CU38/($AI38) -> 2.5569116 | CW38: 10182 | CX38: =CW38/($AI38) -> 2.53599 | CY38: 15452 | DA38: 12039 | DC38: 12588 | DE38: 11736
A39: 43 | B39: L03_LogoutAndLoginDiffAccount | C39: =E39 -> {"username":"Bern.Sachbearbeiterin@diartis.ch","password":"XXxa22?pdTA66-S@"} | E39: =F39&G39&H39&I39&J39&K39&L39&M39&N39&O39&P39&Q39&R39&S39&T39&U39&V39&W39&X39 -> {"username":"Bern.Sachbearbeiterin@diartis.ch","password":"XXxa22?pdTA66-S@"} | F39: {"username":" | G39: Bern.Sachbearbeiterin@diartis.ch | H39: ","password":" | I39: XXxa22?pdTA66-S@ | J39: "} | AI39: 8327 | AL39: 10930 | AM39: =AL39/($AI39) -> 1.3125976 | AN39: 15882 | AO39: =AN39/($AI39) -> 1.9072895 | AP39: 16441 | AQ39: =AP39/($AI39) -> 1.9744206 | AR39: 15637 | AS39: =AR39/($AI39) -> 1.8778672 | AT39: 15783 | AU39: =AT39/($AI39) -> 1.8954005 | AV39: 15539 | AW39: =AV39/($AI39) -> 1.8660982 | AX39: 15242 | AY39: =AX39/($AI39) -> 1.8304311 | AZ39: 8439 | BB39: 8437 | BC39: =BB39/($AI39) -> 1.01321 | BD39: 7603 | BE39: =BD39/($AI39) -> 0.91305392 | BF39: 8134 | BG39: =BF39/($AI39) -> 0.97682239 | BH39: 7499 | BI39: =BH39/($AI39) -> 0.90056443 | BK39: 8307 | BL39: =BK39/($AI39) -> 0.99759817 | BM39: 8658 | BN39: =BM39/($AI39) -> 1.0397502 | BO39: 9945 | BP39: =BO39/($AI39) -> 1.1943077 | BQ39: 9323 | BR39: =BQ39/($AI39) -> 1.1196109 | BS39: 8996 | BT39: =BS39/($AI39) -> 1.0803411 | BU39: 9115 | BV39: =BU39/($AI39) -> 1.0946319 | BW39: 8727 | BX39: =BW39/($AI39) -> 1.0480365 | BY39: 8953 | BZ39: =BY39/($AI39) -> 1.0751771 | CA39: 8692 | CB39: =CA39/($AI39) -> 1.0438333 | CC39: 8467 | CD39: =CC39/($AI39) -> 1.0168128 | CE39: 5939 | CF39: =CE39/($AI39) -> 0.71322205 | CG39: 6203 | CH39: =CG39/($AI39) -> 0.74492614 | CI39: 6078 | CJ39: =CI39/($AI39) -> 0.72991474 | CK39: 10719 | CL39: =CK39/($AI39) -> 1.2872583 | CN39: =CM39/($AI39) -> 0 | CP39: =CO39/($AI39) -> 0 | CQ39: 11273 | CR39: =CQ39/($AI39) -> 1.3537889 | CS39: 9813 | CT39: =CS39/($AI39) -> 1.1784556 | CU39: 14108 | CV39: =CU39/($AI39) -> 1.6942476 | CW39: 11737 | CX39: =CW39/($AI39) -> 1.4095112 | CY39: 10053 | DA39: 8071 | DC39: 7145 | DE39: 7390
A40: 45 | B40: DO11_Dossier_Search_Lupe | C40: =E40 -> {"searchDossierOrKlient":p.DossierName1,"resultType":"Dossiers"} | E40: =F40&G40&H40&I40&J40&K40&L40&M40&N40&O40&P40&Q40&R40&S40&T40&U40&V40&W40&X40 -> {"searchDossierOrKlient":p.DossierName1,"resultType":"Dossiers"} | F40: {"searchDossierOrKlient": | G40: =G38 -> p.DossierName1 | H40: ,"resultType":" | I40: Dossiers | J40: "} | AI40: 1012 | AL40: 1009 | AM40: =AL40/($AI40) -> 0.99703557 | AN40: 1002 | AO40: =AN40/($AI40) -> 0.99011858 | AP40: 1008 | AQ40: =AP40/($AI40) -> 0.99604743 | AR40: 1015 | AS40: =AR40/($AI40) -> 1.0029644 | AT40: 1022 | AU40: =AT40/($AI40) -> 1.0098814 | AV40: 1014 | AW40: =AV40/($AI40) -> 1.0019763 | AX40: 1009 | AY40: =AX40/($AI40) -> 0.99703557 | AZ40: 1006 | BB40: 1009 | BC40: =BB40/($AI40) -> 0.99703557 | BD40: 1006 | BE40: =BD40/($AI40) -> 0.99407115 | BF40: 1003 | BG40: =BF40/($AI40) -> 0.99110672 | BH40: 1008 | BI40: =BH40/($AI40) -> 0.99604743 | BK40: 1009 | BL40: =BK40/($AI40) -> 0.99703557 | BM40: 1005 | BN40: =BM40/($AI40) -> 0.993083 | BO40: 10207 | BP40: =BO40/($AI40) -> 10.085968 | BQ40: 11158 | BR40: =BQ40/($AI40) -> 11.025692 | BS40: 10099 | BT40: =BS40/($AI40) -> 9.979249 | BU40: 11236 | BV40: =BU40/($AI40) -> 11.102767 | BW40: 11130 | BX40: =BW40/($AI40) -> 10.998024 | BY40: 10977 | BZ40: =BY40/($AI40) -> 10.846838 | CA40: 10374 | CB40: =CA40/($AI40) -> 10.250988 | CC40: 10941 | CD40: =CC40/($AI40) -> 10.811265 | CE40: 10477 | CF40: =CE40/($AI40) -> 10.352767 | CG40: 10518 | CH40: =CG40/($AI40) -> 10.393281 | CI40: 10465 | CJ40: =CI40/($AI40) -> 10.340909 | CK40: 11244 | CL40: =CK40/($AI40) -> 11.110672 | CN40: =CM40/($AI40) -> 0 | CP40: =CO40/($AI40) -> 0 | CQ40: 11653 | CR40: =CQ40/($AI40) -> 11.514822 | CS40: 9535 | CT40: =CS40/($AI40) -> 9.4219368 | CU40: 10393 | CV40: =CU40/($AI40) -> 10.269763 | CW40: 11436 | CX40: =CW40/($AI40) -> 11.300395 | CY40: 14854 | DA40: 12940 | DC40: 12926 | DE40: 14246
A41: 46 | B41: BW03b_Bewilligungs_WF_FreigabeVerwendungsPeriode | C41: =E41 -> {"verwendungPeriode":"November 2025,Dezember 2025,Januar 2026,Februar 2026,März 2026,April 2026,Mai 2026","status":"Zu bezahlen"} | E41: =F41&G41&H41&I41&J41&K41&L41&M41&N41&O41&P41&Q41&R41&S41&T41&U41&V41&W41&X41 -> {"verwendungPeriode":"November 2025,Dezember 2025,Januar 2026,Februar 2026,März 2026,April 2026,Mai 2026","status":"Zu bezahlen"} | F41: {"verwendungPeriode":" | G41: =F72&","&F73&","&F74&","&F75&","&F76&","&F77&","&F78 -> November 2025,Dezember 2025,Januar 2026,Februar 2026,März 2026,April 2026,Mai 2026 | J41: ","status":" | K41: Zu bezahlen | L41: "} | AI41: 11232 | AL41: 11618 | AM41: =AL41/($AI41) -> 1.0343661 | AN41: 11145 | AO41: =AN41/($AI41) -> 0.99225427 | AP41: 12036 | AQ41: =AP41/($AI41) -> 1.0715812 | AR41: 12488 | AS41: =AR41/($AI41) -> 1.1118234 | AT41: 12291 | AU41: =AT41/($AI41) -> 1.0942842 | AV41: 12147 | AW41: =AV41/($AI41) -> 1.0814637 | AX41: 12134 | AY41: =AX41/($AI41) -> 1.0803063 | AZ41: 4979 | BB41: 4073 | BC41: =BB41/($AI41) -> 0.36262464 | BD41: 4740 | BE41: =BD41/($AI41) -> 0.42200855 | BF41: 4889 | BG41: =BF41/($AI41) -> 0.43527422 | BH41: 5343 | BI41: =BH41/($AI41) -> 0.47569444 | BK41: 5161 | BL41: =BK41/($AI41) -> 0.45949074 | BM41: 4972 | BN41: =BM41/($AI41) -> 0.44266382 | BO41: 6113 | BP41: =BO41/($AI41) -> 0.54424858 | BQ41: 6005 | BR41: =BQ41/($AI41) -> 0.53463319 | BS41: 6078 | BT41: =BS41/($AI41) -> 0.54113248 | BU41: 6241 | BV41: =BU41/($AI41) -> 0.55564459 | BW41: 6016 | BX41: =BW41/($AI41) -> 0.53561254 | BY41: 6038 | BZ41: =BY41/($AI41) -> 0.53757123 | CA41: 6124 | CB41: =CA41/($AI41) -> 0.54522792 | CC41: 5372 | CD41: =CC41/($AI41) -> 0.47827635 | CE41: 2742 | CF41: =CE41/($AI41) -> 0.24412393 | CG41: 2939 | CH41: =CG41/($AI41) -> 0.26166311 | CI41: 3428 | CJ41: =CI41/($AI41) -> 0.30519943 | CK41: 6274 | CL41: =CK41/($AI41) -> 0.55858262 | CN41: =CM41/($AI41) -> 0 | CP41: =CO41/($AI41) -> 0 | CQ41: 5759 | CR41: =CQ41/($AI41) -> 0.51273148 | CS41: 5063 | CT41: =CS41/($AI41) -> 0.45076567 | CU41: 5347 | CV41: =CU41/($AI41) -> 0.47605057 | CW41: 9599 | CX41: =CW41/($AI41) -> 0.85461182 | CY41: 4881 | DA41: 5791 | DC41: 4813 | DE41: 5010
B42: WSH05_Haftung_Sozialhilfeschuld_Bearbeiten | C42: =E42 -> {"haftungsType":"Einseitige Solidarhaftung erfassen","haftungDurch":`${p.FamilyName1}, ${p.ManFirstName1}`,"haftungVon":"01.11.2025","haftungBis":"31.12.2025","haftungFuer":`${p.FamilyName1}, ${p.WomanFirstName1}`,"person1":"","person2":""} | E42: =F42&G42&H42&I42&J42&K42&L42&M42&N42&O42&P42&Q42&R42&S42&T42&U42&V42&W42&X42 -> {"haftungsType":"Einseitige Solidarhaftung erfassen","haftungDurch":`${p.FamilyName1}, ${p.ManFirstName1}`,"haftungVon":"01.11.2025","haftungBis":"31.12.2025","haftungFuer":`${p.FamilyName1}, ${p.WomanFirstName1}`,"person1":"","person2":""} | F42: {"haftungsType":" | G42: Einseitige Solidarhaftung erfassen | H42: ","haftungDurch":` | I42: =I23 -> ${p.FamilyName1}, ${p.ManFirstName1} | J42: `,"haftungVon":" | K42: ="01."&MONTH(TODAY())&"."&YEAR(TODAY()) -> 01.11.2025 | L42: ","haftungBis":" | M42: ="31.12."&YEAR(TODAY()) -> 31.12.2025 | N42: ","haftungFuer":` | O42: ="${"&$G$4&"}, ${"&$H$63&"}" -> ${p.FamilyName1}, ${p.WomanFirstName1} | P42: `,"person1":" | R42: ","person2":" | T42: "} | AI42: 6915 | AL42: 6982 | AM42: =AL42/($AI42) -> 1.0096891 | AN42: 9078 | AO42: =AN42/($AI42) -> 1.3127983 | AP42: 9444 | AQ42: =AP42/($AI42) -> 1.3657267 | AS42: =AR42/($AI42) -> 0 | AU42: =AT42/($AI42) -> 0 | AW42: =AV42/($AI42) -> 0 | AY42: =AX42/($AI42) -> 0 | BC42: =BB42/($AI42) -> 0 | BE42: =BD42/($AI42) -> 0 | BG42: =BF42/($AI42) -> 0 | BI42: =BH42/($AI42) -> 0 | BL42: =BK42/($AI42) -> 0 | BN42: =BM42/($AI42) -> 0 | BP42: =BO42/($AI42) -> 0 | BR42: =BQ42/($AI42) -> 0 | BT42: =BS42/($AI42) -> 0 | BV42: =BU42/($AI42) -> 0 | BX42: =BW42/($AI42) -> 0 | BZ42: =BY42/($AI42) -> 0 | CB42: =CA42/($AI42) -> 0 | CD42: =CC42/($AI42) -> 0 | CF42: =CE42/($AI42) -> 0 | CH42: =CG42/($AI42) -> 0 | CJ42: =CI42/($AI42) -> 0 | CL42: =CK42/($AI42) -> 0 | CN42: =CM42/($AI42) -> 0 | CP42: =CO42/($AI42) -> 0 | CR42: =CQ42/($AI42) -> 0 | CT42: =CS42/($AI42) -> 0 | CV42: =CU42/($AI42) -> 0 | CX42: =CW42/($AI42) -> 0
B43: WSH05_Haftung_Sozialhilfeschuld_Bearbeiten | C43: =E43 -> {"haftungsType":"Einzelhaftung erfassen","haftungDurch":`${p.FamilyName1}, ${p.ManFirstName1}`,"haftungVon":"01.11.2025","haftungBis":"31.12.2025","haftungFuer":`${p.FamilyName1}, ${p.GirlFirstName1}`,"person1":"","person2":""} | E43: =F43&G43&H43&I43&J43&K43&L43&M43&N43&O43&P43&Q43&R43&S43&T43&U43&V43&W43&X43 -> {"haftungsType":"Einzelhaftung erfassen","haftungDurch":`${p.FamilyName1}, ${p.ManFirstName1}`,"haftungVon":"01.11.2025","haftungBis":"31.12.2025","haftungFuer":`${p.FamilyName1}, ${p.GirlFirstName1}`,"person1":"","person2":""} | F43: {"haftungsType":" | G43: Einzelhaftung erfassen | H43: ","haftungDurch":` | I43: =I23 -> ${p.FamilyName1}, ${p.ManFirstName1} | J43: `,"haftungVon":" | K43: ="01."&MONTH(TODAY())&"."&YEAR(TODAY()) -> 01.11.2025 | L43: ","haftungBis":" | M43: ="31.12."&YEAR(TODAY()) -> 31.12.2025 | N43: ","haftungFuer":` | O43: ="${"&$G$4&"}, ${"&$H$64&"}" -> ${p.FamilyName1}, ${p.GirlFirstName1} | P43: `,"person1":" | R43: ","person2":" | T43: "} | AI43: 5252 | AL43: 5584 | AM43: =AL43/($AI43) -> 1.063214 | AN43: 7647 | AO43: =AN43/($AI43) -> 1.4560168 | AP43: 0 | AQ43: =AP43/($AI43) -> 0 | AS43: =AR43/($AI43) -> 0 | AU43: =AT43/($AI43) -> 0 | AW43: =AV43/($AI43) -> 0 | AY43: =AX43/($AI43) -> 0 | BC43: =BB43/($AI43) -> 0 | BE43: =BD43/($AI43) -> 0 | BG43: =BF43/($AI43) -> 0 | BI43: =BH43/($AI43) -> 0 | BL43: =BK43/($AI43) -> 0 | BN43: =BM43/($AI43) -> 0 | BP43: =BO43/($AI43) -> 0 | BR43: =BQ43/($AI43) -> 0 | BT43: =BS43/($AI43) -> 0 | BV43: =BU43/($AI43) -> 0 | BX43: =BW43/($AI43) -> 0 | BZ43: =BY43/($AI43) -> 0 | CB43: =CA43/($AI43) -> 0 | CD43: =CC43/($AI43) -> 0 | CF43: =CE43/($AI43) -> 0 | CH43: =CG43/($AI43) -> 0 | CJ43: =CI43/($AI43) -> 0 | CL43: =CK43/($AI43) -> 0 | CN43: =CM43/($AI43) -> 0 | CP43: =CO43/($AI43) -> 0 | CR43: =CQ43/($AI43) -> 0 | CT43: =CS43/($AI43) -> 0 | CV43: =CU43/($AI43) -> 0 | CX43: =CW43/($AI43) -> 0
B44: E01_Delay | C44: {"Pause":"2000"} | AI44: 4817 | AL44: 4866 | AM44: =AL44/($AI44) -> 1.0101723 | AN44: 6555 | AO44: =AN44/($AI44) -> 1.3608055 | AP44: 552 | AQ44: =AP44/($AI44) -> 0.11459415 | AR44: 7656 | AS44: =AR44/($AI44) -> 1.589371 | AT44: 7641 | AU44: =AT44/($AI44) -> 1.586257 | AV44: 7477 | AW44: =AV44/($AI44) -> 1.5522109 | AX44: 7539 | AY44: =AX44/($AI44) -> 1.565082 | AZ44: 7418 | BB44: 0 | BC44: =BB44/($AI44) -> 0 | BD44: 5085 | BE44: =BD44/($AI44) -> 1.0556363 | BF44: 5191 | BG44: =BF44/($AI44) -> 1.0776417 | BH44: 5126 | BI44: =BH44/($AI44) -> 1.0641478 | BK44: 5172 | BL44: =BK44/($AI44) -> 1.0736973 | BM44: 4792 | BN44: =BM44/($AI44) -> 0.99481005 | BO44: 5127 | BP44: =BO44/($AI44) -> 1.0643554 | BQ44: 5566 | BR44: =BQ44/($AI44) -> 1.155491 | BS44: 5075 | BT44: =BS44/($AI44) -> 1.0535603 | BU44: 5944 | BV44: =BU44/($AI44) -> 1.233963 | BW44: 5145 | BX44: =BW44/($AI44) -> 1.0680922 | BY44: 6041 | BZ44: =BY44/($AI44) -> 1.2541001 | CA44: 5094 | CB44: =CA44/($AI44) -> 1.0575047 | CC44: 5941 | CD44: =CC44/($AI44) -> 1.2333403 | CE44: 5755 | CF44: =CE44/($AI44) -> 1.194727 | CG44: 5256 | CH44: =CG44/($AI44) -> 1.0911356 | CI44: 5645 | CJ44: =CI44/($AI44) -> 1.1718912 | CK44: 9438 | CL44: =CK44/($AI44) -> 1.9593108 | CN44: =CM44/($AI44) -> 0 | CP44: =CO44/($AI44) -> 0 | CQ44: 5469 | CR44: =CQ44/($AI44) -> 1.135354 | CS44: 4979 | CT44: =CS44/($AI44) -> 1.0336309 | CU44: 5279 | CV44: =CU44/($AI44) -> 1.0959103 | CW44: 5395 | CX44: =CW44/($AI44) -> 1.1199917 | CY44: 5450 | DA44: 4660 | DC44: 8775 | DE44: 5447
B45: A00_BrowserRefresh_F5 | AI45: 2014 | AL45: 2016 | AM45: =AL45/($AI45) -> 1.000993 | AO45: =AN45/($AI45) -> 0 | AQ45: =AP45/($AI45) -> 0 | AS45: =AR45/($AI45) -> 0 | AU45: =AT45/($AI45) -> 0 | AW45: =AV45/($AI45) -> 0 | AY45: =AX45/($AI45) -> 0 | BC45: =BB45/($AI45) -> 0 | BE45: =BD45/($AI45) -> 0 | BG45: =BF45/($AI45) -> 0 | BI45: =BH45/($AI45) -> 0 | BL45: =BK45/($AI45) -> 0 | BN45: =BM45/($AI45) -> 0 | BP45: =BO45/($AI45) -> 0 | BR45: =BQ45/($AI45) -> 0 | BT45: =BS45/($AI45) -> 0 | BV45: =BU45/($AI45) -> 0 | BX45: =BW45/($AI45) -> 0 | BZ45: =BY45/($AI45) -> 0 | CB45: =CA45/($AI45) -> 0 | CD45: =CC45/($AI45) -> 0 | CF45: =CE45/($AI45) -> 0 | CH45: =CG45/($AI45) -> 0 | CJ45: =CI45/($AI45) -> 0 | CL45: =CK45/($AI45) -> 0 | CN45: =CM45/($AI45) -> 0 | CP45: =CO45/($AI45) -> 0 | CR45: =CQ45/($AI45) -> 0 | CT45: =CS45/($AI45) -> 0 | CV45: =CU45/($AI45) -> 0 | CX45: =CW45/($AI45) -> 0
B46: E01_Delay | C46: {"Pause":"2000"} | AI46: 2011 | AL46: 2008 | AM46: =AL46/($AI46) -> 0.9985082 | AN46: 2011 | AO46: =AN46/($AI46) -> 1 | AQ46: =AP46/($AI46) -> 0 | AR46: 2013 | AS46: =AR46/($AI46) -> 1.0009945 | AT46: 2020 | AU46: =AT46/($AI46) -> 1.0044754 | AV46: 2017 | AW46: =AV46/($AI46) -> 1.0029836 | AX46: 2019 | AY46: =AX46/($AI46) -> 1.0039781 | AZ46: 2013 | BB46: 341 | BC46: =BB46/($AI46) -> 0.16956738 | BD46: 2007 | BE46: =BD46/($AI46) -> 0.99801094 | BF46: 2003 | BG46: =BF46/($AI46) -> 0.99602188 | BH46: 2009 | BI46: =BH46/($AI46) -> 0.99900547 | BK46: 2019 | BL46: =BK46/($AI46) -> 1.0039781 | BM46: 2008 | BN46: =BM46/($AI46) -> 0.9985082 | BO46: 2005 | BP46: =BO46/($AI46) -> 0.99701641 | BQ46: 2012 | BR46: =BQ46/($AI46) -> 1.0004973 | BS46: 2004 | BT46: =BS46/($AI46) -> 0.99651914 | BU46: 2005 | BV46: =BU46/($AI46) -> 0.99701641 | BW46: 2013 | BX46: =BW46/($AI46) -> 1.0009945 | BY46: 2013 | BZ46: =BY46/($AI46) -> 1.0009945 | CA46: 2006 | CB46: =CA46/($AI46) -> 0.99751367 | CC46: 2006 | CD46: =CC46/($AI46) -> 0.99751367 | CE46: 2015 | CF46: =CE46/($AI46) -> 1.0019891 | CG46: 2010 | CH46: =CG46/($AI46) -> 0.99950273 | CI46: 2012 | CJ46: =CI46/($AI46) -> 1.0004973 | CK46: 2005 | CL46: =CK46/($AI46) -> 0.99701641 | CN46: =CM46/($AI46) -> 0 | CP46: =CO46/($AI46) -> 0 | CQ46: 2010 | CR46: =CQ46/($AI46) -> 0.99950273 | CS46: 2018 | CT46: =CS46/($AI46) -> 1.0034809 | CU46: 2016 | CV46: =CU46/($AI46) -> 1.0024863 | CW46: 2016 | CX46: =CW46/($AI46) -> 1.0024863 | CY46: 2006 | DA46: 2018 | DC46: 2010 | DE46: 2015
B47: DO11_Dossier_Search_Lupe | C47: =E47 -> {"searchDossierOrKlient":p.DossierName1,"resultType":"Dossiers"} | E47: =F47&G47&H47&I47&J47&K47&L47&M47&N47&O47&P47&Q47&R47&S47&T47&U47&V47&W47&X47 -> {"searchDossierOrKlient":p.DossierName1,"resultType":"Dossiers"} | F47: {"searchDossierOrKlient": | G47: ='001x'!$G$11 -> p.DossierName1 | H47: ,"resultType":" | I47: Dossiers | J47: "} | AI47: 10683 | AL47: 10909 | AM47: =AL47/($AI47) -> 1.0211551 | AN47: 2017 | AO47: =AN47/($AI47) -> 0.18880464 | AQ47: =AP47/($AI47) -> 0 | AR47: 2007 | AS47: =AR47/($AI47) -> 0.18786858 | AT47: 2006 | AU47: =AT47/($AI47) -> 0.18777497 | AV47: 2003 | AW47: =AV47/($AI47) -> 0.18749415 | AX47: 2010 | AY47: =AX47/($AI47) -> 0.1881494 | AZ47: 2012 | BC47: =BB47/($AI47) -> 0 | BD47: 2006 | BE47: =BD47/($AI47) -> 0.18777497 | BF47: 2006 | BG47: =BF47/($AI47) -> 0.18777497 | BH47: 2031 | BI47: =BH47/($AI47) -> 0.19011514 | BK47: 2010 | BL47: =BK47/($AI47) -> 0.1881494 | BM47: 2019 | BN47: =BM47/($AI47) -> 0.18899186 | BO47: 2018 | BP47: =BO47/($AI47) -> 0.18889825 | BQ47: 2005 | BR47: =BQ47/($AI47) -> 0.18768136 | BS47: 2018 | BT47: =BS47/($AI47) -> 0.18889825 | BU47: 2004 | BV47: =BU47/($AI47) -> 0.18758776 | BW47: 2006 | BX47: =BW47/($AI47) -> 0.18777497 | BY47: 2006 | BZ47: =BY47/($AI47) -> 0.18777497 | CA47: 2014 | CB47: =CA47/($AI47) -> 0.18852382 | CC47: 2006 | CD47: =CC47/($AI47) -> 0.18777497 | CE47: 2011 | CF47: =CE47/($AI47) -> 0.188243 | CG47: 2016 | CH47: =CG47/($AI47) -> 0.18871104 | CI47: 2017 | CJ47: =CI47/($AI47) -> 0.18880464 | CK47: 2015 | CL47: =CK47/($AI47) -> 0.18861743 | CN47: =CM47/($AI47) -> 0 | CP47: =CO47/($AI47) -> 0 | CQ47: 2007 | CR47: =CQ47/($AI47) -> 0.18786858 | CS47: 2012 | CT47: =CS47/($AI47) -> 0.18833661 | CU47: 2013 | CV47: =CU47/($AI47) -> 0.18843022 | CW47: 2009 | CX47: =CW47/($AI47) -> 0.18805579 | CY47: 2014 | DA47: 2019 | DC47: 2012 | DE47: 2002
A48: 52 | B48: Z01_WSH_Zahlungen_Freigeben | C48: =E48 -> {"dossierInstitution":p.DossierName1,"freigegebeneZahlungen":"5"} | E48: =F48&G48&H48&I48&J48&K48&L48&M48&N48&O48&P48&Q48&R48&S48&T48&U48&V48&W48&X48 -> {"dossierInstitution":p.DossierName1,"freigegebeneZahlungen":"5"} | F48: {"dossierInstitution": | G48: ='001x'!$G$11 -> p.DossierName1 | H48: ,"freigegebeneZahlungen":" | I48: 5 | J48: "} | AI48: 17062 | AL48: 17338 | AM48: =AL48/($AI48) -> 1.0161763 | AN48: 11068 | AO48: =AN48/($AI48) -> 0.648693 | AQ48: =AP48/($AI48) -> 0 | AR48: 10928 | AS48: =AR48/($AI48) -> 0.64048763 | AT48: 11238 | AU48: =AT48/($AI48) -> 0.65865666 | AV48: 11122 | AW48: =AV48/($AI48) -> 0.65185793 | AX48: 10650 | AY48: =AX48/($AI48) -> 0.62419412 | AZ48: 2569 | BC48: =BB48/($AI48) -> 0 | BD48: 4707 | BE48: =BD48/($AI48) -> 0.27587622 | BF48: 4794 | BG48: =BF48/($AI48) -> 0.28097527 | BH48: 4577 | BI48: =BH48/($AI48) -> 0.26825695 | BK48: 4849 | BL48: =BK48/($AI48) -> 0.2841988 | BM48: 4885 | BN48: =BM48/($AI48) -> 0.28630876 | BO48: 4992 | BP48: =BO48/($AI48) -> 0.29258 | BQ48: 4771 | BR48: =BQ48/($AI48) -> 0.27962724 | BS48: 5023 | BT48: =BS48/($AI48) -> 0.29439691 | BU48: 4921 | BV48: =BU48/($AI48) -> 0.28841871 | BW48: 4937 | BX48: =BW48/($AI48) -> 0.28935646 | BY48: 4890 | BZ48: =BY48/($AI48) -> 0.28660181 | CA48: 4979 | CB48: =CA48/($AI48) -> 0.29181808 | CC48: 4533 | CD48: =CC48/($AI48) -> 0.26567812 | CE48: 1704 | CF48: =CE48/($AI48) -> 0.099871058 | CG48: 1697 | CH48: =CG48/($AI48) -> 0.09946079 | CI48: 2352 | CJ48: =CI48/($AI48) -> 0.13785019 | CK48: 6734 | CL48: =CK48/($AI48) -> 0.39467823 | CN48: =CM48/($AI48) -> 0 | CP48: =CO48/($AI48) -> 0 | CQ48: 4172 | CR48: =CQ48/($AI48) -> 0.24451999 | CS48: 4113 | CT48: =CS48/($AI48) -> 0.24106201 | CU48: 4013 | CV48: =CU48/($AI48) -> 0.23520103 | CW48: 4464 | CX48: =CW48/($AI48) -> 0.26163404 | CY48: 4540 | DA48: 5600 | DC48: 5791 | DE48: 4566
B49: E01_Delay | C49: {"Pause":"4000"}
B50: L03_LogoutAndLoginDiffAccount | C50: =E50 -> {"username":"Bern.Buchhalter@diartis.ch","password":"HBcc73+ppTX42?E."} | E50: =F50&G50&H50&I50&J50&K50&L50&M50&N50&O50&P50&Q50&R50&S50&T50&U50&V50&W50&X50 -> {"username":"Bern.Buchhalter@diartis.ch","password":"HBcc73+ppTX42?E."} | F50: {"username":" | G50: Bern.Buchhalter@diartis.ch | H50: ","password":" | I50: HBcc73+ppTX42?E. | J50: "}
B51: E01_Delay | C51: {"Pause":"3000"}
B52: DO11_Dossier_Search_Lupe | C52: =E52 -> {"searchDossierOrKlient":p.DossierName1,"resultType":"Dossiers"} | E52: =F52&G52&H52&I52&J52&K52&L52&M52&N52&O52&P52&Q52&R52&S52&T52&U52&V52&W52&X52 -> {"searchDossierOrKlient":p.DossierName1,"resultType":"Dossiers"} | F52: {"searchDossierOrKlient": | G52: ='001x'!$G$11 -> p.DossierName1 | H52: ,"resultType":" | I52: Dossiers | J52: "}
B53: BU01_ZahlungsAuftrag_Erstellen | C53: =E53 -> {"bisValutaDatum":"31.12.2024","dossier":p.DossierName1,"zahlungenTotal":"","buchhaltung":`Regionaler Sozialdienst "Bern"`,"zustGemeinde":""} | E53: =F53&G53&H53&I53&J53&K53&L53&M53&N53&O53&P53&Q53&R53&S53&T53&U53&V53&W53&X53 -> {"bisValutaDatum":"31.12.2024","dossier":p.DossierName1,"zahlungenTotal":"","buchhaltung":`Regionaler Sozialdienst "Bern"`,"zustGemeinde":""} | F53: {"bisValutaDatum":" | G53: 31.12.2024 | H53: ","dossier": | I53: =G47 -> p.DossierName1 | J53: ,"zahlungenTotal":" | L53: ","buchhaltung":` | M53: Regionaler Sozialdienst "Bern" | N53: `,"zustGemeinde":" | P53: "}
B54: E01_Delay | C54: {"Pause":"1000"}
B55: WSH99_Zahlungen_AnzahlPruefen | C55: =E55 -> {"dossier":p.DossierName1,"ausgefuehrteZahlungen":"7"} | E55: =F55&G55&H55&I55&J55&K55&L55&M55&N55&O55&P55&Q55&R55&S55&T55&U55&V55&W55 -> {"dossier":p.DossierName1,"ausgefuehrteZahlungen":"7"} | F55: {"dossier": | G55: =G62 -> p.DossierName1 | H55: ,"ausgefuehrteZahlungen":" | I55: 7 | J55: "} | Y55: "}
B56: L03_LogoutAndLoginDiffAccount | C56: {"username":"bern.sozialarbeiterin1a@diartis.ch","password":"SMze97-jkSJ59!F."} | E56: =F56&G56&H56&I56&J56&K56&L56&M56&N56&O56&P56&Q56&R56&S56&T56&U56&V56&W56&X56 -> {"username":"Bern.Sachbearbeiterin@diartis.ch","password":"XXxa22?pdTA66-S@"} | F56: {"username":" | G56: Bern.Sachbearbeiterin@diartis.ch | H56: ","password":" | I56: XXxa22?pdTA66-S@ | J56: "}
B58: {"url":p.aventisURL} | K58: wird nicht geprüft
B59: {"url":"https://dev.aventis.swiss"}
B60: {"url":"http://localhost/"}
B61: {"url":"https://test.aventis.swiss"}
B62: {"url":"https://dev.aventis.swiss"} | F62: Dossier | G62: ="p.DossierName"&G67 -> p.DossierName1 | H62: ="p.ManFirstName"&G67 -> p.ManFirstName1 | I62: ="p.AHVNumber"&G69 -> p.AHVNumber1 | J62: ="p.BirthdayAdult"&G67 -> p.BirthdayAdult1
B63: {"url":p.aventisURL} | F63: Mann | G63: ="p.FamilyName"&G67 -> p.FamilyName1 | H63: ="p.WomanFirstName"&G67 -> p.WomanFirstName1 | I63: ="p.AHVNumber"&G69+1 -> p.AHVNumber2 | J63: ="p.BirthdayAdult"&G68 -> p.BirthdayAdult2
F64: Familie | G64: =G63 -> p.FamilyName1 | H64: ="p.GirlFirstName"&G67 -> p.GirlFirstName1 | I64: ="p.AHVNumber"&G69+2 -> p.AHVNumber3 | J64: ="p.BirthdayKid"&G67 -> p.BirthdayKid1
B65: IBAN CH16 0631 3640 3055 6467 2 | H65: ="p.ManFirstName"&G68 -> p.ManFirstName2 | I65: ="p.AHVNumber"&G69+3 -> p.AHVNumber4 | J65: ="p.BirthdayKid"&G68 -> p.BirthdayKid2
B67: Achtung Formeln | G67: 1
B68: Oktober 2024 | G68: =G67+1 -> 2
B69: November 2024 | G69: =G67*4-4+1 -> 1
B70: Dezember 2024
B71: Januar 2025 | D71: Achtung Formeln
B72: Februar 2025 | E72: =MONTH(TODAY()) -> 11 | F72: {=_xlfn.CHOOSEROWS(H$84:H$107,E72)&" "&_xlfn.CHOOSEROWS(I$84:I$107,E72)} -> November 2025
B73: März 2025 | E73: =E72+1 -> 12 | F73: {=_xlfn.CHOOSEROWS(H$84:H$107,E73)&" "&_xlfn.CHOOSEROWS(I$84:I$107,E73)} -> Dezember 2025
B74: April 2025 | E74: =E73+1 -> 13 | F74: {=_xlfn.CHOOSEROWS(H$84:H$107,E74)&" "&_xlfn.CHOOSEROWS(I$84:I$107,E74)} -> Januar 2026
E75: =E74+1 -> 14 | F75: {=_xlfn.CHOOSEROWS(H$84:H$107,E75)&" "&_xlfn.CHOOSEROWS(I$84:I$107,E75)} -> Februar 2026
E76: =E75+1 -> 15 | F76: {=_xlfn.CHOOSEROWS(H$84:H$107,E76)&" "&_xlfn.CHOOSEROWS(I$84:I$107,E76)} -> März 2026
E77: =E76+1 -> 16 | F77: {=_xlfn.CHOOSEROWS(H$84:H$107,E77)&" "&_xlfn.CHOOSEROWS(I$84:I$107,E77)} -> April 2026
E78: =E77+1 -> 17 | F78: {=_xlfn.CHOOSEROWS(H$84:H$116,E78)&" "&_xlfn.CHOOSEROWS(I$84:I$116,E78)} -> Mai 2026
E80: 13 | F80: {=_xlfn.CHOOSEROWS(I84:I107,E80)} -> 2026
F83: {=_xlfn.CHOOSEROWS(H83:H89,3)} -> Februar
G84: 1 | H84: Januar | I84: 2025
G85: 2 | H85: Februar | I85: 2025
G86: 3 | H86: März | I86: 2025
G87: 4 | H87: April | I87: 2025
G88: 5 | H88: Mai | I88: 2025
G89: 6 | H89: Juni | I89: 2025
G90: 7 | H90: Juli | I90: 2025
G91: 8 | H91: August | I91: 2025
G92: 9 | H92: September | I92: 2025
G93: 10 | H93: Oktober | I93: 2025
G94: 11 | H94: November | I94: 2025
G95: 12 | H95: Dezember | I95: 2025
... G116: 33 | H116: September | I116: 2027

Sheet 001a
A1: Step | B1: Keyword | C1: Testdata | D1: Screenshot | F1: video | G1: =5*60*1000*SpeedFaktor -> 300000 | H1: 50 | AH1: Testresult | AI1: 09.12.2024 | AK1: Testresult | AL1: 09.12.2024 | AM1: Hoch | AN1: 04.02.2025 | AO1: Hoch | AP1: 04.02.2025 13:50:39 | AQ1: Hoch | AR1: 28.03.2025 10:25:49 | AS1: Hoch | AT1: 31.03.2025 18:57:12 | AU1: Hoch | AV1: 01.04.2025 00:27:19 | AW1: Hoch | AX1: 01.04.2025 23:50:20 | AY1: Hoch | AZ1: 09.04.2025 14:35:45 | BA1: Message 09.04.2025 14:35:45 | BB1: 09.04.2025 20:54:34 | BC1: Hoch | BD1: 25.06.2025 19:45:42 | BE1: Hoch | BF1: 26.06.2025 08:23:51 | BG1: Hoch | BH1: 05.07.2025 02:04:53 | BI1: Hoch | BK1: 22.07.2025 05:11:20 | BL1: Hoch | BM1: 22.07.2025 09:53:01 | BN1: Hoch | BO1: 22.07.2025 15:36:51 | BP1: Hoch | BQ1: 22.07.2025 18:44:05 | BR1: Hoch | BS1: 22.07.2025 19:54:04 | BT1: Hoch | BU1: 22.07.2025 22:30:01 | BV1: Hoch | BW1: 23.07.2025 08:43:42 | BX1: Hoch | BY1: 23.07.2025 09:48:50 | BZ1: Hoch | CA1: 24.07.2025 02:30:17 | CB1: Hoch | CC1: 24.07.2025 15:47:38 | CD1: Hoch | CE1: 24.07.2025 17:55:15 | CF1: Hoch | CG1: 24.07.2025 19:37:23 | CH1: Hoch | CI1: 24.07.2025 23:36:24 | CJ1: Hoch | CK1: 05.08.2025 16:09:15 | CL1: Hoch | CM1: 05.08.2025 16:15:04 | CN1: Hoch | CO1: 05.08.2025 16:22:04 | CP1: Hoch | CQ1: 05.08.2025 16:43:41 | CR1: Hoch | CS1: 05.08.2025 17:02:04 | CT1: Hoch | CU1: 05.08.2025 17:20:58 | CV1: Hoch | CW1: 18.08.2025 15:31:20 | CX1: Hoch | CY1: 20.08.2025 10:02:58 | CZ1: Message | DA1: 24.08.2025 15:36:50 | DB1: Message | DC1: 26.08.2025 11:41:22 | DD1: Message | DE1: 26.08.2025 13:36:43 | DF1: Message | DG1: 26.08.2025 16:55:49 | DH1: Message | DI1: 30.10.2025 03:23:00 | DJ1: Message | DK1: 03.11.2025 13:58:05 | DL1: Message
A2: 1 | B2: L00_URLAventis | C2: =B59 -> {"url":p.aventisURL} | E2: =F2&G2&H2&I2&J2&K2&L2&M2&N2&O2&P2&Q2&R2&S2&T2&U2&V2&W2&X2 -> {"url":"https://dev.aventis.swiss"} | F2: {"url":" | G2: https://dev.aventis.swiss | H2: "} | AI2: 2535 | AL2: 933 | AM2: =AL2/($AI2) -> 0.36804734 | AN2: 554 | AO2: =AN2/($AI2) -> 0.21854043 | AP2: 770 | AQ2: =AP2/($AI2) -> 0.30374753 | AR2: 382 | AS2: =AR2/($AI2) -> 0.15069034 | AT2: 555 | AU2: =AT2/($AI2) -> 0.21893491 | AV2: 356 | AW2: =AV2/($AI2) -> 0.14043393 | AX2: 355 | AY2: =AX2/($AI2) -> 0.14003945 | AZ2: 424 | BB2: 354 | BC2: =BB2/($AI2) -> 0.13964497 | BD2: 4014 | BE2: =BD2/($AI2) -> 1.583432 | BF2: 4014 | BG2: =BF2/($AI2) -> 1.583432 | BH2: 4011 | BI2: =BH2/($AI2) -> 1.5822485 | BK2: 338 | BL2: =BK2/($AI2) -> 0.13333333 | BM2: 299 | BN2: =BM2/($AI2) -> 0.11794872 | BO2: 331 | BP2: =BO2/($AI2) -> 0.13057199 | BQ2: 406 | BR2: =BQ2/($AI2) -> 0.16015779 | BS2: 356 | BT2: =BS2/($AI2) -> 0.14043393 | BU2: 295 | BV2: =BU2/($AI2) -> 0.11637081 | BW2: 291 | BX2: =BW2/($AI2) -> 0.1147929 | BY2: 367 | BZ2: =BY2/($AI2) -> 0.14477318 | CA2: 444 | CB2: =CA2/($AI2) -> 0.17514793 | CC2: 354 | CD2: =CC2/($AI2) -> 0.13964497 | CE2: 420 | CF2: =CE2/($AI2) -> 0.16568047 | CG2: 366 | CH2: =CG2/($AI2) -> 0.1443787 | CI2: 173 | CJ2: =CI2/($AI2) -> 0.068244576 | CK2: 1013 | CL2: =CK2/($AI2) -> 0.39960552 | CM2: 707 | CN2: =CM2/($AI2) -> 0.27889546 | CO2: 733 | CP2: =CO2/($AI2) -> 0.28915187 | CQ2: 1009 | CR2: =CQ2/($AI2) -> 0.39802761 | CS2: 953 | CT2: =CS2/($AI2) -> 0.37593688 | CU2: 1182 | CV2: =CU2/($AI2) -> 0.46627219 | CW2: 213 | CX2: =CW2/($AI2) -> 0.084023669 | CY2: 403 | DA2: 904 | DC2: 335 | DE2: 369 | DG2: 363 | DI2: 243 | DK2: 189
A3: 4 | B3: M01_LoginMSOnline | C3: =E3 -> {"username":"bern.sozialarbeiterin1a@diartis.ch","password":"SMze97-jkSJ59!F.","fullname":"Sozialarbeiterin 1A Bern","team":"Sozialarbeit Bern 1"} | E3: =F3&G3&H3&I3&J3&K3&L3&M3&N3&O3&P3&Q3&R3&S3&T3&U3&V3&W3&X3 -> {"username":"bern.sozialarbeiterin1a@diartis.ch","password":"SMze97-jkSJ59!F.","fullname":"Sozialarbeiterin 1A Bern","team":"Sozialarbeit Bern 1"} | F3: {"username":" | G3: bern.sozialarbeiterin1a@diartis.ch | H3: ","password":" | I3: SMze97-jkSJ59!F. | J3: ","fullname":" | K3: Sozialarbeiterin 1A Bern | L3: ","team":" | M3: Sozialarbeit Bern 1 | N3: "} | AI3: 407 | AJ3: seriell | AL3: 407 | AM3: =AL3/($AI3) -> 1 | AN3: 417 | AO3: =AN3/($AI3) -> 1.02457 | AP3: 412 | AQ3: =AP3/($AI3) -> 1.012285 | AR3: 421 | AS3: =AR3/($AI3) -> 1.034398 | AT3: 403 | AU3: =AT3/($AI3) -> 0.99017199 | AV3: 411 | AW3: =AV3/($AI3) -> 1.009828 | AX3: 1391 | AY3: =AX3/($AI3) -> 3.4176904 | AZ3: 1355 | BB3: 1177 | BC3: =BB3/($AI3) -> 2.8918919 | BD3: 410 | BE3: =BD3/($AI3) -> 1.007371 | BF3: 416 | BG3: =BF3/($AI3) -> 1.022113 | BH3: 404 | BI3: =BH3/($AI3) -> 0.99262899 | BK3: 413 | BL3: =BK3/($AI3) -> 1.014742 | BM3: 403 | BN3: =BM3/($AI3) -> 0.99017199 | BO3: 1161 | BP3: =BO3/($AI3) -> 2.8525799 | BQ3: 1183 | BR3: =BQ3/($AI3) -> 2.9066339 | BS3: 1170 | BT3: =BS3/($AI3) -> 2.8746929 | BU3: 1089 | BV3: =BU3/($AI3) -> 2.6756757 | BW3: 1108 | BX3: =BW3/($AI3) -> 2.7223587 | BY3: 1162 | BZ3: =BY3/($AI3) -> 2.8550369 | CA3: 1253 | CB3: =CA3/($AI3) -> 3.0786241 | CC3: 1022 | CD3: =CC3/($AI3) -> 2.5110565 | CE3: 1168 | CF3: =CE3/($AI3) -> 2.8697789 | CG3: 1042 | CH3: =CG3/($AI3) -> 2.5601966 | CI3: 774 | CJ3: =CI3/($AI3) -> 1.9017199 | CK3: 1476 | CL3: =CK3/($AI3) -> 3.6265356 | CM3: 1335 | CN3: =CM3/($AI3) -> 3.2800983 | CO3: 1310 | CP3: =CO3/($AI3) -> 3.2186732 | CQ3: 1597 | CR3: =CQ3/($AI3) -> 3.9238329 | CS3: 1493 | CT3: =CS3/($AI3) -> 3.6683047 | CU3: 1812 | CV3: =CU3/($AI3) -> 4.4520885 | CW3: 814 | CX3: =CW3/($AI3) -> 2 | CY3: 1180 | DA3: 1383 | DC3: 1128 | DE3: 1072 | DG3: 1124 | DI3: 932 | DK3: 481
A4: 50 | B4: E01_Delay | C4: {"Pause":"6000"} | AI4: 2011 | AL4: 2008 | AM4: =AL4/($AI4) -> 0.9985082 | AN4: 2011 | AO4: =AN4/($AI4) -> 1 | AQ4: =AP4/($AI4) -> 0 | AR4: 2013 | AS4: =AR4/($AI4) -> 1.0009945 | AT4: 2020 | AU4: =AT4/($AI4) -> 1.0044754 | AV4: 2017 | AW4: =AV4/($AI4) -> 1.0029836 | AX4: 2019 | AY4: =AX4/($AI4) -> 1.0039781 | AZ4: 2013 | BB4: 341 | BC4: =BB4/($AI4) -> 0.16956738 | BD4: 2007 | BE4: =BD4/($AI4) -> 0.99801094 | BF4: 2003 | BG4: =BF4/($AI4) -> 0.99602188 | BH4: 2009 | BI4: =BH4/($AI4) -> 0.99900547 | BK4: 2019 | BL4: =BK4/($AI4) -> 1.0039781 | BM4: 2008 | BN4: =BM4/($AI4) -> 0.9985082 | BO4: 2005 | BP4: =BO4/($AI4) -> 0.99701641 | BQ4: 2012 | BR4: =BQ4/($AI4) -> 1.0004973 | BS4: 2004 | BT4: =BS4/($AI4) -> 0.99651914 | BU4: 2005 | BV4: =BU4/($AI4) -> 0.99701641 | BW4: 2013 | BX4: =BW4/($AI4) -> 1.0009945 | BY4: 2013 | BZ4: =BY4/($AI4) -> 1.0009945 | CA4: 2006 | CB4: =CA4/($AI4) -> 0.99751367 | CC4: 2006 | CD4: =CC4/($AI4) -> 0.99751367 | CE4: 2015 | CF4: =CE4/($AI4) -> 1.0019891 | CG4: 2010 | CH4: =CG4/($AI4) -> 0.99950273 | CI4: 2012 | CJ4: =CI4/($AI4) -> 1.0004973 | CK4: 2005 | CL4: =CK4/($AI4) -> 0.99701641 | CN4: =CM4/($AI4) -> 0 | CO4: 3307 | CP4: =CO4/($AI4) -> 1.6444555 | CQ4: 12881 | CR4: =CQ4/($AI4) -> 6.405271 | CS4: 16955 | CT4: =CS4/($AI4) -> 8.4311288 | CU4: 17778 | CV4: =CU4/($AI4) -> 8.8403779 | CW4: 3806 | CX4: =CW4/($AI4) -> 1.8925908 | CY4: 1914 | DA4: 6014 | DC4: 6014 | DE4: 6033 | DG4: 609 | DI4: 9005 | DK4: 6643
A5: 3 | B5: P01_Person_Search | C5: =E5 -> {"name":p.FamilyName1,"vorname":p.ManFirstName1,"ahvNumber":"","geburtsdatum":""} | E5: =F5&G5&H5&I5&J5&K5&L5&M5&N5&O5&P5&Q5&R5&S5&T5&U5&V5&W5&X5 -> {"name":p.FamilyName1,"vorname":p.ManFirstName1,"ahvNumber":"","geburtsdatum":""} | F5: {"name": | G5: =G$64 -> p.FamilyName1 | H5: ,"vorname": | I5: =H$63 -> p.ManFirstName1 | J5: ,"ahvNumber":"" | L5: ,"geburtsdatum":" | N5: "} | AI5: 6791 | AJ5: 5 Parallel | AL5: 9630 | AM5: =AL5/($AI5) -> 1.4180533 | AN5: 8889 | AO5: =AN5/($AI5) -> 1.3089383 | AP5: 10209 | AQ5: =AP5/($AI5) -> 1.5033132 | AR5: 9507 | AS5: =AR5/($AI5) -> 1.3999411 | AT5: 6454 | AU5: =AT5/($AI5) -> 0.9503755 | AV5: 8318 | AW5: =AV5/($AI5) -> 1.2248564 | AX5: 10072 | AY5: =AX5/($AI5) -> 1.4831394 | AZ5: 10056 | BB5: 9423 | BC5: =BB5/($AI5) -> 1.3875718 | BD5: 6604 | BE5: =BD5/($AI5) -> 0.97246355 | BF5: 10404 | BG5: =BF5/($AI5) -> 1.5320277 | BH5: 4702 | BI5: =BH5/($AI5) -> 0.69238698 | BK5: 7245 | BL5: =BK5/($AI5) -> 1.0668532 | BM5: 6500 | BN5: =BM5/($AI5) -> 0.95714917 | BO5: 7445 | BP5: =BO5/($AI5) -> 1.0963039 | BQ5: 7658 | BR5: =BQ5/($AI5) -> 1.127669 | BS5: 6851 | BT5: =BS5/($AI5) -> 1.0088352 | BU5: 7556 | BV5: =BU5/($AI5) -> 1.1126491 | BW5: 7074 | BX5: =BW5/($AI5) -> 1.0416728 | BY5: 7362 | BZ5: =BY5/($AI5) -> 1.0840819 | CA5: 6882 | CB5: =CA5/($AI5) -> 1.0134001 | CC5: 7465 | CD5: =CC5/($AI5) -> 1.099249 | CE5: 7303 | CF5: =CE5/($AI5) -> 1.0753939 | CG5: 6858 | CH5: =CG5/($AI5) -> 1.009866 | CI5: 5092 | CJ5: =CI5/($AI5) -> 0.74981593 | CK5: 6341 | CL5: =CK5/($AI5) -> 0.93373583 | CM5: 6443 | CN5: =CM5/($AI5) -> 0.94875571 | CO5: 6003 | CP5: =CO5/($AI5) -> 0.88396407 | CQ5: 6485 | CR5: =CQ5/($AI5) -> 0.95494036 | CS5: 10819 | CT5: =CS5/($AI5) -> 1.593138 | CU5: 6713 | CV5: =CU5/($AI5) -> 0.98851421 | CW5: 5703 | CX5: =CW5/($AI5) -> 0.83978795 | CY5: 8793 | DA5: 6465 | DC5: 8399 | DE5: 7518 | DG5: 8015 | DI5: 6005 | DK5: 6009
A6: 6 | B6: P05_Person_Create_Manual_Complete | C6: =E6 -> {"name":p.FamilyName1,"vorname":p.ManFirstName1,"ahvNumber":p.AHVNumber1,"language":"Deutsch","zivilstand":"ledig","geburtsdatum":p.BirthdayAdult1,"national":"Schweiz","gender":"männlich","aufenthalt":""} | E6: =F6&G6&H6&I6&J6&K6&L6&M6&N6&O6&P6&Q6&R6&S6&T6&U6&V6&W6&X6 -> {"name":p.FamilyName1,"vorname":p.ManFirstName1,"ahvNumber":p.AHVNumber1,"language":"Deutsch","zivilstand":"ledig","geburtsdatum":p.BirthdayAdult1,"national":"Schweiz","gender":"männlich","aufenthalt":""} | F6: {"name": | G6: =G5 -> p.FamilyName1 | H6: ,"vorname": | I6: =I5 -> p.ManFirstName1 | J6: ,"ahvNumber": | K6: =I$63 -> p.AHVNumber1 | L6: ,"language":" | M6: Deutsch | N6: ","zivilstand":" | O6: ledig | P6: ","geburtsdatum": | Q6: =J63 -> p.BirthdayAdult1 | R6: ,"national":" | S6: Schweiz | T6: ","gender":" | U6: männlich | V6: ","aufenthalt":" | X6: "} | AI6: 4248 | AJ6: 10 Parallel | AL6: 2994 | AM6: =AL6/($AI6) -> 0.70480226 | AN6: 3290 | AO6: =AN6/($AI6) -> 0.77448211 | AP6: 3368 | AQ6: =AP6/($AI6) -> 0.79284369 | AR6: 3306 | AS6: =AR6/($AI6) -> 0.77824859 | AT6: 1785 | AU6: =AT6/($AI6) -> 0.42019774 | AV6: 3248 | AW6: =AV6/($AI6) -> 0.7645951 | AX6: 3124 | AY6: =AX6/($AI6) -> 0.7354049 | AZ6: 2770 | BB6: 2828 | BC6: =BB6/($AI6) -> 0.66572505 | BD6: 1839 | BE6: =BD6/($AI6) -> 0.4329096 | BF6: 3591 | BG6: =BF6/($AI6) -> 0.84533898 | BH6: 1286 | BI6: =BH6/($AI6) -> 0.3027307 | BK6: 1866 | BL6: =BK6/($AI6) -> 0.43926554 | BM6: 1734 | BN6: =BM6/($AI6) -> 0.40819209 | BO6: 1743 | BP6: =BO6/($AI6) -> 0.41031073 | BQ6: 1989 | BR6: =BQ6/($AI6) -> 0.46822034 | BS6: 1938 | BT6: =BS6/($AI6) -> 0.45621469 | BU6: 1806 | BV6: =BU6/($AI6) -> 0.42514124 | BW6: 1746 | BX6: =BW6/($AI6) -> 0.41101695 | BY6: 1735 | BZ6: =BY6/($AI6) -> 0.4084275 | CA6: 1625 | CB6: =CA6/($AI6) -> 0.38253296 | CC6: 1839 | CD6: =CC6/($AI6) -> 0.4329096 | CE6: 1633 | CF6: =CE6/($AI6) -> 0.3844162 | CG6: 1427 | CH6: =CG6/($AI6) -> 0.33592279 | CI6: 569 | CJ6: =CI6/($AI6) -> 0.13394539 | CK6: 459 | CL6: =CK6/($AI6) -> 0.10805085 | CM6: 1317 | CN6: =CM6/($AI6) -> 0.31002825 | CO6: 1435 | CP6: =CO6/($AI6) -> 0.33780603 | CQ6: 1356 | CR6: =CQ6/($AI6) -> 0.31920904 | CS6: 1454 | CT6: =CS6/($AI6) -> 0.34227872 | CU6: 1334 | CV6: =CU6/($AI6) -> 0.31403013 | CW6: 1162 | CX6: =CW6/($AI6) -> 0.27354049 | CY6: 1488 | DA6: 484 | DC6: 1126 | DE6: 1206 | DG6: 1425 | DI6: 487 | DK6: 388
A7: 7 | B7: P10_Person_Communikation_Complete | C7: =E7 -> {"mobile":"079 5465658","privateNumber":"079 5287449","email":"5624abc@gmail.com"} | E7: =F7&G7&H7&I7&J7&K7&L7&M7&N7&O7&P7&Q7&R7&S7&T7&U7&V7&W7&X7 -> {"mobile":"079 5465658","privateNumber":"079 5287449","email":"5624abc@gmail.com"} | F7: {"mobile":" | G7: ="079 "&RANDBETWEEN(5234500,5699999) -> 079 5465658 | H7: ","privateNumber":" | I7: ="079 "&RANDBETWEEN(5234500,5699999) -> 079 5287449 | J7: ","email":" | K7: 5624abc@gmail.com | L7: "} | AI7: 3639 | AJ7: 20 Parallel | AL7: 3657 | AM7: =AL7/($AI7) -> 1.0049464 | AN7: 4534 | AO7: =AN7/($AI7) -> 1.2459467 | AP7: 4999 | AQ7: =AP7/($AI7) -> 1.373729 | AR7: 4750 | AS7: =AR7/($AI7) -> 1.3053037 | AT7: 2507 | AU7: =AT7/($AI7) -> 0.68892553 | AV7: 4176 | AW7: =AV7/($AI7) -> 1.147568 | AX7: 3909 | AY7: =AX7/($AI7) -> 1.0741962 | AZ7: 3585 | BB7: 3326 | BC7: =BB7/($AI7) -> 0.91398736 | BD7: 3008 | BE7: =BD7/($AI7) -> 0.82660071 | BF7: 4148 | BG7: =BF7/($AI7) -> 1.1398736 | BH7: 2528 | BI7: =BH7/($AI7) -> 0.69469635 | BK7: 3014 | BL7: =BK7/($AI7) -> 0.82824952 | BM7: 2617 | BN7: =BM7/($AI7) -> 0.71915361 | BO7: 2785 | BP7: =BO7/($AI7) -> 0.76532014 | BQ7: 3146 | BR7: =BQ7/($AI7) -> 0.86452322 | BS7: 3792 | BT7: =BS7/($AI7) -> 1.0420445 | BU7: 3891 | BV7: =BU7/($AI7) -> 1.0692498 | BW7: 3784 | BX7: =BW7/($AI7) -> 1.0398461 | BY7: 3631 | BZ7: =BY7/($AI7) -> 0.99780159 | CA7: 2395 | CB7: =CA7/($AI7) -> 0.65814784 | CC7: 3816 | CD7: =CC7/($AI7) -> 1.0486397 | CE7: 2687 | CF7: =CE7/($AI7) -> 0.73838967 | CG7: 2464 | CH7: =CG7/($AI7) -> 0.6771091 | CI7: 2247 | CJ7: =CI7/($AI7) -> 0.61747733 | CK7: 2207 | CL7: =CK7/($AI7) -> 0.6064853 | CM7: 2514 | CN7: =CM7/($AI7) -> 0.69084913 | CO7: 2449 | CP7: =CO7/($AI7) -> 0.67298708 | CQ7: 2560 | CR7: =CQ7/($AI7) -> 0.70348997 | CS7: 2643 | CT7: =CS7/($AI7) -> 0.72629843 | CU7: 2534 | CV7: =CU7/($AI7) -> 0.69634515 | CW7: 2486 | CX7: =CW7/($AI7) -> 0.68315471 | CY7: 2948 | DA7: 2208 | DC7: 2753 | DE7: 2659 | DG7: 2809 | DI7: 2284 | DK7: 2286
A8: 8 | B8: P15_Person_Adress | C8: =E8 -> {"zusatz":"","strasse":"Strasse_743","houseNumber":"41","ort":"3053 Münchenbuchsee","validDate":"01.01.2025"} | E8: =F8&G8&H8&I8&J8&K8&L8&M8&N8&O8&P8&Q8&R8&S8&T8&U8&V8&W8&X8 -> {"zusatz":"","strasse":"Strasse_743","houseNumber":"41","ort":"3053 Münchenbuchsee","validDate":"01.01.2025"} | F8: {"zusatz":" | H8: ","strasse":" | I8: ="Strasse_"&RANDBETWEEN(1,1000) -> Strasse_743 | J8: ","houseNumber":" | K8: =RANDBETWEEN(1,100) -> 41 | L8: ","ort":" | M8: 3053 Münchenbuchsee | N8: ","validDate":" | O8: ="01.01."&TEXT(TODAY(),"YYYY") -> 01.01.2025 | P8: "} | AI8: 434 | AJ8: 50 Parallel | AL8: 443 | AM8: =AL8/($AI8) -> 1.0207373 | AN8: 807 | AO8: =AN8/($AI8) -> 1.859447 | AP8: 785 | AQ8: =AP8/($AI8) -> 1.8087558 | AR8: 742 | AS8: =AR8/($AI8) -> 1.7096774 | AT8: 407 | AU8: =AT8/($AI8) -> 0.93778802 | AV8: 629 | AW8: =AV8/($AI8) -> 1.4493088 | AX8: 624 | AY8: =AX8/($AI8) -> 1.437788 | AZ8: 547 | BB8: 428 | BC8: =BB8/($AI8) -> 0.98617512 | BD8: 246 | BE8: =BD8/($AI8) -> 0.56682028 | BF8: 641 | BG8: =BF8/($AI8) -> 1.4769585 | BH8: 247 | BI8: =BH8/($AI8) -> 0.56912442 | BK8: 358 | BL8: =BK8/($AI8) -> 0.82488479 | BM8: 344 | BN8: =BM8/($AI8) -> 0.79262673 | BO8: 321 | BP8: =BO8/($AI8) -> 0.73963134 | BQ8: 400 | BR8: =BQ8/($AI8) -> 0.92165899 | BS8: 509 | BT8: =BS8/($AI8) -> 1.1728111 | BU8: 513 | BV8: =BU8/($AI8) -> 1.1820276 | BW8: 456 | BX8: =BW8/($AI8) -> 1.0506912 | BY8: 457 | BZ8: =BY8/($AI8) -> 1.0529954 | CA8: 366 | CB8: =CA8/($AI8) -> 0.84331797 | CC8: 422 | CD8: =CC8/($AI8) -> 0.97235023 | CE8: 346 | CF8: =CE8/($AI8) -> 0.79723502 | CG8: 294 | CH8: =CG8/($AI8) -> 0.67741935 | CI8: 174 | CJ8: =CI8/($AI8) -> 0.40092166 | CK8: 148 | CL8: =CK8/($AI8) -> 0.34101382 | CM8: 240 | CN8: =CM8/($AI8) -> 0.55299539 | CO8: 234 | CP8: =CO8/($AI8) -> 0.53917051 | CQ8: 248 | CR8: =CQ8/($AI8) -> 0.57142857 | CS8: 224 | CT8: =CS8/($AI8) -> 0.51612903 | CU8: 252 | CV8: =CU8/($AI8) -> 0.58064516 | CW8: 175 | CX8: =CW8/($AI8) -> 0.40322581 | CY8: 403 | DA8: 151 | DC8: 237 | DE8: 293 | DG8: 325 | DI8: 225 | DK8: 142
A9: 9 | B9: P20_Person_ZahlungsVerbindung | C9: =E9 -> {"iban":p.IBAN1} | E9: =F9&G9&H9&I9&J9&K9&L9&M9&N9&O9&P9&Q9&R9&S9&T9&U9&V9&W9&X9 -> {"iban":p.IBAN1} | F9: {"iban": | G9: p.IBAN1 | H9: } | AI9: 5206 | AL9: 5243 | AM9: =AL9/($AI9) -> 1.0071072 | AN9: 5874 | AO9: =AN9/($AI9) -> 1.1283135 | AP9: 5927 | AQ9: =AP9/($AI9) -> 1.138494 | AR9: 5864 | AS9: =AR9/($AI9) -> 1.1263926 | AT9: 5028 | AU9: =AT9/($AI9) -> 0.96580868 | AV9: 5359 | AW9: =AV9/($AI9) -> 1.0293892 | AX9: 5610 | AY9: =AX9/($AI9) -> 1.0776028 | AZ9: 5301 | BB9: 5109 | BC9: =BB9/($AI9) -> 0.98136765 | BD9: 4704 | BE9: =BD9/($AI9) -> 0.9035728 | BF9: 5426 | BG9: =BF9/($AI9) -> 1.0422589 | BH9: 4624 | BI9: =BH9/($AI9) -> 0.88820592 | BK9: 4951 | BL9: =BK9/($AI9) -> 0.95101806 | BM9: 4775 | BN9: =BM9/($AI9) -> 0.91721091 | BO9: 4813 | BP9: =BO9/($AI9) -> 0.92451018 | BQ9: 5016 | BR9: =BQ9/($AI9) -> 0.96350365 | BS9: 5090 | BT9: =BS9/($AI9) -> 0.97771802 | BU9: 4875 | BV9: =BU9/($AI9) -> 0.93641952 | BW9: 5143 | BX9: =BW9/($AI9) -> 0.98789858 | BY9: 5098 | BZ9: =BY9/($AI9) -> 0.97925471 | CA9: 4840 | CB9: =CA9/($AI9) -> 0.9296965 | CC9: 5137 | CD9: =CC9/($AI9) -> 0.98674606 | CE9: 4898 | CF9: =CE9/($AI9) -> 0.9408375 | CG9: 4725 | CH9: =CG9/($AI9) -> 0.90760661 | CI9: 4511 | CJ9: =CI9/($AI9) -> 0.86650019 | CK9: 4489 | CL9: =CK9/($AI9) -> 0.8622743 | CM9: 4613 | CN9: =CM9/($AI9) -> 0.88609297 | CO9: 4618 | CP9: =CO9/($AI9) -> 0.8870534 | CQ9: 4611 | CR9: =CQ9/($AI9) -> 0.8857088 | CS9: 4609 | CT9: =CS9/($AI9) -> 0.88532463 | CU9: 4684 | CV9: =CU9/($AI9) -> 0.89973108 | CW9: 1637 | CX9: =CW9/($AI9) -> 0.31444487 | CY9: 2374 | DA9: 984 | DC9: 1361 | DE9: 1502 | DG9: 1728 | DI9: 1858 | DK9: 1761
A10: 10 | B10: P30_Person_Uebernehmen | AI10: 2108 | AL10: 2128 | AM10: =AL10/($AI10) -> 1.0094877 | AN10: 2253 | AO10: =AN10/($AI10) -> 1.0687856 | AP10: 2264 | AQ10: =AP10/($AI10) -> 1.0740038 | AR10: 2224 | AS10: =AR10/($AI10) -> 1.0550285 | AT10: 2165 | AU10: =AT10/($AI10) -> 1.0270398 | AV10: 2154 | AW10: =AV10/($AI10) -> 1.0218216 | AX10: 2204 | AY10: =AX10/($AI10) -> 1.0455408 | AZ10: 2132 | BB10: 2158 | BC10: =BB10/($AI10) -> 1.0237192 | BD10: 104 | BE10: =BD10/($AI10) -> 0.049335863 | BF10: 93 | BG10: =BF10/($AI10) -> 0.044117647 | BH10: 93 | BI10: =BH10/($AI10) -> 0.044117647 | BK10: 80 | BL10: =BK10/($AI10) -> 0.037950664 | BM10: 67 | BN10: =BM10/($AI10) -> 0.031783681 | BO10: 75 | BP10: =BO10/($AI10) -> 0.035578748 | BQ10: 87 | BR10: =BQ10/($AI10) -> 0.041271347 | BS10: 80 | BT10: =BS10/($AI10) -> 0.037950664 | BU10: 107 | BV10: =BU10/($AI10) -> 0.050759013 | BW10: 134 | BX10: =BW10/($AI10) -> 0.063567362 | BY10: 78 | BZ10: =BY10/($AI10) -> 0.037001898 | CA10: 55 | CB10: =CA10/($AI10) -> 0.026091082 | CC10: 62 | CD10: =CC10/($AI10) -> 0.029411765 | CE10: 83 | CF10: =CE10/($AI10) -> 0.039373814 | CG10: 69 | CH10: =CG10/($AI10) -> 0.032732448 | CI10: 74 | CJ10: =CI10/($AI10) -> 0.035104364 | CK10: 58 | CL10: =CK10/($AI10) -> 0.027514231 | CM10: 57 | CN10: =CM10/($AI10) -> 0.027039848 | CO10: 57 | CP10: =CO10/($AI10) -> 0.027039848 | CQ10: 54 | CR10: =CQ10/($AI10) -> 0.025616698 | CS10: 58 | CT10: =CS10/($AI10) -> 0.027514231 | CU10: 55 | CV10: =CU10/($AI10) -> 0.026091082 | CW10: 61 | CX10: =CW10/($AI10) -> 0.028937381 | CY10: 147 | DA10: 79 | DC10: 104 | DE10: 121 | DG10: 150 | DI10: 93 | DK10: 65
A11: 11 | B11: H01_Haushalt_Uebernehmen_Zustaendigkeit | C11: =E11 -> {"zust_Gemeinde":"Münchenbuchsee","zust_SozTeam":"Sozialarbeit Bern 1","zust_SozMitarbeiter":"Bern Sozialarbeiterin 1A","zust_SachbTeam":"Sachbearbeitung Bern","zust_SachbMitarbeiter":"Bern Sachbearbeiterin"} | E11: =F11&G11&H11&I11&J11&K11&L11&M11&N11&O11&P11&Q11&R11&S11&T11&U11&V11&W11&X11 -> {"zust_Gemeinde":"Münchenbuchsee","zust_SozTeam":"Sozialarbeit Bern 1","zust_SozMitarbeiter":"Bern Sozialarbeiterin 1A","zust_SachbTeam":"Sachbearbeitung Bern","zust_SachbMitarbeiter":"Bern Sachbearbeiterin"} | F11: {"zust_Gemeinde":" | G11: Münchenbuchsee | H11: ","zust_SozTeam":" | I11: Sozialarbeit Bern 1 | J11: ","zust_SozMitarbeiter":" | K11: Bern Sozialarbeiterin 1A | L11: ","zust_SachbTeam":" | M11: Sachbearbeitung Bern | N11: ","zust_SachbMitarbeiter":" | O11: Bern Sachbearbeiterin | P11: "} | AI11: 565 | AJ11: QA | AL11: 227 | AM11: =AL11/($AI11) -> 0.40176991 | AN11: 510 | AO11: =AN11/($AI11) -> 0.90265487 | AP11: 511 | AQ11: =AP11/($AI11) -> 0.90442478 | AR11: 382 | AS11: =AR11/($AI11) -> 0.67610619 | AT11: 310 | AU11: =AT11/($AI11) -> 0.54867257 | AV11: 312 | AW11: =AV11/($AI11) -> 0.55221239 | AX11: 331 | AY11: =AX11/($AI11) -> 0.58584071 | AZ11: 160 | BB11: 192 | BC11: =BB11/($AI11) -> 0.33982301 | BD11: 1157 | BE11: =BD11/($AI11) -> 2.0477876 | BF11: 1275 | BG11: =BF11/($AI11) -> 2.2566372 | BH11: 1240 | BI11: =BH11/($AI11) -> 2.1946903 | BK11: 1219 | BL11: =BK11/($AI11) -> 2.1575221 | BM11: 2010 | BN11: =BM11/($AI11) -> 3.5575221 | BO11: 1166 | BP11: =BO11/($AI11) -> 2.0637168 | BQ11: 1218 | BR11: =BQ11/($AI11) -> 2.1557522 | BS11: 1187 | BT11: =BS11/($AI11) -> 2.100885 | BU11: 1174 | BV11: =BU11/($AI11) -> 2.0778761 | BW11: 1217 | BX11: =BW11/($AI11) -> 2.1539823 | BY11: 1162 | BZ11: =BY11/($AI11) -> 2.0566372 | CA11: 1386 | CB11: =CA11/($AI11) -> 2.4530973 | CC11: 1224 | CD11: =CC11/($AI11) -> 2.1663717 | CE11: 1191 | CF11: =CE11/($AI11) -> 2.1079646 | CG11: 1186 | CH11: =CG11/($AI11) -> 2.099115 | CI11: 1151 | CJ11: =CI11/($AI11) -> 2.0371681 | CK11: 1152 | CL11: =CK11/($AI11) -> 2.0389381 | CM11: 1164 | CN11: =CM11/($AI11) -> 2.060177 | CO11: 1181 | CP11: =CO11/($AI11) -> 2.0902655 | CQ11: 1144 | CR11: =CQ11/($AI11) -> 2.0247788 | CS11: 1161 | CT11: =CS11/($AI11) -> 2.0548673 | CU11: 1162 | CV11: =CU11/($AI11) -> 2.0566372 | CW11: 1194 | CX11: =CW11/($AI11) -> 2.1132743 | CY11: 1313 | DA11: 1142 | DC11: 1185 | DE11: 1210 | DG11: 1267 | DI11: 1491 | DK11: 1150
A12: 12 | B12: D01_Dossier_Eroeffnen | C12: =E12 -> {"dossierBezeichnung":p.DossierName1,"eroeffnetAm":"04.11.2025","dossierSprache":"Deutsch"} | E12: =F12&G12&H12&I12&J12&K12&L12&M12&N12&O12&P12&Q12&R12&S12&T12&U12&V12&W12&X12 -> {"dossierBezeichnung":p.DossierName1,"eroeffnetAm":"04.11.2025","dossierSprache":"Deutsch"} | F12: {"dossierBezeichnung": | G12: =G$63 -> p.DossierName1 | H12: ,"eroeffnetAm":" | I12: =TEXT(TEXT(TODAY(),"DD")&"."&TEXT(TODAY(),"MM")&"."&TEXT(TODAY(),"YYYY"),"DD.MM.YYYY") -> 04.11.2025 | J12: ","dossierSprache":" | K12: Deutsch | L12: "} | AI12: 3489 | AL12: 3700 | AM12: =AL12/($AI12) -> 1.0604758 | AN12: 4194 | AO12: =AN12/($AI12) -> 1.2020636 | AP12: 4214 | AQ12: =AP12/($AI12) -> 1.2077959 | AR12: 3773 | AS12: =AR12/($AI12) -> 1.0813987 | AT12: 3081 | AU12: =AT12/($AI12) -> 0.88306105 | AV12: 3350 | AW12: =AV12/($AI12) -> 0.9601605 | AX12: 3683 | AY12: =AX12/($AI12) -> 1.0556033 | AZ12: 4165 | BB12: 4143 | BC12: =BB12/($AI12) -> 1.1874463 | BD12: 3974 | BE12: =BD12/($AI12) -> 1.1390083 | BF12: 4600 | BG12: =BF12/($AI12) -> 1.3184293 | BH12: 3617 | BI12: =BH12/($AI12) -> 1.0366867 | BK12: 3983 | BL12: =BK12/($AI12) -> 1.1415878 | BM12: 3964 | BN12: =BM12/($AI12) -> 1.1361422 | BO12: 3973 | BP12: =BO12/($AI12) -> 1.1387217 | BQ12: 4033 | BR12: =BQ12/($AI12) -> 1.1559186 | BS12: 4113 | BT12: =BS12/($AI12) -> 1.1788478 | BU12: 3934 | BV12: =BU12/($AI12) -> 1.1275437 | BW12: 3743 | BX12: =BW12/($AI12) -> 1.0728002 | BY12: 3999 | BZ12: =BY12/($AI12) -> 1.1461737 | CA12: 3854 | CB12: =CA12/($AI12) -> 1.1046145 | CC12: 4219 | CD12: =CC12/($AI12) -> 1.209229 | CE12: 3977 | CF12: =CE12/($AI12) -> 1.1398682 | CG12: 4155 | CH12: =CG12/($AI12) -> 1.1908856 | CI12: 4192 | CJ12: =CI12/($AI12) -> 1.2014904 | CK12: 4325 | CL12: =CK12/($AI12) -> 1.2396102 | CM12: 4199 | CN12: =CM12/($AI12) -> 1.2034967 | CO12: 4214 | CP12: =CO12/($AI12) -> 1.2077959 | CQ12: 3978 | CR12: =CQ12/($AI12) -> 1.1401548 | CS12: 4207 | CT12: =CS12/($AI12) -> 1.2057896 | CU12: 4243 | CV12: =CU12/($AI12) -> 1.2161078 | CW12: 4067 | CX12: =CW12/($AI12) -> 1.1656635 | CY12: 4229 | DA12: 4044 | DC12: 4085 | DE12: 4121 | DG12: 4106 | DI12: 3852 | DK12: 4281
A13: 14 | B13: BW04_ZahlungsVerbindung_Freigeben | C13: =E13 -> {"dossierInstitution":p.DossierName1,"klientschaft":`${p.FamilyName1}, ${p.ManFirstName1}`,"buttonBewilligung":"Anfragen","checkStatus":"In Bearbeitung"} | E13: =F13&G13&H13&I13&J13&K13&L13&M13&N13&O13&P13&Q13&R13&S13&T13&U13&V13&W13&X13 -> {"dossierInstitution":p.DossierName1,"klientschaft":`${p.FamilyName1}, ${p.ManFirstName1}`,"buttonBewilligung":"Anfragen","checkStatus":"In Bearbeitung"} | F13: {"dossierInstitution": | G13: =G12 -> p.DossierName1 | H13: ,"klientschaft":` | I13: =I24 -> ${p.FamilyName1}, ${p.ManFirstName1} | J13: `,"buttonBewilligung":" | K13: Anfragen | L13: ","checkStatus":" | M13: In Bearbeitung | N13: "} | AI13: 1017 | AL13: 1012 | AM13: =AL13/($AI13) -> 0.99508358 | AN13: 1010 | AO13: =AN13/($AI13) -> 0.99311701 | AP13: 1013 | AQ13: =AP13/($AI13) -> 0.99606686 | AR13: 1021 | AS13: =AR13/($AI13) -> 1.0039331 | AT13: 1017 | AU13: =AT13/($AI13) -> 1 | AV13: 1012 | AW13: =AV13/($AI13) -> 0.99508358 | AX13: 1006 | AY13: =AX13/($AI13) -> 0.98918387 | AZ13: 1010 | BB13: 1011 | BC13: =BB13/($AI13) -> 0.99410029 | BD13: 1544 | BE13: =BD13/($AI13) -> 1.5181908 | BF13: 1115 | BG13: =BF13/($AI13) -> 1.0963618 | BH13: 1067 | BI13: =BH13/($AI13) -> 1.0491642 | BK13: 917 | BL13: =BK13/($AI13) -> 0.90167158 | BM13: 1533 | BN13: =BM13/($AI13) -> 1.5073746 | BO13: 1538 | BP13: =BO13/($AI13) -> 1.5122911 | BQ13: 1396 | BR13: =BQ13/($AI13) -> 1.3726647 | BS13: 900 | BT13: =BS13/($AI13) -> 0.88495575 | BU13: 914 | BV13: =BU13/($AI13) -> 0.89872173 | BW13: 1098 | BX13: =BW13/($AI13) -> 1.079646 | BY13: 941 | BZ13: =BY13/($AI13) -> 0.9252704 | CA13: 1066 | CB13: =CA13/($AI13) -> 1.0481809 | CC13: 1093 | CD13: =CC13/($AI13) -> 1.0747296 | CE13: 1629 | CF13: =CE13/($AI13) -> 1.6017699 | CG13: 952 | CH13: =CG13/($AI13) -> 0.93608653 | CI13: 1544 | CJ13: =CI13/($AI13) -> 1.5181908 | CK13: 1495 | CL13: =CK13/($AI13) -> 1.4700098 | CM13: 1464 | CN13: =CM13/($AI13) -> 1.439528 | CO13: 1522 | CP13: =CO13/($AI13) -> 1.4965585 | CQ13: 1520 | CR13: =CQ13/($AI13) -> 1.4945919 | CS13: 1481 | CT13: =CS13/($AI13) -> 1.4562439 | CU13: 1517 | CV13: =CU13/($AI13) -> 1.4916421 | CW13: 8953 | CX13: =CW13/($AI13) -> 8.8033432 | CY13: 5523 | DA13: 4299 | DC13: 5380 | DE13: 7390 | DG13: 9091 | DI13: 4703 | DK13: 7067
A14: 15 | B14: L03_LogoutAndLoginDiffAccount | C14: =E14 -> {"username":"Bern.Sachbearbeiterin@diartis.ch","password":"XXxa22?pdTA66-S@"} | E14: =F14&G14&H14&I14&J14&K14&L14&M14&N14&O14&P14&Q14&R14&S14&T14&U14&V14&W14&X14 -> {"username":"Bern.Sachbearbeiterin@diartis.ch","password":"XXxa22?pdTA66-S@"} | F14: {"username":" | G14: Bern.Sachbearbeiterin@diartis.ch | H14: ","password":" | I14: XXxa22?pdTA66-S@ | J14: "} | AI14: 12078 | AL14: 12419 | AM14: =AL14/($AI14) -> 1.0282332 | AN14: 12798 | AO14: =AN14/($AI14) -> 1.0596125 | AP14: 12935 | AQ14: =AP14/($AI14) -> 1.0709555 | AR14: 14401 | AS14: =AR14/($AI14) -> 1.1923332 | AT14: 13760 | AU14: =AT14/($AI14) -> 1.1392615 | AV14: 14182 | AW14: =AV14/($AI14) -> 1.174201 | AX14: 14251 | AY14: =AX14/($AI14) -> 1.1799139 | AZ14: 9685 | BB14: 9964 | BC14: =BB14/($AI14) -> 0.82497102 | BD14: 4009 | BE14: =BD14/($AI14) -> 0.33192582 | BF14: 4022 | BG14: =BF14/($AI14) -> 0.33300215 | BH14: 4012 | BI14: =BH14/($AI14) -> 0.3321742 | BK14: 4017 | BL14: =BK14/($AI14) -> 0.33258818 | BM14: 4020 | BN14: =BM14/($AI14) -> 0.33283656 | BO14: 11484 | BP14: =BO14/($AI14) -> 0.95081967 | BQ14: 10053 | BR14: =BQ14/($AI14) -> 0.83233979 | BS14: 11588 | BT14: =BS14/($AI14) -> 0.95943037 | BU14: 11166 | BV14: =BU14/($AI14) -> 0.92449081 | BW14: 11642 | BX14: =BW14/($AI14) -> 0.96390131 | BY14: 9693 | BZ14: =BY14/($AI14) -> 0.80253353 | CA14: 16101 | CB14: =CA14/($AI14) -> 1.3330849 | CC14: 9509 | CD14: =CC14/($AI14) -> 0.78729922 | CE14: 6931 | CF14: =CE14/($AI14) -> 0.57385329 | CG14: 6610 | CH14: =CG14/($AI14) -> 0.54727604 | CI14: 6177 | CJ14: =CI14/($AI14) -> 0.51142573 | CK14: 43627 | CL14: =CK14/($AI14) -> 3.6121047 | CM14: 32197 | CN14: =CM14/($AI14) -> 2.6657559 | CO14: 32138 | CP14: =CO14/($AI14) -> 2.660871 | CQ14: 17430 | CR14: =CQ14/($AI14) -> 1.4431197 | CS14: 27317 | CT14: =CS14/($AI14) -> 2.2617155 | CU14: 29239 | CV14: =CU14/($AI14) -> 2.4208478 | CW14: 20759 | CX14: =CW14/($AI14) -> 1.7187448 | CY14: 8304 | DA14: 8337 | DC14: 9721 | DE14: 11773 | DG14: 19902 | DI14: 12894 | DK14: 36248
A15: 17 | B15: BW04_ZahlungsVerbindung_Freigeben | C15: =E15 -> {"dossierInstitution":p.DossierName1,"klientschaft":`${p.FamilyName1}, ${p.ManFirstName1}`,"buttonBewilligung":"Bewilligen","checkStatus":"Bewilligt"} | E15: =F15&G15&H15&I15&J15&K15&L15&M15&N15&O15&P15&Q15&R15&S15&T15&U15&V15&W15&X15 -> {"dossierInstitution":p.DossierName1,"klientschaft":`${p.FamilyName1}, ${p.ManFirstName1}`,"buttonBewilligung":"Bewilligen","checkStatus":"Bewilligt"} | F15: {"dossierInstitution": | G15: ='001a'!$G$12 -> p.DossierName1 | H15: ,"klientschaft":` | I15: =I24 -> ${p.FamilyName1}, ${p.ManFirstName1} | J15: `,"buttonBewilligung":" | K15: Bewilligen | L15: ","checkStatus":" | M15: Bewilligt | N15: "} | AI15: 4790 | AL15: 5007 | AM15: =AL15/($AI15) -> 1.0453027 | AN15: 5015 | AO15: =AN15/($AI15) -> 1.0469729 | AP15: 5014 | AQ15: =AP15/($AI15) -> 1.0467641 | AR15: 5021 | AS15: =AR15/($AI15) -> 1.0482255 | AT15: 5014 | AU15: =AT15/($AI15) -> 1.0467641 | AV15: 5009 | AW15: =AV15/($AI15) -> 1.0457203 | AX15: 5004 | AY15: =AX15/($AI15) -> 1.0446764 | AZ15: 5018 | BB15: 5021 | BC15: =BB15/($AI15) -> 1.0482255 | BD15: 8626 | BE15: =BD15/($AI15) -> 1.8008351 | BF15: 8975 | BG15: =BF15/($AI15) -> 1.8736952 | BH15: 9664 | BI15: =BH15/($AI15) -> 2.0175365 | BK15: 8654 | BL15: =BK15/($AI15) -> 1.8066806 | BM15: 8903 | BN15: =BM15/($AI15) -> 1.8586639 | BO15: 10580 | BP15: =BO15/($AI15) -> 2.2087683 | BQ15: 9302 | BR15: =BQ15/($AI15) -> 1.9419624 | BS15: 9758 | BT15: =BS15/($AI15) -> 2.0371608 | BU15: 9814 | BV15: =BU15/($AI15) -> 2.0488518 | BW15: 10548 | BX15: =BW15/($AI15) -> 2.2020877 | BY15: 8948 | BZ15: =BY15/($AI15) -> 1.8680585 | CA15: 9461 | CB15: =CA15/($AI15) -> 1.9751566 | CC15: 9691 | CD15: =CC15/($AI15) -> 2.0231733 | CE15: 10751 | CF15: =CE15/($AI15) -> 2.2444676 | CG15: 9774 | CH15: =CG15/($AI15) -> 2.040501 | CI15: 10115 | CJ15: =CI15/($AI15) -> 2.111691 | CK15: 10077 | CL15: =CK15/($AI15) -> 2.1037578 | CM15: 9625 | CN15: =CM15/($AI15) -> 2.0093946 | CO15: 9869 | CP15: =CO15/($AI15) -> 2.060334 | CQ15: 8732 | CR15: =CQ15/($AI15) -> 1.8229645 | CS15: 10681 | CT15: =CS15/($AI15) -> 2.2298539 | CU15: 9851 | CV15: =CU15/($AI15) -> 2.0565762 | CW15: 9773 | CX15: =CW15/($AI15) -> 2.0402923 | CY15: 11811 | DA15: 12426 | DC15: 12341 | DE15: 12021 | DG15: 10831 | DI15: 8934 | DK15: 10584
A16: 18 | B16: L03_LogoutAndLoginDiffAccount | C16: {"username":"bern.sozialarbeiterin1a@diartis.ch","password":"SMze97-jkSJ59!F."} | E16: =F16&G16&H16&I16&J16&K16&L16&M16&N16&O16&P16&Q16&R16&S16&T16&U16&V16&W16&X16 -> {"username":"Bern.Sachbearbeiterin@diartis.ch","password":"XXxa22?pdTA66-S@"} | F16: {"username":" | G16: Bern.Sachbearbeiterin@diartis.ch | H16: ","password":" | I16: XXxa22?pdTA66-S@ | J16: "} | AI16: 12332 | AL16: 12730 | AM16: =AL16/($AI16) -> 1.0322738 | AN16: 12589 | AO16: =AN16/($AI16) -> 1.0208401 | AP16: 13286 | AQ16: =AP16/($AI16) -> 1.0773597 | AR16: 13640 | AS16: =AR16/($AI16) -> 1.1060655 | AT16: 13635 | AU16: =AT16/($AI16) -> 1.1056601 | AV16: 13688 | AW16: =AV16/($AI16) -> 1.1099578 | AX16: 26297 | AY16: =AX16/($AI16) -> 2.1324197 | AZ16: 10616 | BB16: 10362 | BC16: =BB16/($AI16) -> 0.840253 | BD16: 410 | BE16: =BD16/($AI16) -> 0.033246837 | BF16: 416 | BG16: =BF16/($AI16) -> 0.033733377 | BH16: 401 | BI16: =BH16/($AI16) -> 0.032517029 | BK16: 418 | BL16: =BK16/($AI16) -> 0.033895556 | BM16: 404 | BN16: =BM16/($AI16) -> 0.032760298 | BO16: 10163 | BP16: =BO16/($AI16) -> 0.82411612 | BQ16: 10128 | BR16: =BQ16/($AI16) -> 0.82127798 | BS16: 10432 | BT16: =BS16/($AI16) -> 0.84592929 | BU16: 10609 | BV16: =BU16/($AI16) -> 0.86028219 | BW16: 11196 | BX16: =BW16/($AI16) -> 0.90788193 | BY16: 10494 | BZ16: =BY16/($AI16) -> 0.85095686 | CA16: 8885 | CB16: =CA16/($AI16) -> 0.7204833 | CC16: 9805 | CD16: =CC16/($AI16) -> 0.79508596 | CE16: 8275 | CF16: =CE16/($AI16) -> 0.67101849 | CG16: 7229 | CH16: =CG16/($AI16) -> 0.58619851 | CI16: 5168 | CJ16: =CI16/($AI16) -> 0.41907233 | CK16: 14471 | CL16: =CK16/($AI16) -> 1.1734512 | CM16: 9363 | CN16: =CM16/($AI16) -> 0.75924424 | CO16: 9758 | CP16: =CO16/($AI16) -> 0.79127473 | CQ16: 8724 | CR16: =CQ16/($AI16) -> 0.70742783 | CS16: 9595 | CT16: =CS16/($AI16) -> 0.77805709 | CU16: 8421 | CV16: =CU16/($AI16) -> 0.68285761 | CW16: 13550 | CX16: =CW16/($AI16) -> 1.0987674 | CY16: 10640 | DA16: 7882 | DC16: 9028 | DE16: 9203 | DG16: 8945 | DI16: 14973 | DK16: 12825
A17: 20 | B17: DO11_Dossier_Search_Lupe | C17: =E17 -> {"searchDossierOrKlient":p.DossierName1,"resultType":"Dossiers"} | E17: =F17&G17&H17&I17&J17&K17&L17&M17&N17&O17&P17&Q17&R17&S17&T17&U17&V17&W17&X17 -> {"searchDossierOrKlient":p.DossierName1,"resultType":"Dossiers"} | F17: {"searchDossierOrKlient": | G17: ='001a'!$G$12 -> p.DossierName1 | H17: ,"resultType":" | I17: Dossiers | J17: "} | AI17: 5018 | AL17: 5017 | AM17: =AL17/($AI17) -> 0.99980072 | AN17: 5008 | AO17: =AN17/($AI17) -> 0.99800717 | AP17: 5007 | AQ17: =AP17/($AI17) -> 0.99780789 | AR17: 5010 | AS17: =AR17/($AI17) -> 0.99840574 | AT17: 5024 | AU17: =AT17/($AI17) -> 1.0011957 | AV17: 5005 | AW17: =AV17/($AI17) -> 0.99740933 | AX17: 5011 | AY17: =AX17/($AI17) -> 0.99860502 | AZ17: 5005 | BB17: 5022 | BC17: =BB17/($AI17) -> 1.0007971 | BD17: 8677 | BE17: =BD17/($AI17) -> 1.729175 | BF17: 10125 | BG17: =BF17/($AI17) -> 2.0177361 | BH17: 9485 | BI17: =BH17/($AI17) -> 1.8901953 | BK17: 9709 | BL17: =BK17/($AI17) -> 1.9348346 | BM17: 9970 | BN17: =BM17/($AI17) -> 1.9868473 | BO17: 9975 | BP17: =BO17/($AI17) -> 1.9878438 | BQ17: 10619 | BR17: =BQ17/($AI17) -> 2.1161817 | BS17: 9783 | BT17: =BS17/($AI17) -> 1.9495815 | BU17: 10225 | BV17: =BU17/($AI17) -> 2.0376644 | BW17: 10001 | BX17: =BW17/($AI17) -> 1.9930251 | BY17: 9332 | BZ17: =BY17/($AI17) -> 1.8597051 | CA17: 8820 | CB17: =CA17/($AI17) -> 1.7576724 | CC17: 10004 | CD17: =CC17/($AI17) -> 1.993623 | CE17: 9135 | CF17: =CE17/($AI17) -> 1.8204464 | CG17: 8970 | CH17: =CG17/($AI17) -> 1.7875648 | CI17: 9488 | CJ17: =CI17/($AI17) -> 1.8907931 | CK17: 8800 | CL17: =CK17/($AI17) -> 1.7536867 | CM17: 10321 | CN17: =CM17/($AI17) -> 2.0567955 | CO17: 9974 | CP17: =CO17/($AI17) -> 1.9876445 | CQ17: 9194 | CR17: =CQ17/($AI17) -> 1.8322041 | CS17: 9458 | CT17: =CS17/($AI17) -> 1.8848147 | CU17: 9693 | CV17: =CU17/($AI17) -> 1.9316461 | CW17: 10242 | CX17: =CW17/($AI17) -> 2.0410522 | CY17: 21509 | DA17: 11750 | DC17: 11493 | DE17: 13832 | DG17: 11881 | DI17: 8505 | DK17: 9392
A18: 21 | B18: WO32_01b_Wohnsituation_Haushalt_Wohnung_anpassen | C18: =E18 -> {"vermieter":"Graber Immobilien","wohnungsgrosse":"4 Zimmer","mietkosten":1200,"nebenkosten":100} | E18: =F18&G18&H18&I18&J18&K18&L18&M18&N18&O18&P18&Q18&R18&S18&T18&U18&V18&W18&X18 -> {"vermieter":"Graber Immobilien","wohnungsgrosse":"4 Zimmer","mietkosten":1200,"nebenkosten":100} | F18: {"vermieter":" | G18: Graber Immobilien | H18: ","wohnungsgrosse":" | I18: 4 Zimmer | J18: ","mietkosten": | K18: 1200 | L18: ,"nebenkosten": | M18: 100 | N18: } | AI18: 10549 | AL18: 10895 | AM18: =AL18/($AI18) -> 1.0327993 | AN18: 11011 | AO18: =AN18/($AI18) -> 1.0437956 | AP18: 11381 | AQ18: =AP18/($AI18) -> 1.07887 | AR18: 10897 | AS18: =AR18/($AI18) -> 1.0329889 | AT18: 11079 | AU18: =AT18/($AI18) -> 1.0502417 | AV18: 11119 | AW18: =AV18/($AI18) -> 1.0540336 | AX18: 10646 | AY18: =AX18/($AI18) -> 1.0091952 | AZ18: 2477 | BB18: 2456 | BC18: =BB18/($AI18) -> 0.23281828 | BD18: 5594 | BE18: =BD18/($AI18) -> 0.53028723 | BF18: 6235 | BG18: =BF18/($AI18) -> 0.59105128 | BH18: 5583 | BI18: =BH18/($AI18) -> 0.52924448 | BK18: 5890 | BL18: =BK18/($AI18) -> 0.55834676 | BM18: 6024 | BN18: =BM18/($AI18) -> 0.57104939 | BO18: 5965 | BP18: =BO18/($AI18) -> 0.56545644 | BQ18: 5840 | BR18: =BQ18/($AI18) -> 0.55360698 | BS18: 6394 | BT18: =BS18/($AI18) -> 0.6061238 | BU18: 6114 | BV18: =BU18/($AI18) -> 0.579581 | BW18: 6376 | BX18: =BW18/($AI18) -> 0.60441748 | BY18: 5946 | BZ18: =BY18/($AI18) -> 0.56365532 | CA18: 5882 | CB18: =CA18/($AI18) -> 0.5575884 | CC18: 5357 | CD18: =CC18/($AI18) -> 0.50782065 | CE18: 3013 | CF18: =CE18/($AI18) -> 0.28561949 | CG18: 3110 | CH18: =CG18/($AI18) -> 0.29481467 | CI18: 3362 | CJ18: =CI18/($AI18) -> 0.31870319 | CK18: 115554 | CL18: =CK18/($AI18) -> 10.954024 | CM18: 5494 | CN18: =CM18/($AI18) -> 0.52080766 | CO18: 5566 | CP18: =CO18/($AI18) -> 0.52763295 | CQ18: 5405 | CR18: =CQ18/($AI18) -> 0.51237084 | CS18: 4980 | CT18: =CS18/($AI18) -> 0.47208266 | CU18: 5271 | CV18: =CU18/($AI18) -> 0.49966821 | CW18: 6470 | CX18: =CW18/($AI18) -> 0.61332828 | CY18: 7151 | DA18: 5668 | DC18: 5046 | DE18: 5190 | DG18: 4642 | DI18: 9902 | DK18: 9977
A19: 22 | B19: WO30_Wohnsituation_Haushalt_Person_Hinzufuegen | C19: =E19 -> {"name":p.FamilyName1,"vorname":p.WomanFirstName1,"geburtsdatum":p.BirthdayAdult2,"ahvNumber":p.AHVNumber2,"personInhausltVon":"01.11.2025","inHauslt":"Übernehmen","ereignis":"Eheschliessung"} | E19: =F19&G19&H19&I19&J19&K19&L19&M19&N19&O19&P19&Q19&R19&S19&T19&U19&V19&W19&X19 -> {"name":p.FamilyName1,"vorname":p.WomanFirstName1,"geburtsdatum":p.BirthdayAdult2,"ahvNumber":p.AHVNumber2,"personInhausltVon":"01.11.2025","inHauslt":"Übernehmen","ereignis":"Eheschliessung"} | F19: {"name": | G19: =G6 -> p.FamilyName1 | H19: ,"vorname": | I19: =H64 -> p.WomanFirstName1 | J19: ,"geburtsdatum": | K19: =J64 -> p.BirthdayAdult2 | L19: ,"ahvNumber": | M19: =I64 -> p.AHVNumber2 | N19: ,"personInhausltVon":" | O19: ="01."&MONTH(TODAY())&"."&YEAR(TODAY()) -> 01.11.2025 | P19: ","inHauslt":" | Q19: Übernehmen | R19: ","ereignis":" | S19: Eheschliessung | T19: "} | AI19: 2974 | AL19: 3318 | AM19: =AL19/($AI19) -> 1.1156691 | AN19: 5657 | AO19: =AN19/($AI19) -> 1.902152 | AP19: 4597 | AQ19: =AP19/($AI19) -> 1.5457297 | AR19: 5547 | AS19: =AR19/($AI19) -> 1.8651648 | AT19: 5738 | AU19: =AT19/($AI19) -> 1.929388 | AV19: 5121 | AW19: =AV19/($AI19) -> 1.7219233 | AX19: 5462 | AY19: =AX19/($AI19) -> 1.8365837 | AZ19: 5249 | BB19: 5670 | BC19: =BB19/($AI19) -> 1.9065232 | BD19: 3690 | BE19: =BD19/($AI19) -> 1.2407532 | BF19: 3513 | BG19: =BF19/($AI19) -> 1.1812374 | BH19: 3054 | BI19: =BH19/($AI19) -> 1.0268998 | BK19: 4065 | BL19: =BK19/($AI19) -> 1.366846 | BM19: 4042 | BN19: =BM19/($AI19) -> 1.3591123 | BO19: 4106 | BP19: =BO19/($AI19) -> 1.3806321 | BQ19: 4024 | BR19: =BQ19/($AI19) -> 1.3530599 | BS19: 3730 | BT19: =BS19/($AI19) -> 1.2542031 | BU19: 4153 | BV19: =BU19/($AI19) -> 1.3964358 | BW19: 4360 | BX19: =BW19/($AI19) -> 1.466039 | BY19: 3948 | BZ19: =BY19/($AI19) -> 1.327505 | CA19: 3595 | CB19: =CA19/($AI19) -> 1.2088097 | CC19: 3955 | CD19: =CC19/($AI19) -> 1.3298588 | CE19: 3966 | CF19: =CE19/($AI19) -> 1.3335575 | CG19: 3555 | CH19: =CG19/($AI19) -> 1.1953598 | CI19: 2862 | CJ19: =CI19/($AI19) -> 0.96234028 | CK19: 4854 | CL19: =CK19/($AI19) -> 1.6321453 | CM19: 3422 | CN19: =CM19/($AI19) -> 1.1506389 | CO19: 3054 | CP19: =CO19/($AI19) -> 1.0268998 | CQ19: 3169 | CR19: =CQ19/($AI19) -> 1.0655683 | CS19: 3240 | CT19: =CS19/($AI19) -> 1.0894418 | CU19: 7870 | CV19: =CU19/($AI19) -> 2.6462677 | CW19: 4264 | CX19: =CW19/($AI19) -> 1.4337592 | CY19: 4418 | DA19: 3437 | DC19: 3821 | DE19: 4217 | DG19: 3452 | DI19: 4300 | DK19: 2392
A20: 23 | B20: WO30_Wohnsituation_Haushalt_Person_Hinzufuegen | C20: =E20 -> {"name":p.FamilyName1,"vorname":p.GirlFirstName1,"geburtsdatum":p.BirthdayKid1,"ahvNumber":p.AHVNumber3,"personInhausltVon":"01.11.2025","inHauslt":"Übernehmen","ereignis":"Geburt"} | E20: =F20&G20&H20&I20&J20&K20&L20&M20&N20&O20&P20&Q20&R20&S20&T20&U20&V20&W20&X20 -> {"name":p.FamilyName1,"vorname":p.GirlFirstName1,"geburtsdatum":p.BirthdayKid1,"ahvNumber":p.AHVNumber3,"personInhausltVon":"01.11.2025","inHauslt":"Übernehmen","ereignis":"Geburt"} | F20: {"name": | G20: =G19 -> p.FamilyName1 | H20: ,"vorname": | I20: =H65 -> p.GirlFirstName1 | J20: ,"geburtsdatum": | K20: =J65 -> p.BirthdayKid1 | L20: ,"ahvNumber": | M20: =I65 -> p.AHVNumber3 | N20: ,"personInhausltVon":" | O20: ="01."&MONTH(TODAY())&"."&YEAR(TODAY()) -> 01.11.2025 | P20: ","inHauslt":" | Q20: Übernehmen | R20: ","ereignis":" | S20: Geburt | T20: "} | AI20: 2228 | AL20: 2472 | AM20: =AL20/($AI20) -> 1.1095153 | AN20: 3858 | AO20: =AN20/($AI20) -> 1.7315978 | AP20: 4051 | AQ20: =AP20/($AI20) -> 1.8182226 | AR20: 5422 | AS20: =AR20/($AI20) -> 2.4335727 | AT20: 5458 | AU20: =AT20/($AI20) -> 2.4497307 | AV20: 5188 | AW20: =AV20/($AI20) -> 2.3285458 | AX20: 5482 | AY20: =AX20/($AI20) -> 2.4605027 | AZ20: 4093 | BB20: 4059 | BC20: =BB20/($AI20) -> 1.8218133 | BD20: 2309 | BE20: =BD20/($AI20) -> 1.0363555 | BF20: 2476 | BG20: =BF20/($AI20) -> 1.1113106 | BH20: 2375 | BI20: =BH20/($AI20) -> 1.0659785 | BK20: 2955 | BL20: =BK20/($AI20) -> 1.3263016 | BM20: 2440 | BN20: =BM20/($AI20) -> 1.0951526 | BO20: 2465 | BP20: =BO20/($AI20) -> 1.1063734 | BQ20: 2924 | BR20: =BQ20/($AI20) -> 1.3123878 | BS20: 2760 | BT20: =BS20/($AI20) -> 1.2387792 | BU20: 2703 | BV20: =BU20/($AI20) -> 1.2131957 | BW20: 2427 | BX20: =BW20/($AI20) -> 1.0893178 | BY20: 2623 | BZ20: =BY20/($AI20) -> 1.177289 | CA20: 2444 | CB20: =CA20/($AI20) -> 1.0969479 | CC20: 2660 | CD20: =CC20/($AI20) -> 1.1938959 | CE20: 2471 | CF20: =CE20/($AI20) -> 1.1090664 | CG20: 2297 | CH20: =CG20/($AI20) -> 1.0309695 | CI20: 2186 | CJ20: =CI20/($AI20) -> 0.98114901 | CK20: 2336 | CL20: =CK20/($AI20) -> 1.048474 | CM20: 2354 | CN20: =CM20/($AI20) -> 1.056553 | CO20: 2351 | CP20: =CO20/($AI20) -> 1.0552065 | CQ20: 2188 | CR20: =CQ20/($AI20) -> 0.98204668 | CS20: 3215 | CT20: =CS20/($AI20) -> 1.4429982 | CU20: 2269 | CV20: =CU20/($AI20) -> 1.0184022 | CW20: 1834 | CX20: =CW20/($AI20) -> 0.82315978 | CY20: 2491 | DA20: 3260 | DC20: 3227 | DE20: 3846 | DG20: 2698 | DI20: 3416 | DK20: 3639
A21: 24 | B21: WO30_Wohnsituation_Haushalt_Person_Hinzufuegen | C21: =E21 -> {"name":p.FamilyName1,"vorname":p.ManFirstName2,"geburtsdatum":p.BirthdayKid2,"ahvNumber":p.AHVNumber4,"personInhausltVon":"01.11.2025","inHauslt":"Übernehmen","ereignis":"Geburt"} | E21: =F21&G21&H21&I21&J21&K21&L21&M21&N21&O21&P21&Q21&R21&S21&T21&U21&V21&W21&X21 -> {"name":p.FamilyName1,"vorname":p.ManFirstName2,"geburtsdatum":p.BirthdayKid2,"ahvNumber":p.AHVNumber4,"personInhausltVon":"01.11.2025","inHauslt":"Übernehmen","ereignis":"Geburt"} | F21: {"name": | G21: =G20 -> p.FamilyName1 | H21: ,"vorname": | I21: =H66 -> p.ManFirstName2 | J21: ,"geburtsdatum": | K21: =J66 -> p.BirthdayKid2 | L21: ,"ahvNumber": | M21: =I66 -> p.AHVNumber4 | N21: ,"personInhausltVon":" | O21: ="01."&MONTH(TODAY())&"."&YEAR(TODAY()) -> 01.11.2025 | P21: ","inHauslt":" | Q21: Übernehmen | R21: ","ereignis":" | S21: Geburt | T21: "} | AI21: 3768 | AL21: 3446 | AM21: =AL21/($AI21) -> 0.91454352 | AN21: 4686 | AO21: =AN21/($AI21) -> 1.2436306 | AP21: 4805 | AQ21: =AP21/($AI21) -> 1.2752123 | AR21: 5276 | AS21: =AR21/($AI21) -> 1.4002123 | AT21: 5353 | AU21: =AT21/($AI21) -> 1.4206476 | AV21: 5078 | AW21: =AV21/($AI21) -> 1.3476645 | AX21: 5490 | AY21: =AX21/($AI21) -> 1.4570064 | AZ21: 4861 | BB21: 4786 | BC21: =BB21/($AI21) -> 1.2701699 | BD21: 3176 | BE21: =BD21/($AI21) -> 0.84288747 | BF21: 2698 | BG21: =BF21/($AI21) -> 0.71602972 | BH21: 3130 | BI21: =BH21/($AI21) -> 0.83067941 | BK21: 3416 | BL21: =BK21/($AI21) -> 0.90658174 | BM21: 3782 | BN21: =BM21/($AI21) -> 1.0037155 | BO21: 3406 | BP21: =BO21/($AI21) -> 0.90392781 | BQ21: 3395 | BR21: =BQ21/($AI21) -> 0.90100849 | BS21: 3792 | BT21: =BS21/($AI21) -> 1.0063694 | BU21: 3454 | BV21: =BU21/($AI21) -> 0.91666667 | BW21: 2956 | BX21: =BW21/($AI21) -> 0.78450106 | BY21: 3073 | BZ21: =BY21/($AI21) -> 0.81555202 | CA21: 3289 | CB21: =CA21/($AI21) -> 0.87287686 | CC21: 2978 | CD21: =CC21/($AI21) -> 0.7903397 | CE21: 3031 | CF21: =CE21/($AI21) -> 0.80440552 | CG21: 3312 | CH21: =CG21/($AI21) -> 0.87898089 | CI21: 3241 | CJ21: =CI21/($AI21) -> 0.860138 | CK21: 6528 | CL21: =CK21/($AI21) -> 1.7324841 | CM21: 3389 | CN21: =CM21/($AI21) -> 0.89941614 | CO21: 3310 | CP21: =CO21/($AI21) -> 0.87845011 | CQ21: 3745 | CR21: =CQ21/($AI21) -> 0.99389597 | CS21: 8095 | CT21: =CS21/($AI21) -> 2.1483546 | CU21: 3351 | CV21: =CU21/($AI21) -> 0.88933121 | CW21: 3878 | CX21: =CW21/($AI21) -> 1.0291932 | CY21: 3723 | DA21: 3462 | DC21: 3841 | DE21: 3482 | DG21: 2962 | DI21: 3061 | DK21: 2656
A22: 20 | B22: DO11_Dossier_Search_Lupe | C22: =E22 -> {"searchDossierOrKlient":p.DossierName1,"resultType":"Dossiers"} | E22: =F22&G22&H22&I22&J22&K22&L22&M22&N22&O22&P22&Q22&R22&S22&T22&U22&V22&W22&X22 -> {"searchDossierOrKlient":p.DossierName1,"resultType":"Dossiers"} | F22: {"searchDossierOrKlient": | G22: ='001a'!$G$12 -> p.DossierName1 | H22: ,"resultType":" | I22: Dossiers | J22: "} | AI22: 5018 | AL22: 5017 | AM22: =AL22/($AI22) -> 0.99980072 | AN22: 5008 | AO22: =AN22/($AI22) -> 0.99800717 | AP22: 5007 | AQ22: =AP22/($AI22) -> 0.99780789 | AR22: 5223 | AS22: =AR22/($AI22) -> 1.0408529 | AT22: 5240 | AU22: =AT22/($AI22) -> 1.0442407 | AV22: 5055 | AW22: =AV22/($AI22) -> 1.0073735 | AX22: 5244 | AY22: =AX22/($AI22) -> 1.0450379 | AZ22: 4446 | BB22: 4534 | BC22: =BB22/($AI22) -> 0.90354723 | BD22: 2459 | BE22: =BD22/($AI22) -> 0.49003587 | BF22: 2627 | BG22: =BF22/($AI22) -> 0.52351534 | BH22: 2748 | BI22: =BH22/($AI22) -> 0.54762854 | BK22: 2980 | BL22: =BK22/($AI22) -> 0.5938621 | BM22: 8189 | BN22: =BM22/($AI22) -> 1.6319251 | BO22: 2925 | BP22: =BO22/($AI22) -> 0.58290155 | BQ22: 2789 | BR22: =BQ22/($AI22) -> 0.55579912 | BS22: 2861 | BT22: =BS22/($AI22) -> 0.57014747 | BU22: 2881 | BV22: =BU22/($AI22) -> 0.57413312 | BW22: 2922 | BX22: =BW22/($AI22) -> 0.58230371 | BY22: 2740 | BZ22: =BY22/($AI22) -> 0.54603428 | CA22: 3240 | CB22: =CA22/($AI22) -> 0.64567557 | CC22: 2640 | CD22: =CC22/($AI22) -> 0.52610602 | CE22: 3066 | CF22: =CE22/($AI22) -> 0.6110004 | CG22: 2531 | CH22: =CG22/($AI22) -> 0.50438422 | CI22: 2500 | CJ22: =CI22/($AI22) -> 0.49820646 | CK22: 3370 | CL22: =CK22/($AI22) -> 0.6715823 | CM22: 3339 | CN22: =CM22/($AI22) -> 0.66540454 | CO22: 3747 | CP22: =CO22/($AI22) -> 0.74671184 | CQ22: 4278 | CR22: =CQ22/($AI22) -> 0.85253089 | CS22: 3727 | CT22: =CS22/($AI22) -> 0.74272619 | CU22: 3740 | CV22: =CU22/($AI22) -> 0.74531686 | CW22: 3853 | CX22: =CW22/($AI22) -> 0.76783579 | CY22: 3583 | DA22: 2761 | DC22: 2974 | DE22: 2892 | DG22: 2781 | DI22: 2831 | DK22: 2527
B23: WO32_01b_Wohnsituation_Haushalt_Wohnung_anpassen | C23: =E23 -> {"vermieter":"Graber Immobilien","wohnungsgrosse":"4 Zimmer","mietkosten":3000,"nebenkosten":300} | E23: =F23&G23&H23&I23&J23&K23&L23&M23&N23&O23&P23&Q23&R23&S23&T23&U23&V23&W23&X23 -> {"vermieter":"Graber Immobilien","wohnungsgrosse":"4 Zimmer","mietkosten":3000,"nebenkosten":300} | F23: {"vermieter":" | G23: Graber Immobilien | H23: ","wohnungsgrosse":" | I23: 4 Zimmer | J23: ","mietkosten": | K23: 3000 | L23: ,"nebenkosten": | M23: 300 | N23: } | AI23: 2656 | AL23: 2912 | AM23: =AL23/($AI23) -> 1.0963855 | AN23: 4161 | AO23: =AN23/($AI23) -> 1.5666416 | AP23: 4394 | AQ23: =AP23/($AI23) -> 1.6543675 | AR23: 11040 | AS23: =AR23/($AI23) -> 4.1566265 | AT23: 11254 | AU23: =AT23/($AI23) -> 4.2371988 | AV23: 11193 | AW23: =AV23/($AI23) -> 4.2142319 | AX23: 10765 | AY23: =AX23/($AI23) -> 4.0530873 | AZ23: 3743 | BB23: 3727 | BC23: =BB23/($AI23) -> 1.403238 | BD23: 5066 | BE23: =BD23/($AI23) -> 1.9073795 | BF23: 5061 | BG23: =BF23/($AI23) -> 1.905497 | BH23: 4955 | BI23: =BH23/($AI23) -> 1.8655873 | BK23: 5193 | BL23: =BK23/($AI23) -> 1.9551958 | BM23: 6491 | BN23: =BM23/($AI23) -> 2.4439006 | BO23: 5502 | BP23: =BO23/($AI23) -> 2.0715361 | BQ23: 5250 | BR23: =BQ23/($AI23) -> 1.9766566 | BS23: 5454 | BT23: =BS23/($AI23) -> 2.0534639 | BU23: 5295 | BV23: =BU23/($AI23) -> 1.9935994 | BW23: 5422 | BX23: =BW23/($AI23) -> 2.0414157 | BY23: 5319 | BZ23: =BY23/($AI23) -> 2.0026355 | CA23: 5434 | CB23: =CA23/($AI23) -> 2.0459337 | CC23: 4937 | CD23: =CC23/($AI23) -> 1.8588102 | CE23: 2683 | CF23: =CE23/($AI23) -> 1.0101657 | CG23: 2278 | CH23: =CG23/($AI23) -> 0.85768072 | CI23: 2737 | CJ23: =CI23/($AI23) -> 1.030497 | CK23: 5151 | CL23: =CK23/($AI23) -> 1.9393825 | CM23: 5060 | CN23: =CM23/($AI23) -> 1.9051205 | CO23: 5018 | CP23: =CO23/($AI23) -> 1.8893072 | CQ23: 5676 | CR23: =CQ23/($AI23) -> 2.1370482 | CS23: 5499 | CT23: =CS23/($AI23) -> 2.0704066 | CU23: 5544 | CV23: =CU23/($AI23) -> 2.0873494 | CW23: 5403 | CX23: =CW23/($AI23) -> 2.034262 | CY23: 5391
A24: 27 | B24: KL01_Klientschaft_select | C24: =E24 -> {"dossier":p.DossierName1,"klientschaft":`${p.FamilyName1}, ${p.ManFirstName1}`} | E24: =F24&G24&H24&I24&J24&K24&L24&M24&N24&O24&P24&Q24&R24&S24&T24&U24&V24&W24&X24 -> {"dossier":p.DossierName1,"klientschaft":`${p.FamilyName1}, ${p.ManFirstName1}`} | F24: {"dossier": | G24: =G12 -> p.DossierName1 | H24: ,"klientschaft":` | I24: ="${"&$G$5&"}, ${"&$I$5&"}" -> ${p.FamilyName1}, ${p.ManFirstName1} | J24: `} | AI24: 9006 | AL24: 9017 | AM24: =AL24/($AI24) -> 1.0012214 | AN24: 9018 | AO24: =AN24/($AI24) -> 1.0013324 | AP24: 9010 | AQ24: =AP24/($AI24) -> 1.0004441 | AR24: 5023 | AS24: =AR24/($AI24) -> 0.55773928 | AT24: 5019 | AU24: =AT24/($AI24) -> 0.55729514 | AV24: 5007 | AW24: =AV24/($AI24) -> 0.55596269 | AX24: 5020 | AY24: =AX24/($AI24) -> 0.55740617 | AZ24: 5005 | BB24: 5019 | BC24: =BB24/($AI24) -> 0.55729514 | BD24: 2737 | BE24: =BD24/($AI24) -> 0.30390851 | BF24: 2842 | BG24: =BF24/($AI24) -> 0.3155674 | BH24: 2719 | BI24: =BH24/($AI24) -> 0.30190984 | BK24: 2814 | BL24: =BK24/($AI24) -> 0.31245836 | BM24: 3135 | BN24: =BM24/($AI24) -> 0.34810127 | BO24: 2783 | BP24: =BO24/($AI24) -> 0.30901621 | BQ24: 2661 | BR24: =BQ24/($AI24) -> 0.29546969 | BS24: 2900 | BT24: =BS24/($AI24) -> 0.32200755 | BU24: 2926 | BV24: =BU24/($AI24) -> 0.32489451 | BW24: 2996 | BX24: =BW24/($AI24) -> 0.33266711 | BY24: 2749 | BZ24: =BY24/($AI24) -> 0.30524095 | CA24: 2685 | CB24: =CA24/($AI24) -> 0.29813458 | CC24: 2806 | CD24: =CC24/($AI24) -> 0.31157006 | CE24: 2927 | CF24: =CE24/($AI24) -> 0.32500555 | CG24: 2561 | CH24: =CG24/($AI24) -> 0.28436598 | CI24: 2736 | CJ24: =CI24/($AI24) -> 0.30379747 | CK24: 2636 | CL24: =CK24/($AI24) -> 0.29269376 | CM24: 3184 | CN24: =CM24/($AI24) -> 0.35354208 | CO24: 2566 | CP24: =CO24/($AI24) -> 0.28492116 | CQ24: 2392 | CR24: =CQ24/($AI24) -> 0.26560071 | CS24: 3157 | CT24: =CS24/($AI24) -> 0.35054408 | CU24: 3228 | CV24: =CU24/($AI24) -> 0.35842771 | CW24: 2712 | CX24: =CW24/($AI24) -> 0.30113258 | CY24: 2847 | DA24: 5812 | DC24: 5510 | DE24: 4776 | DG24: 4469 | DI24: 5090 | DK24: 4738
B25: E01_Delay | C25: {"Pause":"6000"} | AI25: 2011 | AL25: 2008 | AM25: =AL25/($AI25) -> 0.9985082 | AN25: 2011 | AO25: =AN25/($AI25) -> 1 | AQ25: =AP25/($AI25) -> 0 | AR25: 2013 | AS25: =AR25/($AI25) -> 1.0009945 | AT25: 2020 | AU25: =AT25/($AI25) -> 1.0044754 | AV25: 2017 | AW25: =AV25/($AI25) -> 1.0029836 | AX25: 2019 | AY25: =AX25/($AI25) -> 1.0039781 | AZ25: 2013 | BB25: 341 | BC25: =BB25/($AI25) -> 0.16956738 | BD25: 2007 | BE25: =BD25/($AI25) -> 0.99801094 | BF25: 2003 | BG25: =BF25/($AI25) -> 0.99602188 | BH25: 2009 | BI25: =BH25/($AI25) -> 0.99900547 | BK25: 2019 | BL25: =BK25/($AI25) -> 1.0039781 | BM25: 2008 | BN25: =BM25/($AI25) -> 0.9985082 | BO25: 2005 | BP25: =BO25/($AI25) -> 0.99701641 | BQ25: 2012 | BR25: =BQ25/($AI25) -> 1.0004973 | BS25: 2004 | BT25: =BS25/($AI25) -> 0.99651914 | BU25: 2005 | BV25: =BU25/($AI25) -> 0.99701641 | BW25: 2013 | BX25: =BW25/($AI25) -> 1.0009945 | BY25: 2013 | BZ25: =BY25/($AI25) -> 1.0009945 | CA25: 2006 | CB25: =CA25/($AI25) -> 0.99751367 | CC25: 2006 | CD25: =CC25/($AI25) -> 0.99751367 | CE25: 2015 | CF25: =CE25/($AI25) -> 1.0019891 | CG25: 2010 | CH25: =CG25/($AI25) -> 0.99950273 | CI25: 2012 | CJ25: =CI25/($AI25) -> 1.0004973 | CK25: 2005 | CL25: =CK25/($AI25) -> 0.99701641 | CN25: =CM25/($AI25) -> 0 | CO25: 4190 | CP25: =CO25/($AI25) -> 2.0835405 | CQ25: 4228 | CR25: =CQ25/($AI25) -> 2.1024366 | CS25: 4085 | CT25: =CS25/($AI25) -> 2.0313277 | CU25: 4191 | CV25: =CU25/($AI25) -> 2.0840378 | CW25: 4489 | CX25: =CW25/($AI25) -> 2.2322228 | CY25: 5077
A26: 24 | B26: KL03_ErwerbsituationEinnahmen_Lohn_erfassen | C26: =E26 -> {"zahlbarDurch":"BKW Energie AG","pensumm":"100","betrag":"1000","gueltigVon":"01.01.2025","gueltigBis":"31.12.2025","checkbox":"x"} | E26: =F26&G26&H26&I26&J26&K26&L26&M26&N26&O26&P26&Q26&R26&S26&T26&U26&V26&W26&X26 -> {"zahlbarDurch":"BKW Energie AG","pensumm":"100","betrag":"1000","gueltigVon":"01.01.2025","gueltigBis":"31.12.2025","checkbox":"x"} | F26: { | H26: "zahlbarDurch":" | I26: BKW Energie AG | J26: ","pensumm":" | K26: 100 | L26: ","betrag":" | M26: 1000 | N26: ","gueltigVon":" | O26: ="01.01."&YEAR(TODAY()) -> 01.01.2025 | P26: ","gueltigBis":" | Q26: ="31.12."&YEAR(TODAY()) -> 31.12.2025 | R26: ","checkbox":" | S26: x | T26: "} | AI26: 10643 | AL26: 11047 | AM26: =AL26/($AI26) -> 1.0379592 | AN26: 11734 | AO26: =AN26/($AI26) -> 1.1025087 | AP26: 12167 | AQ26: =AP26/($AI26) -> 1.1431927 | AR26: 11254 | AS26: =AR26/($AI26) -> 1.0574086 | AT26: 11496 | AU26: =AT26/($AI26) -> 1.0801466 | AV26: 11443 | AW26: =AV26/($AI26) -> 1.0751668 | AX26: 11104 | AY26: =AX26/($AI26) -> 1.0433149 | AZ26: 4691 | BB26: 4695 | BC26: =BB26/($AI26) -> 0.44113502 | BD26: 4689 | BE26: =BD26/($AI26) -> 0.44057127 | BF26: 4733 | BG26: =BF26/($AI26) -> 0.44470544 | BH26: 4865 | BI26: =BH26/($AI26) -> 0.45710796 | BK26: 4977 | BL26: =BK26/($AI26) -> 0.46763131 | BM26: 5121 | BN26: =BM26/($AI26) -> 0.48116133 | BO26: 5076 | BP26: =BO26/($AI26) -> 0.4769332 | BQ26: 4962 | BR26: =BQ26/($AI26) -> 0.46622193 | BS26: 5164 | BT26: =BS26/($AI26) -> 0.48520154 | BU26: 5050 | BV26: =BU26/($AI26) -> 0.47449028 | BW26: 5029 | BX26: =BW26/($AI26) -> 0.47251715 | BY26: 5045 | BZ26: =BY26/($AI26) -> 0.47402048 | CA26: 5105 | CB26: =CA26/($AI26) -> 0.47965799 | CC26: 4650 | CD26: =CC26/($AI26) -> 0.43690689 | CE26: 2082 | CF26: =CE26/($AI26) -> 0.19562154 | CG26: 1950 | CH26: =CG26/($AI26) -> 0.18321902 | CI26: 1980 | CJ26: =CI26/($AI26) -> 0.18603777 | CK26: 5065 | CL26: =CK26/($AI26) -> 0.47589965 | CM26: 7022 | CN26: =CM26/($AI26) -> 0.65977638 | CO26: 5085 | CP26: =CO26/($AI26) -> 0.47777882 | CQ26: 5042 | CR26: =CQ26/($AI26) -> 0.47373861 | CS26: 7032 | CT26: =CS26/($AI26) -> 0.66071596 | CU26: 4971 | CV26: =CU26/($AI26) -> 0.46706756 | CW26: 4855 | CX26: =CW26/($AI26) -> 0.45616837 | CY26: 5595 | DI26: 5560 | DK26: 5051
B27: KL0X_ErwerbsituationEinnahmen_erfassen | C27: =E27 -> {"dossier":p.DossierName1,"klientschaft":`${p.FamilyName1}, ${p.ManFirstName1}`,"topMenu":"Erwerbseinkommen","subMenu":"Unselbständiges Erwerbseinkommen","zahlbarDurch":"Berner Schuldenberatung","pensumm":"30","13Ja":"x","betrag":"1500","gueltigVon":"01.01.2025","gueltigBis":"31.12.2025","schweregrad":""} | E27: =F27&G27&H27&I27&J27&K27&L27&M27&N27&O27&P27&Q27&R27&S27&T27&U27&V27&W27&X27&Y27&Z27&AA27&AB27&AC27 -> {"dossier":p.DossierName1,"klientschaft":`${p.FamilyName1}, ${p.ManFirstName1}`,"topMenu":"Erwerbseinkommen","subMenu":"Unselbständiges Erwerbseinkommen","zahlbarDurch":"Berner Schuldenberatung","pensumm":"30","13Ja":"x","betrag":"1500","gueltigVon":"01.01.2025","gueltigBis":"31.12.2025","schweregrad":""} | F27: {"dossier": | G27: =G24 -> p.DossierName1 | H27: ,"klientschaft":` | I27: =I24 -> ${p.FamilyName1}, ${p.ManFirstName1} | J27: `,"topMenu":" | K27: Erwerbseinkommen | L27: ","subMenu":" | M27: Unselbständiges Erwerbseinkommen | N27: ","zahlbarDurch":" | O27: Berner Schuldenberatung | P27: ","pensumm":" | Q27: 30 | R27: ","13Ja":" | S27: x | T27: ","betrag":" | U27: 1500 | V27: ","gueltigVon":" | W27: =O26 -> 01.01.2025 | X27: ","gueltigBis":" | Y27: ="31.12."&YEAR(TODAY()) -> 31.12.2025 | Z27: ","schweregrad":" | AB27: "}
A28: 30 | B28: DO11_Dossier_Search_Lupe | C28: =E28 -> {"searchDossierOrKlient":p.DossierName1,"resultType":"Dossiers"} | E28: =F28&G28&H28&I28&J28&K28&L28&M28&N28&O28&P28&Q28&R28&S28&T28&U28&V28&W28&X28 -> {"searchDossierOrKlient":p.DossierName1,"resultType":"Dossiers"} | F28: {"searchDossierOrKlient": | G28: ='001a'!$G$12 -> p.DossierName1 | H28: ,"resultType":" | I28: Dossiers | J28: "} | AI28: 9010 | AL28: 9011 | AM28: =AL28/($AI28) -> 1.000111 | AN28: 9018 | AO28: =AN28/($AI28) -> 1.0008879 | AP28: 9018 | AQ28: =AP28/($AI28) -> 1.0008879 | AR28: 5022 | AS28: =AR28/($AI28) -> 0.55738069 | AT28: 5012 | AU28: =AT28/($AI28) -> 0.55627081 | AV28: 5031 | AW28: =AV28/($AI28) -> 0.55837958 | AX28: 5018 | AY28: =AX28/($AI28) -> 0.55693674 | AZ28: 5020 | BB28: 5041 | BC28: =BB28/($AI28) -> 0.55948946 | BD28: 3302 | BE28: =BD28/($AI28) -> 0.36648169 | BF28: 3479 | BG28: =BF28/($AI28) -> 0.38612653 | BH28: 3266 | BI28: =BH28/($AI28) -> 0.36248613 | BK28: 4147 | BL28: =BK28/($AI28) -> 0.46026637 | BM28: 4209 | BN28: =BM28/($AI28) -> 0.46714761 | BO28: 3541 | BP28: =BO28/($AI28) -> 0.39300777 | BQ28: 3635 | BR28: =BQ28/($AI28) -> 0.40344062 | BS28: 3543 | BT28: =BS28/($AI28) -> 0.39322974 | BU28: 3571 | BV28: =BU28/($AI28) -> 0.3963374 | BW28: 3634 | BX28: =BW28/($AI28) -> 0.40332963 | BY28: 3696 | BZ28: =BY28/($AI28) -> 0.41021088 | CA28: 5331 | CB28: =CA28/($AI28) -> 0.59167592 | CC28: 4098 | CD28: =CC28/($AI28) -> 0.45482797 | CE28: 3367 | CF28: =CE28/($AI28) -> 0.37369589 | CG28: 3179 | CH28: =CG28/($AI28) -> 0.35283019 | CI28: 3291 | CJ28: =CI28/($AI28) -> 0.36526082 | CK28: 4436 | CL28: =CK28/($AI28) -> 0.49234184 | CM28: 5052 | CN28: =CM28/($AI28) -> 0.56071032 | CO28: 7170 | CP28: =CO28/($AI28) -> 0.79578246 | CQ28: 6100 | CR28: =CQ28/($AI28) -> 0.67702553 | CS28: 4629 | CT28: =CS28/($AI28) -> 0.51376249 | CU28: 3720 | CV28: =CU28/($AI28) -> 0.41287458 | CW28: 4812 | CX28: =CW28/($AI28) -> 0.53407325 | CY28: 6623 | DA28: 6895 | DC28: 6145 | DE28: 4781 | DG28: 4976 | DI28: 4257 | DK28: 3881
A29: 50 | B29: E01_Delay | C29: {"Pause":"6000"} | AI29: 2011 | AL29: 2008 | AM29: =AL29/($AI29) -> 0.9985082 | AN29: 2011 | AO29: =AN29/($AI29) -> 1 | AQ29: =AP29/($AI29) -> 0 | AR29: 2013 | AS29: =AR29/($AI29) -> 1.0009945 | AT29: 2020 | AU29: =AT29/($AI29) -> 1.0044754 | AV29: 2017 | AW29: =AV29/($AI29) -> 1.0029836 | AX29: 2019 | AY29: =AX29/($AI29) -> 1.0039781 | AZ29: 2013 | BB29: 341 | BC29: =BB29/($AI29) -> 0.16956738 | BD29: 2007 | BE29: =BD29/($AI29) -> 0.99801094 | BF29: 2003 | BG29: =BF29/($AI29) -> 0.99602188 | BH29: 2009 | BI29: =BH29/($AI29) -> 0.99900547 | BK29: 2019 | BL29: =BK29/($AI29) -> 1.0039781 | BM29: 2008 | BN29: =BM29/($AI29) -> 0.9985082 | BO29: 2005 | BP29: =BO29/($AI29) -> 0.99701641 | BQ29: 2012 | BR29: =BQ29/($AI29) -> 1.0004973 | BS29: 2004 | BT29: =BS29/($AI29) -> 0.99651914 | BU29: 2005 | BV29: =BU29/($AI29) -> 0.99701641 | BW29: 2013 | BX29: =BW29/($AI29) -> 1.0009945 | BY29: 2013 | BZ29: =BY29/($AI29) -> 1.0009945 | CA29: 2006 | CB29: =CA29/($AI29) -> 0.99751367 | CC29: 2006 | CD29: =CC29/($AI29) -> 0.99751367 | CE29: 2015 | CF29: =CE29/($AI29) -> 1.0019891 | CG29: 2010 | CH29: =CG29/($AI29) -> 0.99950273 | CI29: 2012 | CJ29: =CI29/($AI29) -> 1.0004973 | CK29: 2005 | CL29: =CK29/($AI29) -> 0.99701641 | CN29: =CM29/($AI29) -> 0 | CO29: 4190 | CP29: =CO29/($AI29) -> 2.0835405 | CQ29: 4228 | CR29: =CQ29/($AI29) -> 2.1024366 | CS29: 4085 | CT29: =CS29/($AI29) -> 2.0313277 | CU29: 4191 | CV29: =CU29/($AI29) -> 2.0840378 | CW29: 4489 | CX29: =CW29/($AI29) -> 2.2322228 | CY29: 5077 | DA29: 5624 | DC29: 5469 | DE29: 4557 | DG29: 4480 | DI29: 4870 | DK29: 4929
A30: 31 | B30: A01_AnspruchPruefung_Bedarfspruefung | C30: =E30 -> {"entscheidVom":"04.11.2025","begrundung":"Gar keine Begründung","unterstutzungab":"01.11.2025"} | E30: =F30&G30&H30&I30&J30&K30&L30&M30&N30&O30&P30&Q30&R30&S30&T30&U30&V30&W30&X30 -> {"entscheidVom":"04.11.2025","begrundung":"Gar keine Begründung","unterstutzungab":"01.11.2025"} | F30: {"entscheidVom":" | G30: =TEXT(TEXT(TODAY(),"DD")&"."&TEXT(TODAY(),"MM")&"."&TEXT(TODAY(),"YYYY"),"DD.MM.YYYY") -> 04.11.2025 | H30: ","begrundung":" | I30: Gar keine Begründung | J30: ","unterstutzungab":" | K30: ="01."&TEXT(TODAY(),"MM")&"."&TEXT(TODAY(),"YYYY") -> 01.11.2025 | L30: "} | AI30: 10495 | AL30: 10709 | AM30: =AL30/($AI30) -> 1.0203907 | AN30: 10873 | AO30: =AN30/($AI30) -> 1.0360172 | AP30: 11340 | AQ30: =AP30/($AI30) -> 1.0805145 | AR30: 10826 | AS30: =AR30/($AI30) -> 1.0315388 | AT30: 11092 | AU30: =AT30/($AI30) -> 1.0568842 | AV30: 11079 | AW30: =AV30/($AI30) -> 1.0556455 | AX30: 10608 | AY30: =AX30/($AI30) -> 1.010767 | AZ30: 2528 | BB30: 2494 | BC30: =BB30/($AI30) -> 0.23763697 | BD30: 4818 | BE30: =BD30/($AI30) -> 0.45907575 | BF30: 4986 | BG30: =BF30/($AI30) -> 0.47508337 | BH30: 4682 | BI30: =BH30/($AI30) -> 0.4461172 | BK30: 5051 | BL30: =BK30/($AI30) -> 0.4812768 | BM30: 5031 | BN30: =BM30/($AI30) -> 0.47937113 | BO30: 5232 | BP30: =BO30/($AI30) -> 0.49852311 | BQ30: 4963 | BR30: =BQ30/($AI30) -> 0.47289185 | BS30: 5160 | BT30: =BS30/($AI30) -> 0.4916627 | BU30: 5138 | BV30: =BU30/($AI30) -> 0.48956646 | BW30: 5040 | BX30: =BW30/($AI30) -> 0.48022868 | BY30: 5220 | BZ30: =BY30/($AI30) -> 0.4973797 | CA30: 5673 | CB30: =CA30/($AI30) -> 0.54054312 | CC30: 4745 | CD30: =CC30/($AI30) -> 0.45212006 | CE30: 2293 | CF30: =CE30/($AI30) -> 0.21848499 | CG30: 2166 | CH30: =CG30/($AI30) -> 0.20638399 | CI30: 2801 | CJ30: =CI30/($AI30) -> 0.26688899 | CK30: 4114 | CL30: =CK30/($AI30) -> 0.39199619 | CM30: 4135 | CN30: =CM30/($AI30) -> 0.39399714 | CO30: 14738 | CP30: =CO30/($AI30) -> 1.4042878 | CQ30: 6010 | CR30: =CQ30/($AI30) -> 0.57265364 | CS30: 6012 | CT30: =CS30/($AI30) -> 0.57284421 | CU30: 6009 | CV30: =CU30/($AI30) -> 0.57255836 | CW30: 6010 | CX30: =CW30/($AI30) -> 0.57265364 | CY30: 6006 | DA30: 6013 | DC30: 6017 | DE30: 6006 | DG30: 6014 | DI30: 6004 | DK30: 6009
A31: 50 | B31: E01_Delay | C31: {"Pause":"6000"} | AI31: 2011 | AL31: 2008 | AM31: =AL31/($AI31) -> 0.9985082 | AN31: 2011 | AO31: =AN31/($AI31) -> 1 | AQ31: =AP31/($AI31) -> 0 | AR31: 2013 | AS31: =AR31/($AI31) -> 1.0009945 | AT31: 2020 | AU31: =AT31/($AI31) -> 1.0044754 | AV31: 2017 | AW31: =AV31/($AI31) -> 1.0029836 | AX31: 2019 | AY31: =AX31/($AI31) -> 1.0039781 | AZ31: 2013 | BB31: 341 | BC31: =BB31/($AI31) -> 0.16956738 | BD31: 2007 | BE31: =BD31/($AI31) -> 0.99801094 | BF31: 2003 | BG31: =BF31/($AI31) -> 0.99602188 | BH31: 2009 | BI31: =BH31/($AI31) -> 0.99900547 | BK31: 2019 | BL31: =BK31/($AI31) -> 1.0039781 | BM31: 2008 | BN31: =BM31/($AI31) -> 0.9985082 | BO31: 2005 | BP31: =BO31/($AI31) -> 0.99701641 | BQ31: 2012 | BR31: =BQ31/($AI31) -> 1.0004973 | BS31: 2004 | BT31: =BS31/($AI31) -> 0.99651914 | BU31: 2005 | BV31: =BU31/($AI31) -> 0.99701641 | BW31: 2013 | BX31: =BW31/($AI31) -> 1.0009945 | BY31: 2013 | BZ31: =BY31/($AI31) -> 1.0009945 | CA31: 2006 | CB31: =CA31/($AI31) -> 0.99751367 | CC31: 2006 | CD31: =CC31/($AI31) -> 0.99751367 | CE31: 2015 | CF31: =CE31/($AI31) -> 1.0019891 | CG31: 2010 | CH31: =CG31/($AI31) -> 0.99950273 | CI31: 2012 | CJ31: =CI31/($AI31) -> 1.0004973 | CK31: 2005 | CL31: =CK31/($AI31) -> 0.99701641 | CN31: =CM31/($AI31) -> 0 | CO31: 3307 | CP31: =CO31/($AI31) -> 1.6444555 | CQ31: 12881 | CR31: =CQ31/($AI31) -> 6.405271 | CS31: 16955 | CT31: =CS31/($AI31) -> 8.4311288 | CU31: 17778 | CV31: =CU31/($AI31) -> 8.8403779 | CW31: 21192 | CX31: =CW31/($AI31) -> 10.538041 | CY31: 21674 | DA31: 13839 | DC31: 12390 | DE31: 15752 | DG31: 0 | DH31: Error: locator.click: Error: strict mode violation: getByRole('button', { name: /Bedarfsprüfung sichern|Enregistrer l'évaluation des besoins/i }) resolved to 2 elements: 1) <button tabindex="0" role="button" mat-flat-button="" mat-ripple-loader-uninitialized="" mat-ripple-loader-class-name="mat-mdc-button-ripple" class="primary mdc-button mdc-button--unelevated mat-mdc-unelevated-button mat-unthemed mat-mdc-button-base">…</button> aka locator('#cdk-accordion-child-0').getByRole('button', { name: 'Bedarfsprüfung sichern' }) 2) <button tabindex="0" role="button" mat-flat-button="" mat-ripple-loader-uninitialized="" mat-ripple-loader-class-name="mat-mdc-button-ripple" class="primary mdc-button mdc-button--unelevated mat-mdc-unelevated-button mat-unthemed mat-mdc-button-base">…</button> aka locator('#cdk-accordion-child-1').getByRole('button', { name: 'Bedarfsprüfung sichern' })Call log:[2m - waiting for getByRole('button', { name: /Bedarfsprüfung sichern|Enregistrer l'évaluation des besoins/i })[22m Screenshots: C:\Aventis\Aventis_Playwright-\test-results\videos\006_KeyWords_Smoketest_V2-001a-001a-Microsoft-Edge\test-failed-1.png Videos: C:\Aventis\Aventis_Playwright-\test-results\videos\006_KeyWords_Smoketest_V2-001a-001a-Microsoft-Edge\video.webm | DI31: 19532 | DK31: 13228
B32: R01_Rahmenbudget_Wohnkosten_Anpassen_V2 | C32: =E32 -> {"ubernahmeWohnkostenCFH":"100","uebernahmeWohnkostenVon":"01.11.2025","uebernahmeWohnkostenBis":"27.01.2026","uebernahemBegruendung":"Die Wohnungen sind teuer hier"} | E32: =F32&G32&H32&I32&J32&K32&L32&M32&N32&O32&P32&Q32&R32&S32&T32&U32&V32&W32&X32 -> {"ubernahmeWohnkostenCFH":"100","uebernahmeWohnkostenVon":"01.11.2025","uebernahmeWohnkostenBis":"27.01.2026","uebernahemBegruendung":"Die Wohnungen sind teuer hier"} | F32: {"ubernahmeWohnkostenCFH":" | G32: 100 | H32: ","uebernahmeWohnkostenVon":" | I32: ="01."&TEXT(TODAY(),"MM")&"."&TEXT(TODAY(),"YYYY") -> 01.11.2025 | J32: ","uebernahmeWohnkostenBis":" | K32: ="27."&TEXT(MONTH(TODAY()+180),"MM")&"."&YEAR(TODAY()+180) -> 27.01.2026 | L32: ","uebernahemBegruendung":" | M32: Die Wohnungen sind teuer hier | N32: "} | AI32: 4020 | AL32: 11003 | AM32: =AL32/($AI32) -> 2.7370647 | AN32: 11012 | AO32: =AN32/($AI32) -> 2.7393035 | AP32: 11006 | AQ32: =AP32/($AI32) -> 2.7378109 | AR32: 5009 | AS32: =AR32/($AI32) -> 1.2460199 | AT32: 5011 | AU32: =AT32/($AI32) -> 1.2465174 | AV32: 5008 | AW32: =AV32/($AI32) -> 1.2457711 | AX32: 5012 | AY32: =AX32/($AI32) -> 1.2467662 | AZ32: 5024 | BB32: 5015 | BC32: =BB32/($AI32) -> 1.2475124 | BD32: 10299 | BE32: =BD32/($AI32) -> 2.5619403 | BF32: 10599 | BG32: =BF32/($AI32) -> 2.6365672 | BH32: 10000 | BI32: =BH32/($AI32) -> 2.4875622 | BK32: 11394 | BL32: =BK32/($AI32) -> 2.8343284 | BM32: 11719 | BN32: =BM32/($AI32) -> 2.9151741 | BO32: 11299 | BP32: =BO32/($AI32) -> 2.8106965 | BQ32: 12154 | BR32: =BQ32/($AI32) -> 3.0233831 | BS32: 11838 | BT32: =BS32/($AI32) -> 2.9447761 | BU32: 12116 | BV32: =BU32/($AI32) -> 3.0139303 | BW32: 11604 | BX32: =BW32/($AI32) -> 2.8865672 | BY32: 11074 | BZ32: =BY32/($AI32) -> 2.7547264 | CA32: 11733 | CB32: =CA32/($AI32) -> 2.9186567 | CC32: 11719 | CD32: =CC32/($AI32) -> 2.9151741 | CE32: 10325 | CF32: =CE32/($AI32) -> 2.568408 | CG32: 9157 | CH32: =CG32/($AI32) -> 2.2778607 | CI32: 9700 | CJ32: =CI32/($AI32) -> 2.4129353 | CK32: 18332 | CL32: =CK32/($AI32) -> 4.560199 | CM32: 11574 | CN32: =CM32/($AI32) -> 2.8791045 | CO32: 0 | CP32: =CO32/($AI32) -> 0 | CQ32: 6015 | CR32: =CQ32/($AI32) -> 1.4962687 | CS32: 6006 | CT32: =CS32/($AI32) -> 1.4940299 | CU32: 6015 | CV32: =CU32/($AI32) -> 1.4962687 | CW32: 6003 | CX32: =CW32/($AI32) -> 1.4932836 | CY32: 6010
A33: 50 | B33: E01_Delay | C33: {"Pause":"6000"} | AI33: 2011 | AL33: 2008 | AM33: =AL33/($AI33) -> 0.9985082 | AN33: 2011 | AO33: =AN33/($AI33) -> 1 | AQ33: =AP33/($AI33) -> 0 | AR33: 2013 | AS33: =AR33/($AI33) -> 1.0009945 | AT33: 2020 | AU33: =AT33/($AI33) -> 1.0044754 | AV33: 2017 | AW33: =AV33/($AI33) -> 1.0029836 | AX33: 2019 | AY33: =AX33/($AI33) -> 1.0039781 | AZ33: 2013 | BB33: 341 | BC33: =BB33/($AI33) -> 0.16956738 | BD33: 2007 | BE33: =BD33/($AI33) -> 0.99801094 | BF33: 2003 | BG33: =BF33/($AI33) -> 0.99602188 | BH33: 2009 | BI33: =BH33/($AI33) -> 0.99900547 | BK33: 2019 | BL33: =BK33/($AI33) -> 1.0039781 | BM33: 2008 | BN33: =BM33/($AI33) -> 0.9985082 | BO33: 2005 | BP33: =BO33/($AI33) -> 0.99701641 | BQ33: 2012 | BR33: =BQ33/($AI33) -> 1.0004973 | BS33: 2004 | BT33: =BS33/($AI33) -> 0.99651914 | BU33: 2005 | BV33: =BU33/($AI33) -> 0.99701641 | BW33: 2013 | BX33: =BW33/($AI33) -> 1.0009945 | BY33: 2013 | BZ33: =BY33/($AI33) -> 1.0009945 | CA33: 2006 | CB33: =CA33/($AI33) -> 0.99751367 | CC33: 2006 | CD33: =CC33/($AI33) -> 0.99751367 | CE33: 2015 | CF33: =CE33/($AI33) -> 1.0019891 | CG33: 2010 | CH33: =CG33/($AI33) -> 0.99950273 | CI33: 2012 | CJ33: =CI33/($AI33) -> 1.0004973 | CK33: 2005 | CL33: =CK33/($AI33) -> 0.99701641 | CN33: =CM33/($AI33) -> 0 | CO33: 3307 | CP33: =CO33/($AI33) -> 1.6444555 | CQ33: 12881 | CR33: =CQ33/($AI33) -> 6.405271 | CS33: 16955 | CT33: =CS33/($AI33) -> 8.4311288 | CU33: 17778 | CV33: =CU33/($AI33) -> 8.8403779 | CW33: 3806 | CX33: =CW33/($AI33) -> 1.8925908 | CY33: 1914 | DA33: 6014 | DC33: 6014 | DE33: 6033 | DG33: 609 | DI33: 6005 | DK33: 6011
A34: 35 | B34: BW01_Bewilligungs_Workflow_LeistungsEntscheid | C34: =E34 -> {"lEvonDate":"01.11.2025","lEbisDate":"03.05.2026","checkStatus":"In Bearbeitung"} | E34: =F34&G34&H34&I34&J34&K34&L34&M34&N34&O34&P34&Q34&R34&S34&T34&U34&V34&W34&X34 -> {"lEvonDate":"01.11.2025","lEbisDate":"03.05.2026","checkStatus":"In Bearbeitung"} | F34: {"lEvonDate":" | G34: =K30 -> 01.11.2025 | H34: ","lEbisDate":" | I34: =TEXT(TEXT(TODAY()+180,"DD")&"."&TEXT(TODAY()+180,"MM")&"."&TEXT(TODAY()+180,"YYYY"),"DD.MM.YYYY") -> 03.05.2026 | J34: ","checkStatus":" | K34: In Bearbeitung | L34: "} | AI34: 1017 | AL34: 1014 | AM34: =AL34/($AI34) -> 0.99705015 | AN34: 1009 | AO34: =AN34/($AI34) -> 0.99213373 | AP34: 1008 | AQ34: =AP34/($AI34) -> 0.99115044 | AR34: 1017 | AS34: =AR34/($AI34) -> 1 | AT34: 1017 | AU34: =AT34/($AI34) -> 1 | AV34: 1026 | AW34: =AV34/($AI34) -> 1.0088496 | AX34: 1017 | AY34: =AX34/($AI34) -> 1 | AZ34: 1008 | BB34: 1010 | BC34: =BB34/($AI34) -> 0.99311701 | BD34: 1944 | BE34: =BD34/($AI34) -> 1.9115044 | BF34: 1688 | BG34: =BF34/($AI34) -> 1.6597837 | BH34: 1920 | BI34: =BH34/($AI34) -> 1.8879056 | BK34: 2307 | BL34: =BK34/($AI34) -> 2.2684366 | BM34: 14554 | BN34: =BM34/($AI34) -> 14.310718 | BO34: 3635 | BP34: =BO34/($AI34) -> 3.574238 | BQ34: 2244 | BR34: =BQ34/($AI34) -> 2.2064897 | BS34: 2073 | BT34: =BS34/($AI34) -> 2.0383481 | BU34: 2891 | BV34: =BU34/($AI34) -> 2.8426745 | BW34: 2123 | BX34: =BW34/($AI34) -> 2.0875123 | BY34: 1907 | BZ34: =BY34/($AI34) -> 1.8751229 | CA34: 2856 | CB34: =CA34/($AI34) -> 2.8082596 | CC34: 1540 | CD34: =CC34/($AI34) -> 1.5142576 | CE34: 2090 | CF34: =CE34/($AI34) -> 2.0550639 | CG34: 1762 | CH34: =CG34/($AI34) -> 1.7325467 | CI34: 3116 | CJ34: =CI34/($AI34) -> 3.0639135 | CK34: 8023 | CL34: =CK34/($AI34) -> 7.8888889 | CM34: 3465 | CN34: =CM34/($AI34) -> 3.4070796 | CO34: 196 | CP34: =CO34/($AI34) -> 0.1927237 | CQ34: 1972 | CR34: =CQ34/($AI34) -> 1.9390364 | CS34: 3836 | CT34: =CS34/($AI34) -> 3.7718781 | CU34: 6759 | CV34: =CU34/($AI34) -> 6.6460177 | CW34: 6021 | CX34: =CW34/($AI34) -> 5.920354 | CY34: 6015 | DA34: 6018 | DC34: 6010 | DE34: 6016 | DI34: 6017 | DK34: 6008
B35: L03_LogoutAndLoginDiffAccount | C35: =E35 -> {"username":"aventis-gemeinde-ma@diartis.ch","password":"#xFymiADPk7wJG/FWMz"} | E35: =F35&G35&H35&I35&J35&K35&L35&M35&N35&O35&P35&Q35&R35&S35&T35&U35&V35&W35&X35 -> {"username":"aventis-gemeinde-ma@diartis.ch","password":"#xFymiADPk7wJG/FWMz"} | F35: {"username":" | G35: aventis-gemeinde-ma@diartis.ch | H35: ","password":" | I35: #xFymiADPk7wJG/FWMz | J35: "} | AI35: 6252 | AL35: 33296 | AM35: =AL35/($AI35) -> 5.3256558 | AN35: 16126 | AO35: =AN35/($AI35) -> 2.5793346 | AP35: 16536 | AQ35: =AP35/($AI35) -> 2.6449136 | AR35: 15591 | AS35: =AR35/($AI35) -> 2.493762 | AT35: 15851 | AU35: =AT35/($AI35) -> 2.5353487 | AV35: 15658 | AW35: =AV35/($AI35) -> 2.5044786 | AX35: 15381 | AY35: =AX35/($AI35) -> 2.4601727 | AZ35: 9955 | BB35: 9081 | BC35: =BB35/($AI35) -> 1.4524952 | BD35: 3011 | BE35: =BD35/($AI35) -> 0.48160589 | BF35: 3016 | BG35: =BF35/($AI35) -> 0.48240563 | BH35: 3014 | BI35: =BH35/($AI35) -> 0.48208573 | BK35: 3016 | BL35: =BK35/($AI35) -> 0.48240563 | BM35: 3001 | BN35: =BM35/($AI35) -> 0.4800064 | BO35: 11735 | BP35: =BO35/($AI35) -> 1.8769994 | BQ35: 11939 | BR35: =BQ35/($AI35) -> 1.9096289 | BS35: 11640 | BT35: =BS35/($AI35) -> 1.8618042 | BU35: 12070 | BV35: =BU35/($AI35) -> 1.9305822 | BW35: 11865 | BX35: =BW35/($AI35) -> 1.8977927 | BY35: 11535 | BZ35: =BY35/($AI35) -> 1.8450096 | CA35: 11390 | CB35: =CA35/($AI35) -> 1.821817 | CC35: 11301 | CD35: =CC35/($AI35) -> 1.8075816 | CE35: 10988 | CF35: =CE35/($AI35) -> 1.7575176 | CG35: 11485 | CH35: =CG35/($AI35) -> 1.8370122 | CI35: 11082 | CJ35: =CI35/($AI35) -> 1.7725528 | CK35: 15056 | CL35: =CK35/($AI35) -> 2.4081894 | CM35: 0 | CN35: =CM35/($AI35) -> 0 | CP35: =CO35/($AI35) -> 0 | CR35: =CQ35/($AI35) -> 0 | CT35: =CS35/($AI35) -> 0 | CV35: =CU35/($AI35) -> 0 | CX35: =CW35/($AI35) -> 0
A36: 37 | B36: L03_LogoutAndLoginDiffAccount | C36: =E36 -> {"username":"Bern.Sachbearbeiterin@diartis.ch","password":"XXxa22?pdTA66-S@"} | E36: =F36&G36&H36&I36&J36&K36&L36&M36&N36&O36&P36&Q36&R36&S36&T36&U36&V36&W36&X36 -> {"username":"Bern.Sachbearbeiterin@diartis.ch","password":"XXxa22?pdTA66-S@"} | F36: {"username":" | G36: Bern.Sachbearbeiterin@diartis.ch | H36: ","password":" | I36: XXxa22?pdTA66-S@ | J36: "} | AI36: 3004 | AL36: 3008 | AM36: =AL36/($AI36) -> 1.0013316 | AN36: 3006 | AO36: =AN36/($AI36) -> 1.0006658 | AP36: 3006 | AQ36: =AP36/($AI36) -> 1.0006658 | AR36: 3010 | AS36: =AR36/($AI36) -> 1.0019973 | AT36: 3018 | AU36: =AT36/($AI36) -> 1.0046605 | AV36: 3006 | AW36: =AV36/($AI36) -> 1.0006658 | AX36: 3008 | AY36: =AX36/($AI36) -> 1.0013316 | AZ36: 3007 | BB36: 3008 | BC36: =BB36/($AI36) -> 1.0013316 | BD36: 9135 | BE36: =BD36/($AI36) -> 3.0409454 | BF36: 8411 | BG36: =BF36/($AI36) -> 2.7999334 | BH36: 9333 | BI36: =BH36/($AI36) -> 3.1068575 | BK36: 9239 | BL36: =BK36/($AI36) -> 3.0755659 | BM36: 9147 | BN36: =BM36/($AI36) -> 3.0449401 | BO36: 9040 | BP36: =BO36/($AI36) -> 3.0093209 | BQ36: 9123 | BR36: =BQ36/($AI36) -> 3.0369507 | BS36: 8586 | BT36: =BS36/($AI36) -> 2.8581891 | BU36: 9534 | BV36: =BU36/($AI36) -> 3.1737683 | BW36: 9301 | BX36: =BW36/($AI36) -> 3.0962051 | BY36: 8449 | BZ36: =BY36/($AI36) -> 2.8125832 | CA36: 9063 | CB36: =CA36/($AI36) -> 3.0169774 | CC36: 9298 | CD36: =CC36/($AI36) -> 3.0952064 | CE36: 8311 | CF36: =CE36/($AI36) -> 2.7666445 | CG36: 9275 | CH36: =CG36/($AI36) -> 3.0875499 | CI36: 8399 | CJ36: =CI36/($AI36) -> 2.7959387 | CK36: 10005 | CL36: =CK36/($AI36) -> 3.3305593 | CM36: 172 | CN36: =CM36/($AI36) -> 0.057256991 | CP36: =CO36/($AI36) -> 0 | CQ36: 294017 | CR36: =CQ36/($AI36) -> 97.875166 | CS36: 118678 | CT36: =CS36/($AI36) -> 39.506658 | CU36: 14585 | CV36: =CU36/($AI36) -> 4.8551931 | CW36: 10114 | CX36: =CW36/($AI36) -> 3.3668442 | CY36: 10975 | DA36: 9055 | DC36: 11049 | DE36: 9630 | DI36: 18127 | DK36: 8270
A37: 39 | B37: BW02b_Bewilligungs_Workflow_Step_V2 | C37: =E37 -> {"dossier":p.DossierName1,"buttonName":"Prüfung OK","checkStatus":"In Bearbeitung"} | E37: =F37&G37&H37&I37&J37&K37&L37&M37&N37&O37&P37&Q37&R37&S37&T37&U37&V37&W37&X37 -> {"dossier":p.DossierName1,"buttonName":"Prüfung OK","checkStatus":"In Bearbeitung"} | F37: {"dossier": | G37: ='001a'!$G$12 -> p.DossierName1 | H37: ,"buttonName":" | I37: Prüfung OK | J37: ","checkStatus":" | K37: In Bearbeitung | L37: "} | AI37: 4023 | AL37: 4008 | AM37: =AL37/($AI37) -> 0.99627144 | AN37: 4008 | AO37: =AN37/($AI37) -> 0.99627144 | AP37: 4007 | AQ37: =AP37/($AI37) -> 0.99602287 | AR37: 4006 | AS37: =AR37/($AI37) -> 0.9957743 | AT37: 4029 | AU37: =AT37/($AI37) -> 1.0014914 | AV37: 4009 | AW37: =AV37/($AI37) -> 0.99652001 | AX37: 4006 | AY37: =AX37/($AI37) -> 0.9957743 | AZ37: 4010 | BB37: 4000 | BC37: =BB37/($AI37) -> 0.99428287 | BD37: 4016 | BE37: =BD37/($AI37) -> 0.99826 | BF37: 4007 | BG37: =BF37/($AI37) -> 0.99602287 | BH37: 4008 | BI37: =BH37/($AI37) -> 0.99627144 | BK37: 4011 | BL37: =BK37/($AI37) -> 0.99701715 | BM37: 4008 | BN37: =BM37/($AI37) -> 0.99627144 | BO37: 10990 | BP37: =BO37/($AI37) -> 2.7317922 | BQ37: 10413 | BR37: =BQ37/($AI37) -> 2.5883669 | BS37: 11494 | BT37: =BS37/($AI37) -> 2.8570718 | BU37: 11609 | BV37: =BU37/($AI37) -> 2.8856575 | BW37: 10326 | BX37: =BW37/($AI37) -> 2.5667412 | BY37: 10779 | BZ37: =BY37/($AI37) -> 2.6793438 | CA37: 10140 | CB37: =CA37/($AI37) -> 2.5205071 | CC37: 10588 | CD37: =CC37/($AI37) -> 2.6318668 | CE37: 11170 | CF37: =CE37/($AI37) -> 2.7765349 | CG37: 9876 | CH37: =CG37/($AI37) -> 2.4548844 | CI37: 10803 | CJ37: =CI37/($AI37) -> 2.6853095 | CK37: 12080 | CL37: =CK37/($AI37) -> 3.0027343 | CN37: =CM37/($AI37) -> 0 | CP37: =CO37/($AI37) -> 0 | CQ37: 10252 | CR37: =CQ37/($AI37) -> 2.548347 | CS37: 8710 | CT37: =CS37/($AI37) -> 2.165051 | CU37: 8455 | CV37: =CU37/($AI37) -> 2.1016654 | CW37: 8964 | CX37: =CW37/($AI37) -> 2.2281879 | CY37: 16278 | DA37: 15438 | DC37: 10657 | DE37: 11446 | DI37: 9125 | DK37: 106980
A38: 40 | B38: L03_LogoutAndLoginDiffAccount | C38: =E38 -> {"username":"aventis-gemeinde-ma@diartis.ch","password":"#xFymiADPk7wJG/FWMz"} | E38: =F38&G38&H38&I38&J38&K38&L38&M38&N38&O38&P38&Q38&R38&S38&T38&U38&V38&W38&X38 -> {"username":"aventis-gemeinde-ma@diartis.ch","password":"#xFymiADPk7wJG/FWMz"} | F38: {"username":" | G38: aventis-gemeinde-ma@diartis.ch | H38: ","password":" | I38: #xFymiADPk7wJG/FWMz | J38: "} | AI38: 6252 | AL38: 33296 | AM38: =AL38/($AI38) -> 5.3256558 | AN38: 16126 | AO38: =AN38/($AI38) -> 2.5793346 | AP38: 16536 | AQ38: =AP38/($AI38) -> 2.6449136 | AR38: 15591 | AS38: =AR38/($AI38) -> 2.493762 | AT38: 15851 | AU38: =AT38/($AI38) -> 2.5353487 | AV38: 15658 | AW38: =AV38/($AI38) -> 2.5044786 | AX38: 15381 | AY38: =AX38/($AI38) -> 2.4601727 | AZ38: 9955 | BB38: 9081 | BC38: =BB38/($AI38) -> 1.4524952 | BD38: 7798 | BE38: =BD38/($AI38) -> 1.2472809 | BF38: 8041 | BG38: =BF38/($AI38) -> 1.2861484 | BH38: 7717 | BI38: =BH38/($AI38) -> 1.234325 | BK38: 7691 | BL38: =BK38/($AI38) -> 1.2301663 | BM38: 8688 | BN38: =BM38/($AI38) -> 1.3896353 | BO38: 8810 | BP38: =BO38/($AI38) -> 1.4091491 | BQ38: 9187 | BR38: =BQ38/($AI38) -> 1.4694498 | BS38: 8930 | BT38: =BS38/($AI38) -> 1.4283429 | BU38: 9653 | BV38: =BU38/($AI38) -> 1.5439859 | BW38: 9271 | BX38: =BW38/($AI38) -> 1.4828855 | BY38: 9605 | BZ38: =BY38/($AI38) -> 1.5363084 | CA38: 8290 | CB38: =CA38/($AI38) -> 1.3259757 | CC38: 8678 | CD38: =CC38/($AI38) -> 1.3880358 | CE38: 6401 | CF38: =CE38/($AI38) -> 1.0238324 | CG38: 5987 | CH38: =CG38/($AI38) -> 0.95761356 | CI38: 6089 | CJ38: =CI38/($AI38) -> 0.97392834 | CK38: 13086 | CL38: =CK38/($AI38) -> 2.0930902 | CN38: =CM38/($AI38) -> 0 | CP38: =CO38/($AI38) -> 0 | CQ38: 12221 | CR38: =CQ38/($AI38) -> 1.9547345 | CS38: 12586 | CT38: =CS38/($AI38) -> 2.0131158 | CU38: 7078 | CV38: =CU38/($AI38) -> 1.1321177 | CW38: 11049 | CX38: =CW38/($AI38) -> 1.7672745 | CY38: 9727 | DA38: 7582 | DC38: 6993 | DE38: 7672 | DI38: 11767 | DK38: 12094
A39: 42 | B39: BW02b_Bewilligungs_Workflow_Step_V2 | C39: =E39 -> {"dossier":p.DossierName1,"buttonName":"Bewilligen","checkStatus":"Bewilligt"} | E39: =F39&G39&H39&I39&J39&K39&L39&M39&N39&O39&P39&Q39&R39&S39&T39&U39&V39&W39&X39 -> {"dossier":p.DossierName1,"buttonName":"Bewilligen","checkStatus":"Bewilligt"} | F39: {"dossier": | G39: ='001a'!$G$12 -> p.DossierName1 | H39: ,"buttonName":" | I39: Bewilligen | J39: ","checkStatus":" | K39: Bewilligt | L39: "} | AI39: 4015 | AL39: 4015 | AM39: =AL39/($AI39) -> 1 | AN39: 4016 | AO39: =AN39/($AI39) -> 1.0002491 | AP39: 4005 | AQ39: =AP39/($AI39) -> 0.99750934 | AR39: 4029 | AS39: =AR39/($AI39) -> 1.0034869 | AT39: 4014 | AU39: =AT39/($AI39) -> 0.99975093 | AV39: 4019 | AW39: =AV39/($AI39) -> 1.0009963 | AX39: 4005 | AY39: =AX39/($AI39) -> 0.99750934 | AZ39: 4020 | BB39: 4018 | BC39: =BB39/($AI39) -> 1.0007472 | BD39: 4009 | BE39: =BD39/($AI39) -> 0.9985056 | BF39: 4010 | BG39: =BF39/($AI39) -> 0.99875467 | BH39: 4010 | BI39: =BH39/($AI39) -> 0.99875467 | BK39: 4014 | BL39: =BK39/($AI39) -> 0.99975093 | BM39: 4012 | BN39: =BM39/($AI39) -> 0.9992528 | BO39: 9980 | BP39: =BO39/($AI39) -> 2.4856787 | BQ39: 10493 | BR39: =BQ39/($AI39) -> 2.6134496 | BS39: 10367 | BT39: =BS39/($AI39) -> 2.5820672 | BU39: 10616 | BV39: =BU39/($AI39) -> 2.6440847 | BW39: 10513 | BX39: =BW39/($AI39) -> 2.6184309 | BY39: 10520 | BZ39: =BY39/($AI39) -> 2.6201743 | CA39: 10214 | CB39: =CA39/($AI39) -> 2.5439601 | CC39: 9895 | CD39: =CC39/($AI39) -> 2.4645081 | CE39: 10367 | CF39: =CE39/($AI39) -> 2.5820672 | CG39: 10142 | CH39: =CG39/($AI39) -> 2.5260274 | CI39: 10162 | CJ39: =CI39/($AI39) -> 2.5310087 | CK39: 10156 | CL39: =CK39/($AI39) -> 2.5295143 | CN39: =CM39/($AI39) -> 0 | CP39: =CO39/($AI39) -> 0 | CQ39: 9521 | CR39: =CQ39/($AI39) -> 2.3713574 | CS39: 9789 | CT39: =CS39/($AI39) -> 2.4381071 | CU39: 10266 | CV39: =CU39/($AI39) -> 2.5569116 | CW39: 10182 | CX39: =CW39/($AI39) -> 2.53599 | CY39: 15452 | DA39: 12039 | DC39: 12588 | DE39: 11736 | DI39: 9536 | DK39: 9285
A40: 43 | B40: L03_LogoutAndLoginDiffAccount | C40: =E40 -> {"username":"Bern.Sachbearbeiterin@diartis.ch","password":"XXxa22?pdTA66-S@"} | E40: =F40&G40&H40&I40&J40&K40&L40&M40&N40&O40&P40&Q40&R40&S40&T40&U40&V40&W40&X40 -> {"username":"Bern.Sachbearbeiterin@diartis.ch","password":"XXxa22?pdTA66-S@"} | F40: {"username":" | G40: Bern.Sachbearbeiterin@diartis.ch | H40: ","password":" | I40: XXxa22?pdTA66-S@ | J40: "} | AI40: 8327 | AL40: 10930 | AM40: =AL40/($AI40) -> 1.3125976 | AN40: 15882 | AO40: =AN40/($AI40) -> 1.9072895 | AP40: 16441 | AQ40: =AP40/($AI40) -> 1.9744206 | AR40: 15637 | AS40: =AR40/($AI40) -> 1.8778672 | AT40: 15783 | AU40: =AT40/($AI40) -> 1.8954005 | AV40: 15539 | AW40: =AV40/($AI40) -> 1.8660982 | AX40: 15242 | AY40: =AX40/($AI40) -> 1.8304311 | AZ40: 8439 | BB40: 8437 | BC40: =BB40/($AI40) -> 1.01321 | BD40: 7603 | BE40: =BD40/($AI40) -> 0.91305392 | BF40: 8134 | BG40: =BF40/($AI40) -> 0.97682239 | BH40: 7499 | BI40: =BH40/($AI40) -> 0.90056443 | BK40: 8307 | BL40: =BK40/($AI40) -> 0.99759817 | BM40: 8658 | BN40: =BM40/($AI40) -> 1.0397502 | BO40: 9945 | BP40: =BO40/($AI40) -> 1.1943077 | BQ40: 9323 | BR40: =BQ40/($AI40) -> 1.1196109 | BS40: 8996 | BT40: =BS40/($AI40) -> 1.0803411 | BU40: 9115 | BV40: =BU40/($AI40) -> 1.0946319 | BW40: 8727 | BX40: =BW40/($AI40) -> 1.0480365 | BY40: 8953 | BZ40: =BY40/($AI40) -> 1.0751771 | CA40: 8692 | CB40: =CA40/($AI40) -> 1.0438333 | CC40: 8467 | CD40: =CC40/($AI40) -> 1.0168128 | CE40: 5939 | CF40: =CE40/($AI40) -> 0.71322205 | CG40: 6203 | CH40: =CG40/($AI40) -> 0.74492614 | CI40: 6078 | CJ40: =CI40/($AI40) -> 0.72991474 | CK40: 10719 | CL40: =CK40/($AI40) -> 1.2872583 | CN40: =CM40/($AI40) -> 0 | CP40: =CO40/($AI40) -> 0 | CQ40: 11273 | CR40: =CQ40/($AI40) -> 1.3537889 | CS40: 9813 | CT40: =CS40/($AI40) -> 1.1784556 | CU40: 14108 | CV40: =CU40/($AI40) -> 1.6942476 | CW40: 11737 | CX40: =CW40/($AI40) -> 1.4095112 | CY40: 10053 | DA40: 8071 | DC40: 7145 | DE40: 7390 | DI40: 11451 | DK40: 14160
A41: 45 | B41: DO11_Dossier_Search_Lupe | C41: =E41 -> {"searchDossierOrKlient":p.DossierName1,"resultType":"Dossiers"} | E41: =F41&G41&H41&I41&J41&K41&L41&M41&N41&O41&P41&Q41&R41&S41&T41&U41&V41&W41&X41 -> {"searchDossierOrKlient":p.DossierName1,"resultType":"Dossiers"} | F41: {"searchDossierOrKlient": | G41: =G39 -> p.DossierName1 | H41: ,"resultType":" | I41: Dossiers | J41: "} | AI41: 1012 | AL41: 1009 | AM41: =AL41/($AI41) -> 0.99703557 | AN41: 1002 | AO41: =AN41/($AI41) -> 0.99011858 | AP41: 1008 | AQ41: =AP41/($AI41) -> 0.99604743 | AR41: 1015 | AS41: =AR41/($AI41) -> 1.0029644 | AT41: 1022 | AU41: =AT41/($AI41) -> 1.0098814 | AV41: 1014 | AW41: =AV41/($AI41) -> 1.0019763 | AX41: 1009 | AY41: =AX41/($AI41) -> 0.99703557 | AZ41: 1006 | BB41: 1009 | BC41: =BB41/($AI41) -> 0.99703557 | BD41: 1006 | BE41: =BD41/($AI41) -> 0.99407115 | BF41: 1003 | BG41: =BF41/($AI41) -> 0.99110672 | BH41: 1008 | BI41: =BH41/($AI41) -> 0.99604743 | BK41: 1009 | BL41: =BK41/($AI41) -> 0.99703557 | BM41: 1005 | BN41: =BM41/($AI41) -> 0.993083 | BO41: 10207 | BP41: =BO41/($AI41) -> 10.085968 | BQ41: 11158 | BR41: =BQ41/($AI41) -> 11.025692 | BS41: 10099 | BT41: =BS41/($AI41) -> 9.979249 | BU41: 11236 | BV41: =BU41/($AI41) -> 11.102767 | BW41: 11130 | BX41: =BW41/($AI41) -> 10.998024 | BY41: 10977 | BZ41: =BY41/($AI41) -> 10.846838 | CA41: 10374 | CB41: =CA41/($AI41) -> 10.250988 | CC41: 10941 | CD41: =CC41/($AI41) -> 10.811265 | CE41: 10477 | CF41: =CE41/($AI41) -> 10.352767 | CG41: 10518 | CH41: =CG41/($AI41) -> 10.393281 | CI41: 10465 | CJ41: =CI41/($AI41) -> 10.340909 | CK41: 11244 | CL41: =CK41/($AI41) -> 11.110672 | CN41: =CM41/($AI41) -> 0 | CP41: =CO41/($AI41) -> 0 | CQ41: 11653 | CR41: =CQ41/($AI41) -> 11.514822 | CS41: 9535 | CT41: =CS41/($AI41) -> 9.4219368 | CU41: 10393 | CV41: =CU41/($AI41) -> 10.269763 | CW41: 11436 | CX41: =CW41/($AI41) -> 11.300395 | CY41: 14854 | DA41: 12940 | DC41: 12926 | DE41: 14246 | DI41: 9573 | DK41: 10353
A42: 46 | B42: BW03b_Bewilligungs_WF_FreigabeVerwendungsPeriode | C42: =E42 -> {"verwendungPeriode":"November 2025,Dezember 2025,Januar 2026,Februar 2026,März 2026,April 2026,Mai 2026","status":"Zu bezahlen"} | E42: =F42&G42&H42&I42&J42&K42&L42&M42&N42&O42&P42&Q42&R42&S42&T42&U42&V42&W42&X42 -> {"verwendungPeriode":"November 2025,Dezember 2025,Januar 2026,Februar 2026,März 2026,April 2026,Mai 2026","status":"Zu bezahlen"} | F42: {"verwendungPeriode":" | G42: =F73&","&F74&","&F75&","&F76&","&F77&","&F78&","&F79 -> November 2025,Dezember 2025,Januar 2026,Februar 2026,März 2026,April 2026,Mai 2026 | J42: ","status":" | K42: Zu bezahlen | L42: "} | AI42: 11232 | AL42: 11618 | AM42: =AL42/($AI42) -> 1.0343661 | AN42: 11145 | AO42: =AN42/($AI42) -> 0.99225427 | AP42: 12036 | AQ42: =AP42/($AI42) -> 1.0715812 | AR42: 12488 | AS42: =AR42/($AI42) -> 1.1118234 | AT42: 12291 | AU42: =AT42/($AI42) -> 1.0942842 | AV42: 12147 | AW42: =AV42/($AI42) -> 1.0814637 | AX42: 12134 | AY42: =AX42/($AI42) -> 1.0803063 | AZ42: 4979 | BB42: 4073 | BC42: =BB42/($AI42) -> 0.36262464 | BD42: 4740 | BE42: =BD42/($AI42) -> 0.42200855 | BF42: 4889 | BG42: =BF42/($AI42) -> 0.43527422 | BH42: 5343 | BI42: =BH42/($AI42) -> 0.47569444 | BK42: 5161 | BL42: =BK42/($AI42) -> 0.45949074 | BM42: 4972 | BN42: =BM42/($AI42) -> 0.44266382 | BO42: 6113 | BP42: =BO42/($AI42) -> 0.54424858 | BQ42: 6005 | BR42: =BQ42/($AI42) -> 0.53463319 | BS42: 6078 | BT42: =BS42/($AI42) -> 0.54113248 | BU42: 6241 | BV42: =BU42/($AI42) -> 0.55564459 | BW42: 6016 | BX42: =BW42/($AI42) -> 0.53561254 | BY42: 6038 | BZ42: =BY42/($AI42) -> 0.53757123 | CA42: 6124 | CB42: =CA42/($AI42) -> 0.54522792 | CC42: 5372 | CD42: =CC42/($AI42) -> 0.47827635 | CE42: 2742 | CF42: =CE42/($AI42) -> 0.24412393 | CG42: 2939 | CH42: =CG42/($AI42) -> 0.26166311 | CI42: 3428 | CJ42: =CI42/($AI42) -> 0.30519943 | CK42: 6274 | CL42: =CK42/($AI42) -> 0.55858262 | CN42: =CM42/($AI42) -> 0 | CP42: =CO42/($AI42) -> 0 | CQ42: 5759 | CR42: =CQ42/($AI42) -> 0.51273148 | CS42: 5063 | CT42: =CS42/($AI42) -> 0.45076567 | CU42: 5347 | CV42: =CU42/($AI42) -> 0.47605057 | CW42: 9599 | CX42: =CW42/($AI42) -> 0.85461182 | CY42: 4881 | DA42: 5791 | DC42: 4813 | DE42: 5010 | DI42: 9883 | DK42: 11028
B43: WSH05_Haftung_Sozialhilfeschuld_Bearbeiten | C43: =E43 -> {"haftungsType":"Einseitige Solidarhaftung erfassen","haftungDurch":`${p.FamilyName1}, ${p.ManFirstName1}`,"haftungVon":"01.11.2025","haftungBis":"31.12.2025","haftungFuer":`${p.FamilyName1}, ${p.WomanFirstName1}`,"person1":"","person2":""} | E43: =F43&G43&H43&I43&J43&K43&L43&M43&N43&O43&P43&Q43&R43&S43&T43&U43&V43&W43&X43 -> {"haftungsType":"Einseitige Solidarhaftung erfassen","haftungDurch":`${p.FamilyName1}, ${p.ManFirstName1}`,"haftungVon":"01.11.2025","haftungBis":"31.12.2025","haftungFuer":`${p.FamilyName1}, ${p.WomanFirstName1}`,"person1":"","person2":""} | F43: {"haftungsType":" | G43: Einseitige Solidarhaftung erfassen | H43: ","haftungDurch":` | I43: =I24 -> ${p.FamilyName1}, ${p.ManFirstName1} | J43: `,"haftungVon":" | K43: ="01."&MONTH(TODAY())&"."&YEAR(TODAY()) -> 01.11.2025 | L43: ","haftungBis":" | M43: ="31.12."&YEAR(TODAY()) -> 31.12.2025 | N43: ","haftungFuer":` | O43: ="${"&$G$5&"}, ${"&$H$64&"}" -> ${p.FamilyName1}, ${p.WomanFirstName1} | P43: `,"person1":" | R43: ","person2":" | T43: "} | AI43: 6915 | AL43: 6982 | AM43: =AL43/($AI43) -> 1.0096891 | AN43: 9078 | AO43: =AN43/($AI43) -> 1.3127983 | AP43: 9444 | AQ43: =AP43/($AI43) -> 1.3657267 | AS43: =AR43/($AI43) -> 0 | AU43: =AT43/($AI43) -> 0 | AW43: =AV43/($AI43) -> 0 | AY43: =AX43/($AI43) -> 0 | BC43: =BB43/($AI43) -> 0 | BE43: =BD43/($AI43) -> 0 | BG43: =BF43/($AI43) -> 0 | BI43: =BH43/($AI43) -> 0 | BL43: =BK43/($AI43) -> 0 | BN43: =BM43/($AI43) -> 0 | BP43: =BO43/($AI43) -> 0 | BR43: =BQ43/($AI43) -> 0 | BT43: =BS43/($AI43) -> 0 | BV43: =BU43/($AI43) -> 0 | BX43: =BW43/($AI43) -> 0 | BZ43: =BY43/($AI43) -> 0 | CB43: =CA43/($AI43) -> 0 | CD43: =CC43/($AI43) -> 0 | CF43: =CE43/($AI43) -> 0 | CH43: =CG43/($AI43) -> 0 | CJ43: =CI43/($AI43) -> 0 | CL43: =CK43/($AI43) -> 0 | CN43: =CM43/($AI43) -> 0 | CP43: =CO43/($AI43) -> 0 | CR43: =CQ43/($AI43) -> 0 | CT43: =CS43/($AI43) -> 0 | CV43: =CU43/($AI43) -> 0 | CX43: =CW43/($AI43) -> 0
B44: WSH05_Haftung_Sozialhilfeschuld_Bearbeiten | C44: =E44 -> {"haftungsType":"Einzelhaftung erfassen","haftungDurch":`${p.FamilyName1}, ${p.ManFirstName1}`,"haftungVon":"01.11.2025","haftungBis":"31.12.2025","haftungFuer":`${p.FamilyName1}, ${p.GirlFirstName1}`,"person1":"","person2":""} | E44: =F44&G44&H44&I44&J44&K44&L44&M44&N44&O44&P44&Q44&R44&S44&T44&U44&V44&W44&X44 -> {"haftungsType":"Einzelhaftung erfassen","haftungDurch":`${p.FamilyName1}, ${p.ManFirstName1}`,"haftungVon":"01.11.2025","haftungBis":"31.12.2025","haftungFuer":`${p.FamilyName1}, ${p.GirlFirstName1}`,"person1":"","person2":""} | F44: {"haftungsType":" | G44: Einzelhaftung erfassen | H44: ","haftungDurch":` | I44: =I24 -> ${p.FamilyName1}, ${p.ManFirstName1} | J44: `,"haftungVon":" | K44: ="01."&MONTH(TODAY())&"."&YEAR(TODAY()) -> 01.11.2025 | L44: ","haftungBis":" | M44: ="31.12."&YEAR(TODAY()) -> 31.12.2025 | N44: ","haftungFuer":` | O44: ="${"&$G$5&"}, ${"&$H$65&"}" -> ${p.FamilyName1}, ${p.GirlFirstName1} | P44: `,"person1":" | R44: ","person2":" | T44: "} | AI44: 5252 | AL44: 5584 | AM44: =AL44/($AI44) -> 1.063214 | AN44: 7647 | AO44: =AN44/($AI44) -> 1.4560168 | AP44: 0 | AQ44: =AP44/($AI44) -> 0 | AS44: =AR44/($AI44) -> 0 | AU44: =AT44/($AI44) -> 0 | AW44: =AV44/($AI44) -> 0 | AY44: =AX44/($AI44) -> 0 | BC44: =BB44/($AI44) -> 0 | BE44: =BD44/($AI44) -> 0 | BG44: =BF44/($AI44) -> 0 | BI44: =BH44/($AI44) -> 0 | BL44: =BK44/($AI44) -> 0 | BN44: =BM44/($AI44) -> 0 | BP44: =BO44/($AI44) -> 0 | BR44: =BQ44/($AI44) -> 0 | BT44: =BS44/($AI44) -> 0 | BV44: =BU44/($AI44) -> 0 | BX44: =BW44/($AI44) -> 0 | BZ44: =BY44/($AI44) -> 0 | CB44: =CA44/($AI44) -> 0 | CD44: =CC44/($AI44) -> 0 | CF44: =CE44/($AI44) -> 0 | CH44: =CG44/($AI44) -> 0 | CJ44: =CI44/($AI44) -> 0 | CL44: =CK44/($AI44) -> 0 | CN44: =CM44/($AI44) -> 0 | CP44: =CO44/($AI44) -> 0 | CR44: =CQ44/($AI44) -> 0 | CT44: =CS44/($AI44) -> 0 | CV44: =CU44/($AI44) -> 0 | CX44: =CW44/($AI44) -> 0
